Workbook
Name ´2: 'CATEGORIAS MEDICINAS'!$B$8
Name ACARIGUA: adm!$F$2:$F$5
Name ADMIN1: [1]!Table486[NAMESTADO]
Name ADMIN1: [2]!Table48[NAMESTADO]
Name Admin1_Linked_Pcode: [3]!Admin2_1['#adm1+code]
Name ADMIN11: [2]!Table48[NAMESTADO]
Name ADMIN1NAME: [1]!Table374[NAMEESTADO]
Name ADMIN1NAME: [2]!Table37[NAMEESTADO]
Name ADMIN2: [1]!Table109[ConcateEstaMuni]
Name ADMIN2: [2]!Table10[ConcateEstaMuni]
Name Admin2_Linked_Pcode: [3]!Admin3_1['#adm2+code]
Name ADMIN2CODE: [1]!Table486[[#Headers],[PCODEMUNI]]
Name ADMIN2CODE: [2]!Table48[[#Headers],[PCODEMUNI]]
Name Admin3: [3]!Admin3_1['#adm3+name]
Name ADMIN3CODE: [1]!Table109[[#Headers],[PCODEPARROQUIA]]
Name ADMIN3CODE: [2]!Table10[[#Headers],[PCODEPARROQUIA]]
Name AEE_kit_type_T: [3]!AEE_kit_type['#kit+type]
Name Agua_Higiene_Saneamiento_WASH: 'Validación Actividades'!$C$2:$C$9
Name Alianzas: 'Validación Actividades'!$T$2
Name AMAZONAS: adm!$B$4:$B$10
Name Analgésicos_Antipiréticos_AINES: 'CATEGORIAS MEDICINAS'!$C$8:$C$25
Name Anestésicos: 'CATEGORIAS MEDICINAS'!$C$1:$C$7
Name Antialérgicos: 'CATEGORIAS MEDICINAS'!$C$26:$C$31
Name Antiamebianos_Antileishmaniasis: 'CATEGORIAS MEDICINAS'!$C$84:$C$90
Name Antiasmáticos_Antitusígenos: 'CATEGORIAS MEDICINAS'!$C$248:$C$253
Name Antibióticos_Antifúngicos_Antivirales: 'CATEGORIAS MEDICINAS'!$H$32:$H$66
Name Antidiabéticos: 'CATEGORIAS MEDICINAS'!$C$174:$C$182
Name Antidiarreico_sales_de_rehidratación_oral: 'CATEGORIAS MEDICINAS'!$H$146:$H$149
Name Antiepilécticos: 'CATEGORIAS MEDICINAS'!$C$32:$C$38
Name Antiespasmódicos: 'CATEGORIAS MEDICINAS'!$C$207:$C$213
Name Antihelmínticos_Antiparasitarios: 'CATEGORIAS MEDICINAS'!$C$39:$C$46
Name Antiinflamatorios: 'CATEGORIAS MEDICINAS'!$C$163:$C$170
Name Antimaláricos: 'CATEGORIAS MEDICINAS'!$C$91:$C$101
Name Antituberculosis: 'CATEGORIAS MEDICINAS'!$C$112:$C$118
Name ANZOATEGUI: adm!$B$12:$B$32
Name APURE: adm!$B$34:$B$40
Name ARAGUA: adm!$B$42:$B$58
Name BARCELONA: adm!$G$2:$G$15
Name BARINAS: adm!$H$2:$H$15
Name BARINAS_: adm!$B$61:$B$72
Name BARQUISIMETO: adm!$I$2:$I$11
Name BOLIVAR: adm!$B$74:$B$84
Name CABIMAS: adm!$J$2:$J$10
Name CALABOZO: adm!$K$2:$K$8
Name Cambio_Comportamiento_Bienestar_Social_CCBS: 'Validación Actividades'!$D$2:$D$6
Name Capacitaciones: 'Validación Actividades'!$V$4
Name CARABOBO: adm!$B$86:$B$99
Name CARACAS: adm!$L$2:$L$10
Name CARONI: adm!$AM$2
Name CARUPANO: adm!$M$2:$M$8
Name CIUDAD_BOLIVAR: adm!$N$2:$N$10
Name COJEDES: adm!$B$101:$B$109
Name Comedores: 'Validación Actividades'!#REF!
Name CORO: adm!$O$2:$O$8
Name CUMANA: adm!$P$2:$P$6
Name Database: #REF!
Name Database: #REF!
Name Database: #REF!
Name Database: #REF!
Name Database: #REF!

Sheet Indicaciones
C2: Actualización Julio 2020
B3: ¿Qué es un Reporte Mensual DIOCESANO?
B5: Cáritas tiene como objetivo monitorear la presencia operacional en las actividades de respuesta de las Diocesis
B7: Recuerden que el reporte es una herramienta para poner en común información de las Diocesis para poder hacer análisis de brechas de cobertura. Nuestro enfoque es de poder identificar rápidamente nuestras acciones a nivel nacional
B9: Debe reportarse los 3 últimos dias de cada mes y enviar a basededatoscaritasvenezuela@gmail.com en el titulo del correo y el nombre del archivo deben indicar el nombre de la Diocesis y mes del Reporte
B11: ¿Como llenar el Reporte Mensual de Cáritas?
B13: 1. Solo llenar las columnas en blanco, las columnas en color azul estan bloquedas.
B14: Para la comodidad del transcriptor hay columnas que se llenan solas o estan solo en formato de numeros estas nos sirven para contabilizar la información mas rápidamente, es decir, no se podran colocar numeros y letras en la misma casilla Ej. 5años, no se podra hacer la información que se solicita es solo el numero.
B16: 2. Por favor tengan cuidado con el copiar-pegar
B17: Por ejemplo si hacen un clic y arrastran sin averiguar, los números pueden cambiar para hacer una cadena de números al revés de replicarse. (ej. 101, 102, 103, etc.) con esta accion podrian elimar las formulas que estan predeterminadas, para la accion de cortar y pegar deberan seleccionar mas de una fila para que le den a opcion de arrastrar.
B19: ACTUALIZACIONES
B21: . Pestaña Resumen: es una manera rapida y visual de ver la accion del mes de cada Diocesis.
B23: a. Para la Pestaña de SALUD
... B48: SAMAN DE NIÑOS Y NIÑAS
B49: N° | C49: Numero correlativo, este numero tiene relacion con la historia que tiene el niño en la Parroquia o Diocesis
B50: TIPO DE INGRESO | C50: Lista de Validación
B51: N° Control | C51: Numero ( 0 / 10000) numero de semana que tiene el niño en el control
B52: DIOCESIS | C52: Lista de Validación
B53: ESTADO | C53: se auto-llena Lista de Validación Anidadas (depende del listado de la Diocesis)
B54: MUNICIPIO | C54: Lista de Validación Anidadas (depende del listado de Estado)
B55: PARROQUIA CIVIL / COMUNIDAD | C55: Precisar la Parroquia Civil o comunidad
B56: PARROQUIA ECLESIAL | C56: Lista de Validación Anidadas (depende del listado de Centinelas proporcionado por las Diocesis)
B57: MES | C57: Lista de Validación
B58: AÑO | C58: Lista de Validación
B59: CENTRO | C59: se auto-llena
B60: GRUPO ETNICO | C60: Colocar el nombre del grupo etnico
... B102: REFERIDO S/N | C102: Lista de Validación
B103: Observaciones
B105: EMBARAZADAS Y LACTANTES
B106: #
B107: FECHA DE MEDICIÓN | C107: DD/MM/AAAA
B108: TIPO DE INGRESO | C108: DIAGNOSTICO INICIAL
B109: NOMBRE
B110: APELLIDO
B111: FECHA NACIMIENTO | C111: DD/MM/AAAA
B112: EMBARAZADA ó LACTANTE | C112: EMBARAZADA
B113: SEMANA DE GESTACIÓN | C113: Numero ( 0 / 10000)
B114: EDAD | C114: se auto-llena
B115: EDEMA | C115: SI
B116: BRAZO (CM) | C116: Numero ( 0 / 100)
B117: PESO | C117: Numero ( 0 / 150)
B118: TALLA | C118: Numero ( 0 / 200)
B119: CLASIFICACIÓN NUTRICIONAL | C119: se auto-llena
B120: CRITERIO DE EMBARAZADA VULNERABLE | C120: MUJER AL FRENTE
B121: DIOCESIS | C121: Lista de Validación
B122: ESTADO | C122: se auto-llena
B123: MUNICIPIO | C123: Lista de Validación
B124: PARROQUIA CIVIL / COMUNIDAD
B125: PARROQUIA ECLESIAL
B126: MES | C126: Lista de Validación
B127: AÑO | C127: Lista de Validación
B128: CENTRO | C128: se auto-llena
B132: DESPARASITACIÓN
B133: Nro
B134: FECHA DE ATENCIÓN dd/mm/aaaa | C134: DD/MM/AAAA
B135: DIOCESIS | C135: Lista de Validación
B136: ESTADO | C136: se auto-llena
B137: MUNICIPIO | C137: Lista de Validación
B138: PARROQUIA
B139: COMUNIDAD
B140: NOMBRE
B141: APELLIDO
B142: FECHA DE NACIMIENTO dd/mm/aaaa | C142: DD/MM/AAAA
B143: RANGO DE EDAD | C143: Lista de Validación
B144: SEXO | C144: Lista de Validación
B145: DESPARASITADO | C145: Lista de Validación
B148: CAPACITACIONES
B149: # | C149: 1
B150: FECHA | C150: DD/MM/AAAA
B151: TEMA DE LA CAPACITACIÓN | C151: Lista de Validación
B152: TIPO DE PARTICIPANTE | C152: LISTA DE VALIDACION (Hay dos tipos de participantes VOLUNTARIOS de Caritas cuya capacitación es mas especifica de acuerdo a su servicio en la parroquia y los Participantes en general son los beneficiarios de los programas que se les realiza sensibilizacion de los temas como nutricion, salud, agua entre otros.
B153: TOTAL PARTICIPANTES CAPACITADOS | C153: se auto-llena
B154: TOTAL FEMENINO | C154: se auto-llena
B155: 0-4,9 Años | C155: Deberan reportar la cantidad de mujeres en este rango de edad que participan en el taller
B156: 5 - 17 Años | C156: Deberan reportar la cantidad de mujeres en este rango de edad que participan en el taller
B157: 18 - 49 Años | C157: Deberan reportar la cantidad de mujeres en este rango de edad que participan en el taller
B158: > 49 Años | C158: Deberan reportar la cantidad de mujeres en este rango de edad que participan en el taller
B159: TOTAL MASCULINO | C159: se auto-llena
B160: 0-4,9 Años | C160: Deberan reportar la cantidad de hombres en este rango de edad que participan en el taller
B161: 5 - 17 Años | C161: Deberan reportar la cantidad de hombres en este rango de edad que participan en el taller
... B163: > 49 Años | C163: Deberan reportar la cantidad de hombres en este rango de edad que participan en el taller
B164: DIOCESIS
B165: ESTADO
B166: MUNICIPIO
B167: PARROQUIA CIVIL / COMUNIDAD
B168: PARROQUIA ECLESIAL
B169: MES
B170: AÑO
B171: CENTRO | C171: =C164&" - "&C168 -> -
B173: OLLA COMUNITARIA
B174: # | C174: Según el gasto adminitrativo el gasto de la olla es de maximo 100 personas, si la olla pasa de los 100 beneficiarios deberá contabilizar dos (2 ) ollas para que una olla no pase de las 100 porciones entregadas.
B175: FECHA DE LA OLLA | C175: DD/MM/AAAA
B176: TOTAL N° DE BENEFICIARIOS DE LA OLLA | C176: se auto-llena
B177: TOTAL PARTICIPANTES CAPACITADOS | C177: se auto-llena
B178: TOTAL FEMENINO | C178: se auto-llena
B179: 0-4,9 Años | C179: Deberan reportar la cantidad de mujeres en este rango de edad que se benefician de la Olla
B180: 5 - 17 Años | C180: Deberan reportar la cantidad de mujeres en este rango de edad que se benefician de la Olla
B181: 18 - 49 Años | C181: Deberan reportar la cantidad de mujeres en este rango de edad que se benefician de la Olla
B182: > 49 Años | C182: Deberan reportar la cantidad de mujeres en este rango de edad que se benefician de la Olla
B183: TOTAL MASCULINO | C183: se auto-llena
...

Sheet adm
A1: ESTADO | B1: MUNICIPIO | C1: NOMBRE DE LA DIOCESIS | D1: ESTADO | E1: CODIGO DE IDENTIFICACION DE LA DIOCESIS | F1: ACARIGUA | G1: BARCELONA | H1: BARINAS | I1: BARQUISIMETO | J1: CABIMAS | K1: CALABOZO | L1: CARACAS | M1: CARUPANO | N1: CIUDAD BOLIVAR | O1: CORO | P1: CUMANA | Q1: GUASDUALITO | R1: LA GUAIRA | S1: LOS TEQUES | T1: MACHIQUES | U1: MARACAIBO | V1: MARACAY | W1: MATURIN | X1: MERIDA | Y1: PUERTO CABELLO | Z1: PUNTO FIJO | AA1: SAN FELIPE | AB1: SAN FERNANDO | AC1: TRUJILLO | AD1: VALENCIA | AE1: PUERTO_AYACUCHO | AF1: GUARENAS | AG1: EL_VIGIA | AH1: SAN_CRISTOBAL | AI1: SAN_CARLOS | AJ1: MARGARITA | AK1: EL_TIGRE | AL1: TUCUPITA | AM1: CARONI | AN1: VALLE_DE_LA_PASCUA
A2: Caracas | B2: 1. Municipio Libertador (Caracas) | C2: ACARIGUA | D2: PORTUGUESA | E2: D18AC | F2: CORAZON DE JESUS | G2: VIRGEN DE FATIMA | H2: SAN ISIDRO LABRADOR | I2: NTRA SRA DE GUADALUPE | J2: OTRO- COLOCAR EL NOMBRE EN LA PARROQUIA CIVIL | K2: NTRA SRA DE FATIMA | L2: SANTO CRISTO | M2: DIVINA MISERICORDIA | N2: SAN PABLO APOSTOL | O2: NTRA SRA DE FATIMA | P2: CRISTO RESUCITADO | Q2: NTRA SRA DEL CARMEN | R2: ESPIRITU SANTO | S2: CURIA DIOSESANA CARITAS LOS TEQUES | T2: BUEN PASTOR | U2: JESUS BUEN PASTOR | V2: SAGRADA FAMILIA | W2: SANTO DOMINGO DE GUZMAN | X2: PARROQUIA SANTO DOMINGO DE GUZMÁN. MUNICIPIO CARDENAL QUINTERO | Y2: CATEDRAL SAN JOSE | Z2: SAGRADO CORAZON DE JESUS | AA2: ESPIRITU SANTO | AB2: NTRA SRA DEL ROSARIO | AC2: MARIA AUXILIADORA | AD2: CORPUS CHRISTI | AE2: OTRO- COLOCAR EL NOMBRE EN LA PARROQUIA CIVIL | AF2: OTRO- COLOCAR EL NOMBRE EN LA PARROQUIA CIVIL | AG2: OTRO- COLOCAR EL NOMBRE EN LA PARROQUIA CIVIL | AH2: OTRO- COLOCAR EL NOMBRE EN LA PARROQUIA CIVIL | AI2: OTRO- COLOCAR EL NOMBRE EN LA PARROQUIA CIVIL | AJ2: OTRO- COLOCAR EL NOMBRE EN LA PARROQUIA CIVIL | AK2: OTRO- COLOCAR EL NOMBRE EN LA PARROQUIA CIVIL | AL2: OTRO- COLOCAR EL NOMBRE EN LA PARROQUIA CIVIL | AM2: OTRO- COLOCAR EL NOMBRE EN LA PARROQUIA CIVIL | AN2: OTRO- COLOCAR EL NOMBRE EN LA PARROQUIA CIVIL
C3: BARCELONA | D3: ANZOATEGUI | E3: D06BR | F3: SANTA BARBARA | G3: SANTISIMO SACRAMENTO | H3: DIVINO NIÑO | I3: NSTRA SRA GUADALUPE BOBARE | K3: VIRGEN DEL VALLE | L3: SAN JOSE OBRERO | M3: SAN JUAN BAUTISTA | N3: NTRA SRA DEL VALLE | O3: SAN JOSE OBRERO | P3: NTRA SRA DE FATIMA | Q3: SAN MIGUEL ARCANGEL | R3: INMACULADO CORAZON DE MARIA | S3: NTRA SRA DE LA ASUNCION | T3: CRISTO REY | U3: JESUS REDENTOR | V3: OTRO- COLOCAR EL NOMBRE EN LA PARROQUIA CIVIL | W3: SAN IGNACIO DE LOYOLA | X3: PARROQUIA SAN RAFAEL ARCÁNGEL. MUNICIPIO RANGEL | Y3: CRISTO REY | Z3: NTRA SRA DE GUADALUPE | AA3: ESPIRITU SANTO YARITAGUA | AB3: MARIA AUXILIADORA | AC3: NTRA SRA DEL CARMEN | AD3: NTRA SRA DE GUADALUPE
A4: Amazonas | B4: 1. Municipio Alto Orinoco (La Esmeralda). | C4: BARINAS | D4: BARINAS_ | E4: D03BN | F4: SANTA ELENA | G4: NTRA SRA DE COROMOTO | H4: CARITAS BARINAS | I4: SAN JUAN BOSCO | K4: SANTA ROSA DE LIMA | L4: SAN MONS ROMERO | M4: SAN MARTIN DE PORRES | N4: SANTA EDUVIGIS | O4: SANTA ANA DE CORO | P4: NTRA SRA DEL ROSARIO | Q4: SANTISIMA TRINIDAD | R4: MARIA AUXILIADORA | S4: SAGRADO CORAZON DE JESUS Y MARIA | T4: EL ROSARIO | U4: SAN JUAN BAUTISTA | W4: CRISTO RESUCITADO | X4: PARROQUIA SANTA LUCÍA: MUNICIPIO RANGEL | Y4: SAN JOSE OBRERO | Z4: SAN JOSE DE TACUATO | AA4: NTRA SRA DE LAS MERCEDES | AB4: SANTA LUCIA | AC4: SAN PEDRO | AD4: MARIA MADRE DE LA IGLESIA
B5: 2. Municipio Atabapo (San Fernando de Atabapo). | C5: BARQUISIMETO | D5: LARA | E5: D13BQ | F5: SAN FRANCISCO JAVIER | G5: CATEDRAL BARCELONA | H5: CRISTO REY | I5: SAN JUAN PABLO II | K5: NTRA SRA DE GUADALUPE | L5: LA ENCARNACIÓN DEL VALLE | M5: SAN RAFAEL ARCANGEL | N5: INMACULADA | O5: OTRO- COLOCAR EL NOMBRE EN LA PARROQUIA CIVIL | P5: NTRA SRA DE LA ESPERANZA | Q5: SAN CAMILO LELIS | R5: NTRA SEÐORA DEL CARMEN | S5: SAN DIEGO DE ALCALA ALTOS MIRANDINOS | T5: INMACULADA | U5: SANTISIMO SALVADOR | W5: SAN CARLOS BORROMEO | X5: PARROQUIA INMACULADA CONCEPCIÓN. MUNICIPIO RANGEL | Y5: SAN PIO X | Z5: OTRO- COLOCAR EL NOMBRE EN LA PARROQUIA CIVIL | AA5: NTRA SRA DEL ROSARIO DE FATIMA | AB5: SAN JOSE DEL YAGUAL | AC5: SAGRADO CORAZON DE JESUS | AD5: MARIA MADRE DEL REDENTOR
B6: 3. Municipio Atures (Puerto Ayacucho). | C6: CABIMAS | D6: ZULIA | E6: D23CB | F6: OTRO- COLOCAR EL NOMBRE EN LA PARROQUIA CIVIL | G6: CORAZON DE JESUS | H6: NTRA SRA DE LA ESPERANZA | I6: SAN NICOLAS DE BARI | K6: SAN JOSE OBRERO | L6: CASA DE LA MISERICORDIA | M6: SAN JUAN BAUTISTA YAGUARAPARO | N6: ESPIRITU SANTO | O6: SAN FRANCISCO DE ASIS | P6: OTRO- COLOCAR EL NOMBRE EN LA PARROQUIA CIVIL | Q6: OTRO- COLOCAR EL NOMBRE EN LA PARROQUIA CIVIL | R6: SAGRADO CORAZON DE JESUS | S6: SAN FRANCISCO DE PAULA | T6: SAGRADA FAMILIA | U6: NTRA SRA COROMOTO Y SAN JOSE OBRERO | W6: VIRGEN DEL VALLE | X6: PARROQUIA NTRA. SRA. DE LA MILAGROSA. MUNICIPIO LIBERTADOR | Y6: NTRA SRA DE GUADALUPE | AA6: SANTA EDUVIGIS | AB6: SANTUARIO JESUS DE NAZARENO | AC6: SAN MIGUEL | AD6: NTRA SRA DE BEGOÑA
B7: 4. Municipio Autana (Isla Ratón). | C7: CALABOZO | D7: GUARICO | E7: D12CZ | G7: NTRA SRA DE LOURDES | H7: NTRA SRA DEL ROSARIO | I7: NTRA SRA DE LAS MERCEDES | K7: SAN JUAN PABLO II | L7: SAN JOAQUIN Y SANTA ANA | M7: NTRA SRA DE COROMOTO | N7: SAN ANTONIO DE PADUA | O7: SANTO NIÑO DE JESUS | R7: SAN FRANCISCO DE ASIS | S7: SANTA LUCIA VIRGEN Y MARTIN | T7: SAN EUGENIO | U7: SAN BENITO DE PALERMO | W7: OTRO- COLOCAR EL NOMBRE EN LA PARROQUIA CIVIL | X7: PARROQUIA INMACULADO CORAZÓN DE MARÍA. MUNICIPIO LIBERTADOR | Y7: OTRO- COLOCAR EL NOMBRE EN LA PARROQUIA CIVIL | AA7: NTRA SRA DEL CARMEN | AB7: SAGRADA FAMILIA DE NAZARET | AC7: SAN AGUSTIN HIPONA | AD7: SAN JOSE DE CALASANZ
B8: 5. Municipio Manapiare (San Juan de Manapiare). | C8: CARACAS | D8: DTO_CAPITAL | E8: D01CCS | G8: NUESTRA SEÑORA DEL CARMEN | H8: SAGRADA FAMILIA | I8: SANTA CRUZ | K8: OTRO- COLOCAR EL NOMBRE EN LA PARROQUIA CIVIL | L8: SANTO DOMINGO SAVIO | M8: OTRO- COLOCAR EL NOMBRE EN LA PARROQUIA CIVIL | N8: SAN JOSE | O8: OTRO- COLOCAR EL NOMBRE EN LA PARROQUIA CIVIL | R8: SAN MARTIN DE PORRES | S8: NTRA SRA DE COROMOTO | T8: SAN JOSE | U8: SANTISIMO SACRAMENTO | X8: PARROQUIA NTRA. SRA. DEL ROSARIO. MUNICIPIO LIBERTADOR | AA8: EL NAZARENO | AB8: NTRA SRA DEL VALLE | AC8: OTRO- COLOCAR EL NOMBRE EN LA PARROQUIA CIVIL | AD8: SAN JUAN MARIA VIANNEY
B9: 6. Municipio Maroa (Maroa). | C9: CARONI | D9: BOLIVAR | E9: D07CR | G9: NTRA SRA DEL ROSARIO DE POMPEI | H9: SANTO DOMINGO DE GUZMAN | I9: SAN ANTONIO DE PADUA | L9: NTRA SRA DE LA ENCARNACION DEL VALLE | N9: JESÚS DE NAZARET | R9: SAN MIGUEL ARCANGEL | S9: NTRA SRA DEL ROSARIO | T9: CATERAL MACHIQUES | U9: SAN RAFAEL ARCANGEL | X9: PARROQUIA SAN JOSÉ OBRERO. MUNICIPIO LIBERTADOR | AA9: VICARIA SAN ISIDRO | AB9: LA MILAGROSA | AD9: LA MILAGROSA
B10: 7. Municipio Río Negro (San Carlos de Río Negro). | C10: CARUPANO | D10: SUCRE | E10: D19CP | G10: SAN CELESTINO MARTIR | H10: MEDALLA MILAGROSA | I10: NTRA SRA DEL CARMEN | L10: OTRO- COLOCAR EL NOMBRE EN LA PARROQUIA CIVIL | N10: OTRO- COLOCAR EL NOMBRE EN LA PARROQUIA CIVIL | R10: SANTISIMA TRINIDAD | S10: STA ROSA DE LIMA | T10: MISION DEL TUKUKO | U10: SAN RAMON NONATO | X10: PARROQUIA BASÍLICA SANTA LUCIA. MUNICIPIO MIRANDA | AA10: SAN GERONIMO | AB10: INMACULADA CONCEPCION | AD10: SAGRADO CORAZON DE JESUS DE AGUIRRE
C11: CIUDAD_BOLIVAR | D11: BOLIVAR | E11: D07BV | G11: DIVINA PASTORA | H11: SAN PEDRO APOSTOL | I11: OTRO- COLOCAR EL NOMBRE EN LA PARROQUIA CIVIL | R11: STO CRISTO DE LA MISERICORDIA | S11: CASA HNAS AGUSTINA | T11: SAN IGNACIO | U11: SAN MIGUEL ARCANGEL | X11: SANTUARIO SAN BUENAVENTURA. MUNICIPIO CAMPO ELÍAS | AA11: SANTA LUCIA | AB11: NTRA SRA DE GUADALUPE | AD11: SAN JUAN BAUTISTA
A12: Anzoátegui | B12: 1. Municipio Anaco (Anaco). | C12: CIUDAD GUAYANA | D12: BOLIVAR | E12: D11CR | G12: SANTA LUCIA MARTIR | H12: SAN JOSE/LA CARAMUCA | R12: NTRA SRA GUARACARUMBO | S12: SAN DIEGO ALCALA OCUMARE | T12: NTRA SRA DE CHIQUINQUIRA | U12: INMACULADA CONCEPCION DE CARRASQUERO | X12: SANTUARIO INMACULADA CONCEPCIÓN. MUNICIPIO ANDRÉS BELLO | AA12: NTRA SRA DE LA VICTORIA | AB12: OTRO- COLOCAR EL NOMBRE EN LA PARROQUIA CIVIL | AD12: NTRA SRA DEL CARMEN
B13: 2. Municipio Aragua (Aragua de Barcelona). | C13: CORO | D13: FALCON | E13: D19CN | G13: ROSA MISTICA | H13: SANTISIMA TRINIDAD | R13: SAN SEBASTIAN | S13: SAN JOSE OBRERO | T13: SAN PEDRO APOSTOL | U13: NTRA SRA DE LOURDES ISLA DE TOAS | X13: PARROQUIA NTRA. SRA. DEL CARMEN. MUNICIPIO CAMPO ELÍAS | AA13: PURISIMA CONCEPCION DE TINAJAS | AD13: SANTA EDUVIGIS
B14: 3. Municipio Bolívar (Barcelona). | C14: CUMANA | D14: SUCRE | E14: D03TG | G14: SANTA CRUZ | H14: SANTA ROSA DE LIMA/CALDERAS | R14: SAN JOSE CARAYACA | S14: SAGRADO CORAZON DE JESUS | T14: SANTISIMA TRINIDAD | U14: SAN MARTIN DE PORRES | X14: PARROQUIA SAN ANTONIO DE PADUA. MUNICIPIO LIBERTADOR | AA14: OTRO- COLOCAR EL NOMBRE EN LA PARROQUIA CIVIL | AD14: INMACULADA CONCEPCION
B15: 4. Municipio Bruzual (Clarines). | C15: EL_TIGRE | D15: ANZOATEGUI | E15: D23EV | G15: OTRO- COLOCAR EL NOMBRE EN LA PARROQUIA CIVIL | H15: SAN MARTIN DE PORRES/CAMIRI | R15: NTRA SRA DEL VALLE | S15: NTRA SRA DE LA MACARENA | T15: NTRA SRA DEL CARMEN | U15: OTRO- COLOCAR EL NOMBRE EN LA PARROQUIA CIVIL | X15: PARROQUIA NTRA. SRA. DE LA CANDELARIA. MUNICIPIO ANTONIO PINTO SALINA | AD15: OTRO- COLOCAR EL NOMBRE EN LA PARROQUIA CIVIL
B16: 5. Municipio Cajigal (Onoto). | C16: EL_VIGIA | D16: ZULIA/MÉRIDA | E16: D15GN | H16: OTRO- COLOCAR EL NOMBRE EN LA PARROQUIA CIVIL | R16: SAN JOSE OBRERO | S16: SAN PEDRO APOSTOL | T16: OTRO- COLOCAR EL NOMBRE EN LA PARROQUIA CIVIL | X16: PARROQUIA NTRA. SRA. DE FÁTIMA. MUNICIPIO TOVAR
B17: 6. Municipio Carvajal (Valle de Guanape). | C17: GUANARE | D17: MIRANDA | E17: D04GD | R17: BEATA MARIA JOSE | S17: NTRA SRA DE FATIMA | X17: PARROQUIA NTRA. SRA. DEL CARMEN. MUNICIPIO ARZOBISPO CHACÓN
B18: 7. Municipio Diego Bautista Urbaneja (Lechería). | C18: GUARENAS | D18: APURE | E18: D24LG | R18: OTRO- COLOCAR EL NOMBRE EN LA PARROQUIA CIVIL | S18: SAN MARTIN DE PORRES NUEVA CUA | X18: PARROQUIA NTRA. SRA. DE COROMOTO. MUNICIPIO LIBERTADOR
B19: 8. Municipio Freites (Cantaura). | C19: GUASDUALITO | D19: VARGAS | E19: D15TQ | S19: OTRO- COLOCAR EL NOMBRE EN LA PARROQUIA CIVIL | X19: PARROQUIA SAN ANTONIO DE PADUA. MUNICIPIO SUCRE
B20: 9. Municipio Guanipa (San José de Guanipa). | C20: LA_GUAIRA | D20: MIRANDA | E20: D23MQ | X20: PARROQUIA SAN FRANCISCO DE ASÍS. MUNICIPIO LIBERTADOR
B21: 10. Municipio Guanta (Guanta). | C21: LOS_TEQUES | D21: ZULIA | E21: D23MB | X21: OTRO- COLOCAR EL NOMBRE EN LA PARROQUIA CIVIL
B22: 11. Municipio Independencia (Soledad). | C22: MACHIQUES | D22: ZULIA | E22: D05MC
B23: 12. Municipio Libertad (San Mateo). | C23: MARACAIBO I | D23: ZULIA | E23: DMG
B24: 13. Municipio McGregor (El Chaparro). | C24: MARACAIBO II | D24: ARAGUA | E24: D16MR
B25: 14. Municipio Miranda (Pariaguán) | C25: MARACAY | D25: ESPARTA | E25: D25MR
B26: 15. Municipio Monagas (San Diego de Cabrutica) | C26: MARGARITA | D26: MONAGAS | E26: DPA
B27: 16. Municipio Peñalver (Puerto Píritu) | C27: MATURIN | D27: MERIDA_ | E27: D08PTC
B28: 17. Municipio Píritu (Píritu). | C28: MERIDA | D28: BOLIVAR | E28: D11PF
B29: 18. Municipio San Juan de Capistrano (Boca de Uchire). | C29: PUERTO_AYACUCHO | D29: CARABOBO | E29: DSC
B30: 19. Municipio Santa Ana (Santa Ana). | C30: PUERTO_CABELLO | D30: FALCON | E30: DSCC
B31: 20. Municipio Simón Rodriguez (El Tigre). | C31: PUNTO_FIJO | D31: TACHIRA | E31: D22SF
B32: 21. Municipio Sotillo (Puerto La Cruz). | C32: SAN_CRISTOBAL | D32: COJEDES | E32: D04SFA
C33: SAN_CARLOS | D33: YARACUY | E33: D21TJ
A34: Apure | B34: 1. Municipio Achaguas (Achaguas). | C34: SAN_FELIPE | D34: APURE | E34: DTUP
B35: 2. Municipio Biruaca (Biruaca). | C35: SAN_FERNANDO | D35: TRUJILLO_ | E35: D08VL
B36: 3. Municipio Muñoz (Bruzual). | C36: TRUJILLO | D36: DELTA AMACURO | E36: D12CVP
B37: 4. Municipio Páez (Guasdualito). | C37: TUCUPITA | D37: CARABOBO
B38: 5. Municipio Pedro Camejo (San Juan de Payara). | C38: VALENCIA | D38: GUARICO
B39: 6. Municipio Rómulo Gallegos (Elorza). | C39: VALLE_DE_LA_PASCUA
B40: 7. Municipio San Fernando (San Fernando de Apure).
A42: Aragua | B42: 1. Municipio Bolívar (San Mateo).
B43: 2. Municipio Camatagua(Camatagua).
B44: 3. Municipio Francisco Linares Alcántara (Santa Rita).
B45: 4. Municipio Girardot (Maracay).
B46: 5. Municipio José Ángel Lamas (Santa Cruz).
B47: 6. Municipio José Félix Ribas (La Victoria).
B48: 7. Municipio José Rafael Revenga (El Consejo).
B49: 8. Municipio Libertador (Palo Negro).
B50: 9. Municipio Mario Briceño Iragorry (El Limón).
B51: 11. Municipio San Casimiro (San Casimiro).
B52: 12. Municipio San Sebastián (San Sebastián de los Reyes).
B53: 13. Municipio Santiago Mariño (Turmero).
B54: 14. Municipio Santos Michelena (Las Tejerías).
... B58: 18. Municipio Zamora (Villa de Cura).
A61: Barinas | B61: 1. Municipio Alberto Arvelo Torrealba (Sabaneta).
B62: 2. Municipio Andrés Eloy Blanco (El Cantón).
B63: 3. Municipio Antonio José de Sucre (Socopó).
B64: 4. Municipio Arismendi (Arismendi).
B65: 5. Municipio Barinas (Barinas).
B66: 6. Municipio Bolívar (Barinitas).
B67: 7. Municipio Cruz Paredes (Barrancas).
B68: 8. Municipio Ezequiel Zamora (Santa Bárbara).
B69: 9. Municipio Obispos (Obispos).
B70: 10. Municipio Pedraza (Ciudad Bolivia).
B71: 11. Municipio Rojas (Libertad).
B72: 12. Municipio Sosa (Ciudad de Nutrias).
A74: Bolívar | B74: 1. Municipio Caroní (Ciudad Guayana).
B75: 2. Municipio Cedeño (Caicara del Orinoco).
B76: 3. Municipio El Callao (El Callao).
B77: 4. Municipio Gran Sabana (Santa Elena de Uairén).
B78: 5. Municipio Heres (Ciudad Bolívar).
B79: 6. Municipio Piar (Upata).
B80: 7. Municipio Raúl Leoni (Ciudad Piar).
B81: 8. Municipio Roscio (Guasipati).
B82: 9. Municipio Sifontes (Tumeremo).
B83: 10. Municipio Sucre (Maripa).
B84: 11. Municipio Padre Pedro Chen (El Palmar).
A86: Carabobo | B86: 1. Municipio Bejuma (Bejuma).
B87: 2. Municipio Carlos Arvelo (Güigüe).
B88: 3. Municipio Diego Ibarra (Mariara).
B89: 4. Municipio Guacara (Guacara).
B90: 5. Municipio Juan José Mora (Morón).
B91: 6. Municipio Libertador (Tocuyito).
B92: 7. Municipio Los Guayos (Los Guayos).
B93: 8. Municipio Miranda (Miranda).
B94: 9. Municipio Montalbán (Montalbán).
B95: 10. Municipio Naguanagua (Naguanagua).
B96: 11. Municipio Puerto Cabello (Puerto Cabello).
B97: 12. Municipio San Diego (San Diego).
B98: 13. Municipio San Joaquín (San Joaquín).
B99: 14. Municipio Valencia (Valencia).
A101: Cojedes | B101: 1. Municipio Anzoátegui (Cojedes).
B102: 2. Municipio Falcón (Tinaquillo).
B103: 3. Municipio Girardot (El Baúl).
B104: 4. Municipio Lima Blanco (Macapo).
B105: 5. Municipio Pao de San Juan Bautista (El Pao).
B106: 6. Municipio Ricaurte (Libertad).
B107: 7. Municipio Rómulo Gallegos.
B108: 8. Municipio Ezequiel Zamora (San Carlos)
B109: 9. Municipio Tinaco (Tinaco)
...

Sheet CATEGORIAS MEDICINAS
A1: 1 | B1: Anestésicos | C1: 1. Ketamina Ampollas | F1: 1 | G1: Anestésicos | H1: 1. Ketamina Ampollas | I1: Anestésicos | J1: 1
C2: 1. Lidocaína Ampollas | F2: 1 | G2: Anestésicos | H2: 1. Lidocaína Ampollas | I2: Anestésicos | J2: 1
C3: 1. Naloxona Ampollas | F3: 1 | G3: Anestésicos | H3: 1. Naloxona Ampollas | I3: Anestésicos | J3: 1
C4: 1. Otro…Anestésicos | F4: 1 | G4: Anestésicos | H4: 1. Otro…Anestésicos | I4: Anestésicos | J4: 1
F5: 2 | G5: Analgésicos_Antipiréticos_AINES | H5: 2. Ácido acetilsalicílico | I5: Analgésicos_Antipiréticos_AINES | J5: 2
F6: 2 | G6: Analgésicos_Antipiréticos_AINES | H6: 2. Diclofenac Gel | I6: Analgésicos_Antipiréticos_AINES | J6: 2
F7: 2 | G7: Analgésicos_Antipiréticos_AINES | H7: 2. Diclofenac Potasico | I7: Analgésicos_Antipiréticos_AINES | J7: 2
A8: 2 | B8: Analgésicos_Antipiréticos_AINES | C8: 2. Ácido acetilsalicílico | F8: 2 | G8: Analgésicos_Antipiréticos_AINES | H8: 2. Diclofenac Sódico | I8: Analgésicos_Antipiréticos_AINES | J8: 2
C9: 2. Diclofenac Gel | F9: 2 | G9: Analgésicos_Antipiréticos_AINES | H9: 2. Diclofenac Sódico Ampollas | I9: Analgésicos_Antipiréticos_AINES | J9: 2
C10: 2. Diclofenac Potasico | F10: 2 | G10: Analgésicos_Antipiréticos_AINES | H10: 2. Ibuprofeno 400 mg | I10: Analgésicos_Antipiréticos_AINES | J10: 2
C11: 2. Diclofenac Sódico | F11: 2 | G11: Analgésicos_Antipiréticos_AINES | H11: 2. Ibuprofeno tabs | I11: Analgésicos_Antipiréticos_AINES | J11: 2
C12: 2. Diclofenac Sódico Ampollas | F12: 2 | G12: Analgésicos_Antipiréticos_AINES | H12: 2. Ibuprofeno, Suspensión oral | I12: Analgésicos_Antipiréticos_AINES | J12: 2
C13: 2. Ibuprofeno 400 mg | F13: 2 | G13: Analgésicos_Antipiréticos_AINES | H13: 2. Paracetamol 100mg | I13: Analgésicos_Antipiréticos_AINES | J13: 2
C14: 2. Ibuprofeno tabs | F14: 2 | G14: Analgésicos_Antipiréticos_AINES | H14: 2. Paracetamol 500mg | I14: Analgésicos_Antipiréticos_AINES | J14: 2
C15: 2. Ibuprofeno, Suspensión oral | F15: 2 | G15: Analgésicos_Antipiréticos_AINES | H15: 2. Paracetamol Ampollas | I15: Analgésicos_Antipiréticos_AINES | J15: 2
C16: 2. Paracetamol 100mg | F16: 2 | G16: Analgésicos_Antipiréticos_AINES | H16: 2. Paracetamol supositorios | I16: Analgésicos_Antipiréticos_AINES | J16: 2
C17: 2. Paracetamol 500mg | F17: 2 | G17: Analgésicos_Antipiréticos_AINES | H17: 2. Paracetamol, Suspensión oral | I17: Analgésicos_Antipiréticos_AINES | J17: 2
C18: 2. Paracetamol Ampollas | F18: 2 | G18: Analgésicos_Antipiréticos_AINES | H18: 2. Tramadol tabs./caps | I18: Analgésicos_Antipiréticos_AINES | J18: 2
C19: 2. Paracetamol supositorios | F19: 2 | G19: Analgésicos_Antipiréticos_AINES | H19: 2. Otro… Analgésicos_Antipiréticos_AINES | I19: Analgésicos_Antipiréticos_AINES | J19: 2
C20: 2. Paracetamol, Suspensión oral | F20: 3 | G20: Antialérgicos | H20: 3. Prometazina | I20: Antialérgicos | J20: 3
... C22: 2. Otro… Analgésicos_Antipiréticos_AINES | F22: 3 | G22: Antialérgicos | H22: 3. Otro... Antialérgicos | I22: Antialérgicos | J22: 3
F23: 4 | G23: Antiepilépticos_Anticonvulsivantes | H23: 4. Carbamazepina | I23: Antiepilécticos | J23: 4
F24: 4 | G24: Antiepilépticos_Anticonvulsivantes | H24: 4. Fenitoína Sódica | I24: Antiepilécticos | J24: 4
F25: 4 | G25: Antiepilépticos_Anticonvulsivantes | H25: 4. Levodopa + Carbidopa | I25: Antiepilécticos | J25: 4
A26: 3 | B26: Antialérgicos | C26: 3. Prometazina | F26: 4 | G26: Antiepilépticos_Anticonvulsivantes | H26: 4. Otro…Antiepilépticos/anticonvulsivo | I26: Antiepilécticos | J26: 4
C27: 3. Prometazina Ampollas | F27: 5 | G27: Antihelmínticos_Antiparasitarios | H27: 5. Albendazol tabs. 400 mg | I27: Antihelmínticos_Antiparasitarios | J27: 5
C28: 3. Otro... Antialérgicos | F28: 5 | G28: Antihelmínticos_Antiparasitarios | H28: 5. Albendazol tabs. masticables 200 mg | I28: Antihelmínticos_Antiparasitarios | J28: 5
F29: 5 | G29: Antihelmínticos_Antiparasitarios | H29: 5. Mebendazol 500 mg | I29: Antihelmínticos_Antiparasitarios | J29: 5
F30: 5 | G30: Antihelmínticos_Antiparasitarios | H30: 5. Mebendazol tabs. 100 mg | I30: Antihelmínticos_Antiparasitarios | J30: 5
F31: 5 | G31: Antihelmínticos_Antiparasitarios | H31: 5. Otro…Antihelmínticos_Antiparasitarios | I31: Antihelmínticos_Antiparasitarios | J31: 5
A32: 4 | B32: Antiepilécticos | C32: 4. Carbamazepina | F32: 6 | G32: Antibióticos_Antifúngicos_Antivirales | H32: 6. Amoxicilina 250 mg + Ácido Clavulánico 62,5 mg/5 ml para suspensión oral | I32: Antibióticos_Antifúngicos_Antivirales | J32: 6
C33: 4. Fenitoína Sódica | F33: 6 | G33: Antibióticos_Antifúngicos_Antivirales | H33: 6. Amoxicilina 875 mg+ acido clavulanico | I33: Antibióticos_Antifúngicos_Antivirales | J33: 6
C34: 4. Levodopa + Carbidopa | F34: 6 | G34: Antibióticos_Antifúngicos_Antivirales | H34: 6. Amoxicilina dispersable 10x10 250mg | I34: Antibióticos_Antifúngicos_Antivirales | J34: 6
C35: 4. Otro…Antiepilécticos | F35: 6 | G35: Antibióticos_Antifúngicos_Antivirales | H35: 6. Amoxicilina para Suspensión oral 125 mg/5 ml | I35: Antibióticos_Antifúngicos_Antivirales | J35: 6
F36: 6 | G36: Antibióticos_Antifúngicos_Antivirales | H36: 6. Amoxicilina tabs./caps. 250 mg | I36: Antibióticos_Antifúngicos_Antivirales | J36: 6
F37: 6 | G37: Antibióticos_Antifúngicos_Antivirales | H37: 6. Amoxicilina tabs./caps. 500 mg | I37: Antibióticos_Antifúngicos_Antivirales | J37: 6
F38: 6 | G38: Antibióticos_Antifúngicos_Antivirales | H38: 6. Ampicilina Sódica para inyectar 1g | I38: Antibióticos_Antifúngicos_Antivirales | J38: 6
A39: 5 | B39: Antihelmínticos_Antiparasitarios | C39: 5. Albendazol tabs. 400 mg | F39: 6 | G39: Antibióticos_Antifúngicos_Antivirales | H39: 6. Cefalexina caps. 250 mg | I39: Antibióticos_Antifúngicos_Antivirales | J39: 6
C40: 5. Albendazol tabs. masticables 200 mg | F40: 6 | G40: Antibióticos_Antifúngicos_Antivirales | H40: 6. Cefixima tabs. 200 mg | I40: Antibióticos_Antifúngicos_Antivirales | J40: 6
C41: 5. Mebendazol 500 mg | F41: 6 | G41: Antibióticos_Antifúngicos_Antivirales | H41: 6. Ceftriaxona para inyectar 1.000 mg (Substancia seca) | I41: Antibióticos_Antifúngicos_Antivirales | J41: 6
C42: 5. Mebendazol tabs. 100 mg | F42: 6 | G42: Antibióticos_Antifúngicos_Antivirales | H42: 6. Ceftriaxona Sódica para inyectar 1g | I42: Antibióticos_Antifúngicos_Antivirales | J42: 6
C43: 5. Otro…Antihelmínticos_Antiparasitarios | F43: 6 | G43: Antibióticos_Antifúngicos_Antivirales | H43: 6. Ceftriaxona Sódica para inyectar 250 mg | I43: Antibióticos_Antifúngicos_Antivirales | J43: 6
F44: 6 | G44: Antibióticos_Antifúngicos_Antivirales | H44: 6. Ciprofloxacina tabs. 250 mg | I44: Antibióticos_Antifúngicos_Antivirales | J44: 6
F45: 6 | G45: Antibióticos_Antifúngicos_Antivirales | H45: 6. Ciprofloxacina tabs. 500 mg | I45: Antibióticos_Antifúngicos_Antivirales | J45: 6
F46: 6 | G46: Antibióticos_Antifúngicos_Antivirales | H46: 6. Cloxacilina caps 500 mg | I46: Antibióticos_Antifúngicos_Antivirales | J46: 6
A47: 6 | B47: Antibióticos_Antifúngicos_Antivirales | C47: 6. Amoxicilina 250 mg + Ácido Clavulánico 62,5 mg/5 ml para suspensión oral | F47: 6 | G47: Antibióticos_Antifúngicos_Antivirales | H47: 6. Cloxacilina Sódica para inyección 500 mg (sustancia seca) | I47: Antibióticos_Antifúngicos_Antivirales | J47: 6
C48: 6. Amoxicilina 875 mg+ acido clavulanico | F48: 6 | G48: Antibióticos_Antifúngicos_Antivirales | H48: 6. Cotrimoxazol en polvo para suspensión oral. 240 mg/5 ml Sulfametoxazol 200 mg, Trimetropima 40 mg/5 ml | I48: Antibióticos_Antifúngicos_Antivirales | J48: 6
C49: 6. Amoxicilina dispersable 10x10 250mg | F49: 6 | G49: Antibióticos_Antifúngicos_Antivirales | H49: 6. Cotrimoxazol tabs. 480 mg | I49: Antibióticos_Antifúngicos_Antivirales | J49: 6
C50: 6. Amoxicilina para Suspensión oral 125 mg/5 ml | F50: 6 | G50: Antibióticos_Antifúngicos_Antivirales | H50: 6. Doxicilina tabs. 100 mg | I50: Antibióticos_Antifúngicos_Antivirales | J50: 6
C51: 6. Amoxicilina tabs./caps. 250 mg | F51: 6 | G51: Antibióticos_Antifúngicos_Antivirales | H51: 6. Eritromicina etilsuccinato para suspensión oral 125 mg/5 ml | I51: Antibióticos_Antifúngicos_Antivirales | J51: 6
C52: 6. Amoxicilina tabs./caps. 500 mg | F52: 6 | G52: Antibióticos_Antifúngicos_Antivirales | H52: 6. Eritromicina tabs. 250 mg | I52: Antibióticos_Antifúngicos_Antivirales | J52: 6
C53: 6. Ampicilina Sódica para inyectar 1g | F53: 6 | G53: Antibióticos_Antifúngicos_Antivirales | H53: 6. Fluconazol caps. 50 mg | I53: Antibióticos_Antifúngicos_Antivirales | J53: 6
C54: 6. Cefalexina caps. 250 mg | F54: 6 | G54: Antibióticos_Antifúngicos_Antivirales | H54: 6. Gentamicina 80 mg, ampollas | I54: Antibióticos_Antifúngicos_Antivirales | J54: 6
C55: 6. Cefixima tabs. 200 mg | F55: 6 | G55: Antibióticos_Antifúngicos_Antivirales | H55: 6. Ketoconazol tabs. 200 mg | I55: Antibióticos_Antifúngicos_Antivirales | J55: 6
C56: 6. Ceftriaxona para inyectar 1.000 mg (Substancia seca) | F56: 6 | G56: Antibióticos_Antifúngicos_Antivirales | H56: 6. Miconazol 20 mg/g | I56: Antibióticos_Antifúngicos_Antivirales | J56: 6
C57: 6. Ceftriaxona Sódica para inyectar 1g | F57: 6 | G57: Antibióticos_Antifúngicos_Antivirales | H57: 6. Nistatina Suspensión oral 100.000 IU/ml | I57: Antibióticos_Antifúngicos_Antivirales | J57: 6
C58: 6. Ceftriaxona Sódica para inyectar 250 mg | F58: 6 | G58: Antibióticos_Antifúngicos_Antivirales | H58: 6. Nistatina vaginal tabs. 100.000 IU | I58: Antibióticos_Antifúngicos_Antivirales | J58: 6
C59: 6. Ciprofloxacina tabs. 250 mg | F59: 6 | G59: Antibióticos_Antifúngicos_Antivirales | H59: 6. Nistatina vaginal tabs. 100.000 IU con aplicador | I59: Antibióticos_Antifúngicos_Antivirales | J59: 6
... C81: 6. Otro… Antibióticos_Antifúngicos_Antivirales | F81: 8 | G81: Antimaláricos | H81: 8. Otro…Antimaláricos | I81: Antimaláricos | J81: 8
F82: 9 | G82: Inmunosupresores_Antineoplásicos | H82: 9. Azatioprina tabs. 50 mg | I82: Inmunosupresores_Antineoplásicos | J82: 9
F83: 9 | G83: Inmunosupresores_Antineoplásicos | H83: 9. Tamoxifeno tabs 20mg | I83: Inmunosupresores_Antineoplásicos | J83: 9
A84: 7 | B84: Antiamebianos_Antileishmaniasis | C84: 7. Metronidazol inyección 500 mg/100 ml | F84: 9 | G84: Inmunosupresores_Antineoplásicos | H84: 9. Otro… Inmunosupresores_Antineoplásicos | I84: Inmunosupresores_Antineoplásicos | J84: 9
C85: 7. Metronidazol tabs. 250 mg | F85: 10 | G85: Antituberculosos | H85: 10. Etambutil tabs. 400 mg | I85: Antituberculosis | J85: 10
C86: 7. Metronidazol vaginal tabs. 500 mg | F86: 10 | G86: Antituberculosos | H86: 10. Pirazinamida tabs. 500 mg | I86: Antituberculosis | J86: 10
C87: 7. Otro… Antiamebianos_Antileishmaniasis | F87: 10 | G87: Antituberculosos | H87: 10. Rifampicina/Isoniazida tabs. 300/150 mg | I87: Antituberculosis | J87: 10
F88: 10 | G88: Antituberculosos | H88: 10. Otro…Antituberculosis | I88: Antituberculosis | J88: 10
F89: 11 | G89: Antianémicos/Medicinas_con_afectación_sanguínea | H89: 11. Ácido Fólico tabs. 5 mg | I89: Medicinas_con_afectación_sanguínea | J89: 11
F90: 11 | G90: Antianémicos/Medicinas_con_afectación_sanguínea | H90: 11. Fumarato ferroso 182.4mg + acido folico 0.4 mg | I90: Medicinas_con_afectación_sanguínea | J90: 11
A91: 8 | B91: Antimaláricos | C91: 8. Arteméter 180 mg + Lumefantrina 1080 mg suspensión | F91: 11 | G91: Antianémicos/Medicinas_con_afectación_sanguínea | H91: 11. Sulfato Ferroso 200 mg + 0,4 mg ácido fólico tabletas recubiertas. | I91: Medicinas_con_afectación_sanguínea | J91: 11
C92: 8. Arteméter 20 mg + Lumefantrina 120 mg tabs. (Coartem ®) | F92: 11 | G92: Antianémicos/Medicinas_con_afectación_sanguínea | H92: 11. Sulfato ferroso tabs. 200 mg | I92: Medicinas_con_afectación_sanguínea | J92: 11
C93: 8. Arteméter 20 mg + Lumefantrina 120 mg tabs. dispersables (Coartem ®) | F93: 11 | G93: Antianémicos/Medicinas_con_afectación_sanguínea | H93: 11. Otro… Medicinas_con_afectación_sanguínea | I93: Medicinas_con_afectación_sanguínea | J93: 11
C94: 8. Arteméter inyección 80 mg/ml | F94: 12 | G94: Fármacos_Cardiovasculares | H94: 12. Ácido acetilsalisílico tabs. 100 mg | I94: Fármacos_Cardiovasculares | J94: 12
C95: 8. Artesiunato para inyección 60 mg/ml (con solvente) | F95: 12 | G95: Fármacos_Cardiovasculares | H95: 12. Atenolol tabs. 50mg | I95: Fármacos_Cardiovasculares | J95: 12
C96: 8. Artesunato 50 mg + Amodiaquina 153 mg base tabs. | F96: 12 | G96: Fármacos_Cardiovasculares | H96: 12. Captopril tabs. 25 mg | I96: Fármacos_Cardiovasculares | J96: 12
C97: 8. Cloroquina 150 mg | F97: 12 | G97: Fármacos_Cardiovasculares | H97: 12. Digoxina tabs. 0,25 mg | I97: Fármacos_Cardiovasculares | J97: 12
C98: 8. Diclorhidrato de quininda inyección 300 mg/ml | F98: 12 | G98: Fármacos_Cardiovasculares | H98: 12. Enalapril tabs. 5 mg | I98: Fármacos_Cardiovasculares | J98: 12
C99: 8. Primaquina 5 mg | F99: 12 | G99: Fármacos_Cardiovasculares | H99: 12. Hidralazina en polvo para inyección 20 mg | I99: Fármacos_Cardiovasculares | J99: 12
C100: 8. Sulfato de quinina tabs. 300 mg | F100: 12 | G100: Fármacos_Cardiovasculares | H100: 12. Metildopa tabs. 250 mg | I100: Fármacos_Cardiovasculares | J100: 12
C101: 8. Otro…Antimaláricos | F101: 12 | G101: Fármacos_Cardiovasculares | H101: 12. Nifedipina tabs. 10 mg | I101: Fármacos_Cardiovasculares | J101: 12
F102: 12 | G102: Fármacos_Cardiovasculares | H102: 12. Nifedipina tabs. 20 mg | I102: Fármacos_Cardiovasculares | J102: 12
F103: 12 | G103: Fármacos_Cardiovasculares | H103: 12. Otro… Fármacos_Cardiovasculares | I103: Fármacos_Cardiovasculares | J103: 12
F104: 13 | G104: Preparaciones_Dermatológicas | H104: 13. Benzoato de bencilo 25% | I104: Preparaciones_Dermatológicas | J104: 13
A105: 9 | B105: Inmunosupresores_Antineoplásicos | C105: 9. Azatioprina tabs. 50 mg | F105: 13 | G105: Preparaciones_Dermatológicas | H105: 13. Benzoato de bencilo concentrado de 90% | I105: Preparaciones_Dermatológicas | J105: 13
C106: 9. Dexametasona inyección 4 mg/ml | F106: 13 | G106: Preparaciones_Dermatológicas | H106: 13. Betametasona crema 0.1% | I106: Preparaciones_Dermatológicas | J106: 13
C107: 9. Tamoxifeno tabs 20mg | F107: 13 | G107: Preparaciones_Dermatológicas | H107: 13. Cetrimida 15% + Gluconato clorhexidina 1,5% solución | I107: Preparaciones_Dermatológicas | J107: 13
C108: 9. Otro… Inmunosupresores_Antineoplásicos | F108: 13 | G108: Preparaciones_Dermatológicas | H108: 13. Clotrimazol crema 1% | I108: Preparaciones_Dermatológicas | J108: 13
F109: 13 | G109: Preparaciones_Dermatológicas | H109: 13. Dexpantenol 5%, óxido de zinc 5% Pomada para heridas | I109: Preparaciones_Dermatológicas | J109: 13
F110: 13 | G110: Preparaciones_Dermatológicas | H110: 13. Gluconato de clorhexidina 5% | I110: Preparaciones_Dermatológicas | J110: 13
F111: 13 | G111: Preparaciones_Dermatológicas | H111: 13. Gluconato de clorhexidina solución 5% | I111: Preparaciones_Dermatológicas | J111: 13
A112: 10 | B112: Antituberculosis | C112: 10. Etambutil tabs. 400 mg | F112: 13 | G112: Preparaciones_Dermatológicas | H112: 13. Hidrocortisona crema 1% | I112: Preparaciones_Dermatológicas | J112: 13
C113: 10. Pirazinamida tabs. 500 mg | F113: 13 | G113: Preparaciones_Dermatológicas | H113: 13. Neomicina + Bacitracina (3,5 mg neomicina como sulfato de neomicina + 500 IU bacitracina/g) Pomada | I113: Preparaciones_Dermatológicas | J113: 13
C114: 10. Rifampicina/Isoniazida tabs. 300/150 mg | F114: 13 | G114: Preparaciones_Dermatológicas | H114: 13. Nistatina 100.000 IU Pomada | I114: Preparaciones_Dermatológicas | J114: 13
C115: 10. Otro…Antituberculosis | F115: 13 | G115: Preparaciones_Dermatológicas | H115: 13. Nitrato de Miconazol crema 2% | I115: Preparaciones_Dermatológicas | J115: 13
F116: 13 | G116: Preparaciones_Dermatológicas | H116: 13. Povidina yodada 10% | I116: Preparaciones_Dermatológicas | J116: 13
F117: 13 | G117: Preparaciones_Dermatológicas | H117: 13. Sulfadiazina de plata crema 1% | I117: Preparaciones_Dermatológicas | J117: 13
F118: 13 | G118: Preparaciones_Dermatológicas | H118: 13. Yodo povidona solución 10% | I118: Preparaciones_Dermatológicas | J118: 13
A119: 11 | B119: Medicinas_con_afectación_sanguínea | C119: 11. Ácido Fólico tabs. 5 mg | F119: 13 | G119: Preparaciones_Dermatológicas | H119: 13. Otro…Preparaciones_Dermatológicas | I119: Preparaciones_Dermatológicas | J119: 13
C120: 11. Fumarato ferroso 182.4mg + acido folico 0.4 mg | F120: 14 | G120: Esteroides | H120: 14. Hidrocortisona para inyección 100 mg/vial | I120: Esteroides | J120: 14
C121: 11. Sulfato Ferroso 200 mg + 0,4 mg ácido fólico tabletas recubiertas. | F121: 14 | G121: Esteroides | H121: 14. Hidrocortisona para inyección 100 mg | I121: Esteroides | J121: 14
C122: 11. Sulfato ferroso tabs. 200 mg | F122: 14 | G122: Esteroides | H122: 14. Prednisolona tabs. 5 mg | I122: Esteroides | J122: 14
...

Sheet Resumen
C1: Pestaña N° | D1: Resumen de Gestión Diocesana | E1: Beneficiarios directos de la acción | F1: DIOCESIS | G1: MES | H1: AÑO
C2: 1 | D2: N° de Niños con evaluación Talla/Peso (Total de Niños medidos)
C3: 1 | D3: N° de Niños identificados en Alerta (z-score 0)
C4: 1 | D4: N° de Niños identificados en Manejo Preventivo (Riesgo z-score -1 )
C5: 1 | D5: N° de Niños identificados con Desnutricion GAM Moderada (z-score -2 )
C6: 1 | D6: N° de Niños identificados con Desnutricion GAM Severa (z-score -3 )
C7: 1 | D7: N° de Niños Desparasitados de 2 - 5 años
C8: 1 | D8: N° de Niños en vivero con atencion según protocolo
C9: 1 | D9: N° de Niños Recuperados
C10: 2 | D10: N° de Embarazadas/Lactantes evaluadas (Total Medidas C. Brazo)
C11: 2 | D11: N° de Embarazadas/Lactantes Desparasitadas
C12: 2 | D12: N° de Embarazadas/Lactantes con bajo peso (>23cm)
C13: 2 | D13: N° de Kits Embarazadas (Acido Folico + Vitaminas) entregados
... C18: 4 | D18: N° de Consultas Psicologicas
C19: 4.1 | D19: N° de Medicinas entregadas
C20: 6 | D20: N° de Capacitaciones a benediciarios de las comunidades
C21: 6 | D21: N° de Participantes en capacitaciones comunitarias
C22: 6 | D22: N° de Capacitaciones a Voluntarios/Promotores de Caritas
C23: 6 | D23: Participantes en capacitaciones a Cáritas
C24: 7 | D24: N° de Encuestas Hogares realizadas
C25: 8 | D25: N° de Beneficiarios del Fondo solidario
C26: 8 | D26: N° de Beneficiarios Kits de higiene
C27: 8 | D27: N° de Beneficiarios Filtros artesanales
C28: 8 | D28: N° de Beneficiarios Pastillas purificadoras
C29: 9 | D29: N° de Beneficiarios Kits de Proteccion COVID-19
C30: 8 | D30: N° de Beneficiarios Kits de alimentos
C31: 10 | D31: N° de Encuestas Percepcion realizadas
... C33: 14 | D33: N° de Salas Situacional

Sheet 0. LOCALIZACIÓN
B3: ESTADO | C3: MUNICIPIO | D3: PARROQUIA
B4: Distrito Capital | C4: Libertador | D4: Altagracia
B5: Distrito Capital | C5: Libertador | D5: Antimano
B6: Distrito Capital | C6: Libertador | D6: Candelaria
B7: Distrito Capital | C7: Libertador | D7: Caricuao
B8: Distrito Capital | C8: Libertador | D8: Catedral
B9: Distrito Capital | C9: Libertador | D9: Coche
B10: Distrito Capital | C10: Libertador | D10: El Junquito
B11: Distrito Capital | C11: Libertador | D11: El Paraíso
B12: Distrito Capital | C12: Libertador | D12: El Recreo
B13: Distrito Capital | C13: Libertador | D13: El Valle
B14: Distrito Capital | C14: Libertador | D14: La Pastora
... B1138: La Guaira | C1138: Vargas | D1138: Carlos Soublette

Sheet 1. SAMAN NIÑOS
A1: N° | B1: DIOCESIS | C1: ESTADO | D1: MUNICIPIO | E1: PARROQUIA CIVIL | F1: PARROQUIA ECLESIAL / CENTRO CENTINELA | G1: SECTOR O COMUNIDAD | H1: GRUPO ETNICO | I1: CÉDULA DE IDENTIDAD de la madre o cuidador (ingrese solo números sin espacios) | J1: EDAD (de la madre o cuidador) | K1: PARENTESCO con el niño / niña | L1: TIPO DE INGRESO | M1: N° Control / N° de Semana | N1: N° de Historia o Código del niño | O1: Nombres del niño o niña | P1: Apellidos del niño o niña | Q1: Sexo | R1: Fecha de Nacimiento dd/mm/aaaa | S1: Fecha de Medición dd/mm/aaaa | T1: Edad (Años y Meses) | U1: Rango de Edad | V1: ¿Tiene condición de discapacidad? | W1: En caso afirmativo indique: ¿Cúal? | X1: Edema | Y1: Hemoglobina (g/dL) | Z1: C. BRAZO (cm) | AA1: Clasificación PB | AB1: TALLA (cm) | AC1: PESO (kg) | AD1: Z-Score (ZPT) | AE1: Estado Nutricional | AF1: Desparasitado en la jornada | AG1: Tratamiento suministrado Según Protocolo Cáritas | AH1: Cantidad Suministrada (sobres o unidades) | AI1: Otros Complementos | AJ1: FECHA INICIO DE VIVERO | AK1: FECHA SALIDA DE VIVERO | AL1: Z-Score (ZPT) ENTRADA | AM1: Z-Score (ZPT) SALIDA | AN1: SAMANAS DE DURACION EN VIVERO | AO1: SITUACÍON A LA SALIDA | AP1: REFERIDO AL MEDICO | AQ1: Observaciones | AR1: MES | AS1: AÑO | AT1: CENTRO | AU1: CODIGO DE DIOCESIS | AV1: Indicar si el niño es Beneficiario del Proyecto TENGO
A2: 1 | N2: =AU2&R2&A2 -> 1 | T2: =IF(R2="","",(S2-R2)/365) | U2: =IF(R2="","",IF(T2<=0.6,"0-6 meses",IF(T2<=2,"7-23 meses",IF(T2<=5,"24-59 meses",IF(T2>5,"Mayor a 5 años"))))) | AA2: =IF(ISBLANK(Z2),"ERROR",IF(AND(Z2>=12.5,Z2<=35),"Adecuado",IF(AND(Z2<11.5,Z2>=9),"Desnutrición aguda severa",IF(AND(Z2>=11.5,Z2<12.5),"Desnutrición aguda moderada",IF(AND(Z2>=6,Z2<9),"Referencia valoración médica",IF(Z2<6,"Dato inválido",IF(Z2>35,"Dato inválido"))))))) -> ERROR | AE2: =IF(ISBLANK(AD2),"ERROR",IF(AND(AD2>3,AD2<5),"Obesidad",IF(AND(AD2>2,AD2<=3),"Sobrepeso",IF(AND(AD2<=2,AD2>=-2),"Adecuado",IF(AND(AD2>=-3,AD2<-2),"Desnutrición aguda moderada",IF(AND(AD2<-3,AD2>-5),"Desnutrición aguda severa",IF(AD2<=-5,"Dato inválido",IF(AD2>=5,"Dato inválido")))))))) -> ERROR | AR2: =IF(D2="","",TEXT(S2,"MMMM")) | AS2: =IF(F2="","",TEXT(S2,"YYYY")) | AT2: =B2&" - "&E2 -> - | AU2: =IFERROR(VLOOKUP(B2,adm!$C$2:$E$36,3,FALSE),"")
A3: 2 | N3: =AU3&R3&A3 -> 2 | T3: =IF(R3="","",(S3-R3)/365) | U3: =IF(R3="","",IF(T3<=0.6,"0-6 meses",IF(T3<=2,"7-23 meses",IF(T3<=5,"24-59 meses",IF(T3>5,"Mayor a 5 años"))))) | AA3: =IF(ISBLANK(Z3),"ERROR",IF(AND(Z3>=12.5,Z3<=35),"Adecuado",IF(AND(Z3<11.5,Z3>=9),"Desnutrición aguda severa",IF(AND(Z3>=11.5,Z3<12.5),"Desnutrición aguda moderada",IF(AND(Z3>=6,Z3<9),"Referencia valoración médica",IF(Z3<6,"Dato inválido",IF(Z3>35,"Dato inválido"))))))) -> ERROR | AE3: =IF(ISBLANK(AD3),"ERROR",IF(AND(AD3>3,AD3<5),"Obesidad",IF(AND(AD3>2,AD3<=3),"Sobrepeso",IF(AND(AD3<=2,AD3>=-2),"Adecuado",IF(AND(AD3>=-3,AD3<-2),"Desnutrición aguda moderada",IF(AND(AD3<-3,AD3>-5),"Desnutrición aguda severa",IF(AD3<=-5,"Dato inválido",IF(AD3>=5,"Dato inválido")))))))) -> ERROR | AR3: =IF(D3="","",TEXT(S3,"MMMM")) | AS3: =IF(F3="","",TEXT(S3,"YYYY")) | AT3: =B3&" - "&E3 -> - | AU3: =IFERROR(VLOOKUP(B3,adm!$C$2:$E$36,3,FALSE),"")
A4: 3 | N4: =AU4&R4&A4 -> 3 | T4: =IF(R4="","",(S4-R4)/365) | U4: =IF(R4="","",IF(T4<=0.6,"0-6 meses",IF(T4<=2,"7-23 meses",IF(T4<=5,"24-59 meses",IF(T4>5,"Mayor a 5 años"))))) | AA4: =IF(ISBLANK(Z4),"ERROR",IF(AND(Z4>=12.5,Z4<=35),"Adecuado",IF(AND(Z4<11.5,Z4>=9),"Desnutrición aguda severa",IF(AND(Z4>=11.5,Z4<12.5),"Desnutrición aguda moderada",IF(AND(Z4>=6,Z4<9),"Referencia valoración médica",IF(Z4<6,"Dato inválido",IF(Z4>35,"Dato inválido"))))))) -> ERROR | AE4: =IF(ISBLANK(AD4),"ERROR",IF(AND(AD4>3,AD4<5),"Obesidad",IF(AND(AD4>2,AD4<=3),"Sobrepeso",IF(AND(AD4<=2,AD4>=-2),"Adecuado",IF(AND(AD4>=-3,AD4<-2),"Desnutrición aguda moderada",IF(AND(AD4<-3,AD4>-5),"Desnutrición aguda severa",IF(AD4<=-5,"Dato inválido",IF(AD4>=5,"Dato inválido")))))))) -> ERROR | AR4: =IF(D4="","",TEXT(S4,"MMMM")) | AS4: =IF(F4="","",TEXT(S4,"YYYY")) | AT4: =B4&" - "&E4 -> - | AU4: =IFERROR(VLOOKUP(B4,adm!$C$2:$E$36,3,FALSE),"")
A5: 4 | N5: =AU5&R5&A5 -> 4 | T5: =IF(R5="","",(S5-R5)/365) | U5: =IF(R5="","",IF(T5<=0.6,"0-6 meses",IF(T5<=2,"7-23 meses",IF(T5<=5,"24-59 meses",IF(T5>5,"Mayor a 5 años"))))) | AA5: =IF(ISBLANK(Z5),"ERROR",IF(AND(Z5>=12.5,Z5<=35),"Adecuado",IF(AND(Z5<11.5,Z5>=9),"Desnutrición aguda severa",IF(AND(Z5>=11.5,Z5<12.5),"Desnutrición aguda moderada",IF(AND(Z5>=6,Z5<9),"Referencia valoración médica",IF(Z5<6,"Dato inválido",IF(Z5>35,"Dato inválido"))))))) -> ERROR | AE5: =IF(ISBLANK(AD5),"ERROR",IF(AND(AD5>3,AD5<5),"Obesidad",IF(AND(AD5>2,AD5<=3),"Sobrepeso",IF(AND(AD5<=2,AD5>=-2),"Adecuado",IF(AND(AD5>=-3,AD5<-2),"Desnutrición aguda moderada",IF(AND(AD5<-3,AD5>-5),"Desnutrición aguda severa",IF(AD5<=-5,"Dato inválido",IF(AD5>=5,"Dato inválido")))))))) -> ERROR | AR5: =IF(D5="","",TEXT(S5,"MMMM")) | AS5: =IF(F5="","",TEXT(S5,"YYYY")) | AT5: =B5&" - "&E5 -> - | AU5: =IFERROR(VLOOKUP(B5,adm!$C$2:$E$36,3,FALSE),"")
A6: 5 | N6: =AU6&R6&A6 -> 5 | T6: =IF(R6="","",(S6-R6)/365) | U6: =IF(R6="","",IF(T6<=0.6,"0-6 meses",IF(T6<=2,"7-23 meses",IF(T6<=5,"24-59 meses",IF(T6>5,"Mayor a 5 años"))))) | AA6: =IF(ISBLANK(Z6),"ERROR",IF(AND(Z6>=12.5,Z6<=35),"Adecuado",IF(AND(Z6<11.5,Z6>=9),"Desnutrición aguda severa",IF(AND(Z6>=11.5,Z6<12.5),"Desnutrición aguda moderada",IF(AND(Z6>=6,Z6<9),"Referencia valoración médica",IF(Z6<6,"Dato inválido",IF(Z6>35,"Dato inválido"))))))) -> ERROR | AE6: =IF(ISBLANK(AD6),"ERROR",IF(AND(AD6>3,AD6<5),"Obesidad",IF(AND(AD6>2,AD6<=3),"Sobrepeso",IF(AND(AD6<=2,AD6>=-2),"Adecuado",IF(AND(AD6>=-3,AD6<-2),"Desnutrición aguda moderada",IF(AND(AD6<-3,AD6>-5),"Desnutrición aguda severa",IF(AD6<=-5,"Dato inválido",IF(AD6>=5,"Dato inválido")))))))) -> ERROR | AR6: =IF(D6="","",TEXT(S6,"MMMM")) | AS6: =IF(F6="","",TEXT(S6,"YYYY")) | AT6: =B6&" - "&E6 -> - | AU6: =IFERROR(VLOOKUP(B6,adm!$C$2:$E$36,3,FALSE),"")
A7: 6 | N7: =AU7&R7&A7 -> 6 | T7: =IF(R7="","",(S7-R7)/365) | U7: =IF(R7="","",IF(T7<=0.6,"0-6 meses",IF(T7<=2,"7-23 meses",IF(T7<=5,"24-59 meses",IF(T7>5,"Mayor a 5 años"))))) | AA7: =IF(ISBLANK(Z7),"ERROR",IF(AND(Z7>=12.5,Z7<=35),"Adecuado",IF(AND(Z7<11.5,Z7>=9),"Desnutrición aguda severa",IF(AND(Z7>=11.5,Z7<12.5),"Desnutrición aguda moderada",IF(AND(Z7>=6,Z7<9),"Referencia valoración médica",IF(Z7<6,"Dato inválido",IF(Z7>35,"Dato inválido"))))))) -> ERROR | AE7: =IF(ISBLANK(AD7),"ERROR",IF(AND(AD7>3,AD7<5),"Obesidad",IF(AND(AD7>2,AD7<=3),"Sobrepeso",IF(AND(AD7<=2,AD7>=-2),"Adecuado",IF(AND(AD7>=-3,AD7<-2),"Desnutrición aguda moderada",IF(AND(AD7<-3,AD7>-5),"Desnutrición aguda severa",IF(AD7<=-5,"Dato inválido",IF(AD7>=5,"Dato inválido")))))))) -> ERROR | AR7: =IF(D7="","",TEXT(S7,"MMMM")) | AS7: =IF(F7="","",TEXT(S7,"YYYY")) | AT7: =B7&" - "&E7 -> - | AU7: =IFERROR(VLOOKUP(B7,adm!$C$2:$E$36,3,FALSE),"")
A8: 7 | N8: =AU8&R8&A8 -> 7 | T8: =IF(R8="","",(S8-R8)/365) | U8: =IF(R8="","",IF(T8<=0.6,"0-6 meses",IF(T8<=2,"7-23 meses",IF(T8<=5,"24-59 meses",IF(T8>5,"Mayor a 5 años"))))) | AA8: =IF(ISBLANK(Z8),"ERROR",IF(AND(Z8>=12.5,Z8<=35),"Adecuado",IF(AND(Z8<11.5,Z8>=9),"Desnutrición aguda severa",IF(AND(Z8>=11.5,Z8<12.5),"Desnutrición aguda moderada",IF(AND(Z8>=6,Z8<9),"Referencia valoración médica",IF(Z8<6,"Dato inválido",IF(Z8>35,"Dato inválido"))))))) -> ERROR | AE8: =IF(ISBLANK(AD8),"ERROR",IF(AND(AD8>3,AD8<5),"Obesidad",IF(AND(AD8>2,AD8<=3),"Sobrepeso",IF(AND(AD8<=2,AD8>=-2),"Adecuado",IF(AND(AD8>=-3,AD8<-2),"Desnutrición aguda moderada",IF(AND(AD8<-3,AD8>-5),"Desnutrición aguda severa",IF(AD8<=-5,"Dato inválido",IF(AD8>=5,"Dato inválido")))))))) -> ERROR | AR8: =IF(D8="","",TEXT(S8,"MMMM")) | AS8: =IF(F8="","",TEXT(S8,"YYYY")) | AT8: =B8&" - "&E8 -> - | AU8: =IFERROR(VLOOKUP(B8,adm!$C$2:$E$36,3,FALSE),"")
A9: 8 | N9: =AU9&R9&A9 -> 8 | T9: =IF(R9="","",(S9-R9)/365) | U9: =IF(R9="","",IF(T9<=0.6,"0-6 meses",IF(T9<=2,"7-23 meses",IF(T9<=5,"24-59 meses",IF(T9>5,"Mayor a 5 años"))))) | AA9: =IF(ISBLANK(Z9),"ERROR",IF(AND(Z9>=12.5,Z9<=35),"Adecuado",IF(AND(Z9<11.5,Z9>=9),"Desnutrición aguda severa",IF(AND(Z9>=11.5,Z9<12.5),"Desnutrición aguda moderada",IF(AND(Z9>=6,Z9<9),"Referencia valoración médica",IF(Z9<6,"Dato inválido",IF(Z9>35,"Dato inválido"))))))) -> ERROR | AE9: =IF(ISBLANK(AD9),"ERROR",IF(AND(AD9>3,AD9<5),"Obesidad",IF(AND(AD9>2,AD9<=3),"Sobrepeso",IF(AND(AD9<=2,AD9>=-2),"Adecuado",IF(AND(AD9>=-3,AD9<-2),"Desnutrición aguda moderada",IF(AND(AD9<-3,AD9>-5),"Desnutrición aguda severa",IF(AD9<=-5,"Dato inválido",IF(AD9>=5,"Dato inválido")))))))) -> ERROR | AR9: =IF(D9="","",TEXT(S9,"MMMM")) | AS9: =IF(F9="","",TEXT(S9,"YYYY")) | AT9: =B9&" - "&E9 -> - | AU9: =IFERROR(VLOOKUP(B9,adm!$C$2:$E$36,3,FALSE),"")
A10: 9 | N10: =AU10&R10&A10 -> 9 | T10: =IF(R10="","",(S10-R10)/365) | U10: =IF(R10="","",IF(T10<=0.6,"0-6 meses",IF(T10<=2,"7-23 meses",IF(T10<=5,"24-59 meses",IF(T10>5,"Mayor a 5 años"))))) | AA10: =IF(ISBLANK(Z10),"ERROR",IF(AND(Z10>=12.5,Z10<=35),"Adecuado",IF(AND(Z10<11.5,Z10>=9),"Desnutrición aguda severa",IF(AND(Z10>=11.5,Z10<12.5),"Desnutrición aguda moderada",IF(AND(Z10>=6,Z10<9),"Referencia valoración médica",IF(Z10<6,"Dato inválido",IF(Z10>35,"Dato inválido"))))))) -> ERROR | AE10: =IF(ISBLANK(AD10),"ERROR",IF(AND(AD10>3,AD10<5),"Obesidad",IF(AND(AD10>2,AD10<=3),"Sobrepeso",IF(AND(AD10<=2,AD10>=-2),"Adecuado",IF(AND(AD10>=-3,AD10<-2),"Desnutrición aguda moderada",IF(AND(AD10<-3,AD10>-5),"Desnutrición aguda severa",IF(AD10<=-5,"Dato inválido",IF(AD10>=5,"Dato inválido")))))))) -> ERROR | AR10: =IF(D10="","",TEXT(S10,"MMMM")) | AS10: =IF(F10="","",TEXT(S10,"YYYY")) | AT10: =B10&" - "&E10 -> - | AU10: =IFERROR(VLOOKUP(B10,adm!$C$2:$E$36,3,FALSE),"")
A11: 10 | N11: =AU11&R11&A11 -> 10 | T11: =IF(R11="","",(S11-R11)/365) | U11: =IF(R11="","",IF(T11<=0.6,"0-6 meses",IF(T11<=2,"7-23 meses",IF(T11<=5,"24-59 meses",IF(T11>5,"Mayor a 5 años"))))) | AA11: =IF(ISBLANK(Z11),"ERROR",IF(AND(Z11>=12.5,Z11<=35),"Adecuado",IF(AND(Z11<11.5,Z11>=9),"Desnutrición aguda severa",IF(AND(Z11>=11.5,Z11<12.5),"Desnutrición aguda moderada",IF(AND(Z11>=6,Z11<9),"Referencia valoración médica",IF(Z11<6,"Dato inválido",IF(Z11>35,"Dato inválido"))))))) -> ERROR | AE11: =IF(ISBLANK(AD11),"ERROR",IF(AND(AD11>3,AD11<5),"Obesidad",IF(AND(AD11>2,AD11<=3),"Sobrepeso",IF(AND(AD11<=2,AD11>=-2),"Adecuado",IF(AND(AD11>=-3,AD11<-2),"Desnutrición aguda moderada",IF(AND(AD11<-3,AD11>-5),"Desnutrición aguda severa",IF(AD11<=-5,"Dato inválido",IF(AD11>=5,"Dato inválido")))))))) -> ERROR | AR11: =IF(D11="","",TEXT(S11,"MMMM")) | AS11: =IF(F11="","",TEXT(S11,"YYYY")) | AT11: =B11&" - "&E11 -> - | AU11: =IFERROR(VLOOKUP(B11,adm!$C$2:$E$36,3,FALSE),"")
A12: 11 | N12: =AU12&R12&A12 -> 11 | T12: =IF(R12="","",(S12-R12)/365) | U12: =IF(R12="","",IF(T12<=0.6,"0-6 meses",IF(T12<=2,"7-23 meses",IF(T12<=5,"24-59 meses",IF(T12>5,"Mayor a 5 años"))))) | AA12: =IF(ISBLANK(Z12),"ERROR",IF(AND(Z12>=12.5,Z12<=35),"Adecuado",IF(AND(Z12<11.5,Z12>=9),"Desnutrición aguda severa",IF(AND(Z12>=11.5,Z12<12.5),"Desnutrición aguda moderada",IF(AND(Z12>=6,Z12<9),"Referencia valoración médica",IF(Z12<6,"Dato inválido",IF(Z12>35,"Dato inválido"))))))) -> ERROR | AE12: =IF(ISBLANK(AD12),"ERROR",IF(AND(AD12>3,AD12<5),"Obesidad",IF(AND(AD12>2,AD12<=3),"Sobrepeso",IF(AND(AD12<=2,AD12>=-2),"Adecuado",IF(AND(AD12>=-3,AD12<-2),"Desnutrición aguda moderada",IF(AND(AD12<-3,AD12>-5),"Desnutrición aguda severa",IF(AD12<=-5,"Dato inválido",IF(AD12>=5,"Dato inválido")))))))) -> ERROR | AR12: =IF(D12="","",TEXT(S12,"MMMM")) | AS12: =IF(F12="","",TEXT(S12,"YYYY")) | AT12: =B12&" - "&E12 -> - | AU12: =IFERROR(VLOOKUP(B12,adm!$C$2:$E$36,3,FALSE),"")
A13: 12 | N13: =AU13&R13&A13 -> 12 | T13: =IF(R13="","",(S13-R13)/365) | U13: =IF(R13="","",IF(T13<=0.6,"0-6 meses",IF(T13<=2,"7-23 meses",IF(T13<=5,"24-59 meses",IF(T13>5,"Mayor a 5 años"))))) | AA13: =IF(ISBLANK(Z13),"ERROR",IF(AND(Z13>=12.5,Z13<=35),"Adecuado",IF(AND(Z13<11.5,Z13>=9),"Desnutrición aguda severa",IF(AND(Z13>=11.5,Z13<12.5),"Desnutrición aguda moderada",IF(AND(Z13>=6,Z13<9),"Referencia valoración médica",IF(Z13<6,"Dato inválido",IF(Z13>35,"Dato inválido"))))))) -> ERROR | AE13: =IF(ISBLANK(AD13),"ERROR",IF(AND(AD13>3,AD13<5),"Obesidad",IF(AND(AD13>2,AD13<=3),"Sobrepeso",IF(AND(AD13<=2,AD13>=-2),"Adecuado",IF(AND(AD13>=-3,AD13<-2),"Desnutrición aguda moderada",IF(AND(AD13<-3,AD13>-5),"Desnutrición aguda severa",IF(AD13<=-5,"Dato inválido",IF(AD13>=5,"Dato inválido")))))))) -> ERROR | AR13: =IF(D13="","",TEXT(S13,"MMMM")) | AS13: =IF(F13="","",TEXT(S13,"YYYY")) | AT13: =B13&" - "&E13 -> - | AU13: =IFERROR(VLOOKUP(B13,adm!$C$2:$E$36,3,FALSE),"")
... A15: 14 | N15: =AU15&R15&A15 -> 14 | T15: =IF(R15="","",(S15-R15)/365) | U15: =IF(R15="","",IF(T15<=0.6,"0-6 meses",IF(T15<=2,"7-23 meses",IF(T15<=5,"24-59 meses",IF(T15>5,"Mayor a 5 años"))))) | AA15: =IF(ISBLANK(Z15),"ERROR",IF(AND(Z15>=12.5,Z15<=35),"Adecuado",IF(AND(Z15<11.5,Z15>=9),"Desnutrición aguda severa",IF(AND(Z15>=11.5,Z15<12.5),"Desnutrición aguda moderada",IF(AND(Z15>=6,Z15<9),"Referencia valoración médica",IF(Z15<6,"Dato inválido",IF(Z15>35,"Dato inválido"))))))) -> ERROR | AE15: =IF(ISBLANK(AD15),"ERROR",IF(AND(AD15>3,AD15<5),"Obesidad",IF(AND(AD15>2,AD15<=3),"Sobrepeso",IF(AND(AD15<=2,AD15>=-2),"Adecuado",IF(AND(AD15>=-3,AD15<-2),"Desnutrición aguda moderada",IF(AND(AD15<-3,AD15>-5),"Desnutrición aguda severa",IF(AD15<=-5,"Dato inválido",IF(AD15>=5,"Dato inválido")))))))) -> ERROR | AR15: =IF(D15="","",TEXT(S15,"MMMM")) | AS15: =IF(F15="","",TEXT(S15,"YYYY")) | AT15: =B15&" - "&E15 -> - | AU15: =IFERROR(VLOOKUP(B15,adm!$C$2:$E$36,3,FALSE),"")
A16: 15 | N16: =AU16&R16&A16 -> 15 | T16: =IF(R16="","",(S16-R16)/365) | U16: =IF(R16="","",IF(T16<=0.6,"0-6 meses",IF(T16<=2,"7-23 meses",IF(T16<=5,"24-59 meses",IF(T16>5,"Mayor a 5 años"))))) | AA16: =IF(ISBLANK(Z16),"ERROR",IF(AND(Z16>=12.5,Z16<=35),"Adecuado",IF(AND(Z16<11.5,Z16>=9),"Desnutrición aguda severa",IF(AND(Z16>=11.5,Z16<12.5),"Desnutrición aguda moderada",IF(AND(Z16>=6,Z16<9),"Referencia valoración médica",IF(Z16<6,"Dato inválido",IF(Z16>35,"Dato inválido"))))))) -> ERROR | AE16: =IF(ISBLANK(AD17),"ERROR",IF(AND(AD17>3,AD17<5),"Obesidad",IF(AND(AD17>2,AD17<=3),"Sobrepeso",IF(AND(AD17<=2,AD17>=-2),"Adecuado",IF(AND(AD17>=-3,AD17<-2),"Desnutrición aguda moderada",IF(AND(AD17<-3,AD17>-5),"Desnutrición aguda severa",IF(AD17<=-5,"Dato inválido",IF(AD17>=5,"Dato inválido")))))))) -> ERROR | AR16: =IF(D16="","",TEXT(S16,"MMMM")) | AS16: =IF(F16="","",TEXT(S16,"YYYY")) | AT16: =B16&" - "&E16 -> - | AU16: =IFERROR(VLOOKUP(B16,adm!$C$2:$E$36,3,FALSE),"")
A17: 16 | N17: =AU17&R17&A17 -> 16 | T17: =IF(R17="","",(S17-R17)/365) | U17: =IF(R17="","",IF(T17<=0.6,"0-6 meses",IF(T17<=2,"7-23 meses",IF(T17<=5,"24-59 meses",IF(T17>5,"Mayor a 5 años"))))) | AA17: =IF(ISBLANK(Z17),"ERROR",IF(AND(Z17>=12.5,Z17<=35),"Adecuado",IF(AND(Z17<11.5,Z17>=9),"Desnutrición aguda severa",IF(AND(Z17>=11.5,Z17<12.5),"Desnutrición aguda moderada",IF(AND(Z17>=6,Z17<9),"Referencia valoración médica",IF(Z17<6,"Dato inválido",IF(Z17>35,"Dato inválido"))))))) -> ERROR | AE17: =IF(ISBLANK(AD18),"ERROR",IF(AND(AD18>3,AD18<5),"Obesidad",IF(AND(AD18>2,AD18<=3),"Sobrepeso",IF(AND(AD18<=2,AD18>=-2),"Adecuado",IF(AND(AD18>=-3,AD18<-2),"Desnutrición aguda moderada",IF(AND(AD18<-3,AD18>-5),"Desnutrición aguda severa",IF(AD18<=-5,"Dato inválido",IF(AD18>=5,"Dato inválido")))))))) -> ERROR | AR17: =IF(D17="","",TEXT(S17,"MMMM")) | AS17: =IF(F17="","",TEXT(S17,"YYYY")) | AT17: =B17&" - "&E17 -> - | AU17: =IFERROR(VLOOKUP(B17,adm!$C$2:$E$36,3,FALSE),"")
A18: 17 | N18: =AU18&R18&A18 -> 17 | T18: =IF(R18="","",(S18-R18)/365) | U18: =IF(R18="","",IF(T18<=0.6,"0-6 meses",IF(T18<=2,"7-23 meses",IF(T18<=5,"24-59 meses",IF(T18>5,"Mayor a 5 años"))))) | AA18: =IF(ISBLANK(Z18),"ERROR",IF(AND(Z18>=12.5,Z18<=35),"Adecuado",IF(AND(Z18<11.5,Z18>=9),"Desnutrición aguda severa",IF(AND(Z18>=11.5,Z18<12.5),"Desnutrición aguda moderada",IF(AND(Z18>=6,Z18<9),"Referencia valoración médica",IF(Z18<6,"Dato inválido",IF(Z18>35,"Dato inválido"))))))) -> ERROR | AE18: =IF(ISBLANK(AD18),"ERROR",IF(AND(AD18>3,AD18<5),"Obesidad",IF(AND(AD18>2,AD18<=3),"Sobrepeso",IF(AND(AD18<=2,AD18>=-2),"Adecuado",IF(AND(AD18>=-3,AD18<-2),"Desnutrición aguda moderada",IF(AND(AD18<-3,AD18>-5),"Desnutrición aguda severa",IF(AD18<=-5,"Dato inválido",IF(AD18>=5,"Dato inválido")))))))) -> ERROR | AR18: =IF(D18="","",TEXT(S18,"MMMM")) | AS18: =IF(F18="","",TEXT(S18,"YYYY")) | AT18: =B18&" - "&E18 -> - | AU18: =IFERROR(VLOOKUP(B18,adm!$C$2:$E$36,3,FALSE),"")
A19: 18 | N19: =AU19&R19&A19 -> 18 | T19: =IF(R19="","",(S19-R19)/365) | U19: =IF(R19="","",IF(T19<=0.6,"0-6 meses",IF(T19<=2,"7-23 meses",IF(T19<=5,"24-59 meses",IF(T19>5,"Mayor a 5 años"))))) | AA19: =IF(ISBLANK(Z19),"ERROR",IF(AND(Z19>=12.5,Z19<=35),"Adecuado",IF(AND(Z19<11.5,Z19>=9),"Desnutrición aguda severa",IF(AND(Z19>=11.5,Z19<12.5),"Desnutrición aguda moderada",IF(AND(Z19>=6,Z19<9),"Referencia valoración médica",IF(Z19<6,"Dato inválido",IF(Z19>35,"Dato inválido"))))))) -> ERROR | AE19: =IF(ISBLANK(AD19),"ERROR",IF(AND(AD19>3,AD19<5),"Obesidad",IF(AND(AD19>2,AD19<=3),"Sobrepeso",IF(AND(AD19<=2,AD19>=-2),"Adecuado",IF(AND(AD19>=-3,AD19<-2),"Desnutrición aguda moderada",IF(AND(AD19<-3,AD19>-5),"Desnutrición aguda severa",IF(AD19<=-5,"Dato inválido",IF(AD19>=5,"Dato inválido")))))))) -> ERROR | AR19: =IF(D19="","",TEXT(S19,"MMMM")) | AS19: =IF(F19="","",TEXT(S19,"YYYY")) | AT19: =B19&" - "&E19 -> - | AU19: =IFERROR(VLOOKUP(B19,adm!$C$2:$E$36,3,FALSE),"")
A20: 19 | N20: =AU20&R20&A20 -> 19 | T20: =IF(R20="","",(S20-R20)/365) | U20: =IF(R20="","",IF(T20<=0.6,"0-6 meses",IF(T20<=2,"7-23 meses",IF(T20<=5,"24-59 meses",IF(T20>5,"Mayor a 5 años"))))) | AA20: =IF(ISBLANK(Z20),"ERROR",IF(AND(Z20>=12.5,Z20<=35),"Adecuado",IF(AND(Z20<11.5,Z20>=9),"Desnutrición aguda severa",IF(AND(Z20>=11.5,Z20<12.5),"Desnutrición aguda moderada",IF(AND(Z20>=6,Z20<9),"Referencia valoración médica",IF(Z20<6,"Dato inválido",IF(Z20>35,"Dato inválido"))))))) -> ERROR | AE20: =IF(ISBLANK(AD20),"ERROR",IF(AND(AD20>3,AD20<5),"Obesidad",IF(AND(AD20>2,AD20<=3),"Sobrepeso",IF(AND(AD20<=2,AD20>=-2),"Adecuado",IF(AND(AD20>=-3,AD20<-2),"Desnutrición aguda moderada",IF(AND(AD20<-3,AD20>-5),"Desnutrición aguda severa",IF(AD20<=-5,"Dato inválido",IF(AD20>=5,"Dato inválido")))))))) -> ERROR | AR20: =IF(D20="","",TEXT(S20,"MMMM")) | AS20: =IF(F20="","",TEXT(S20,"YYYY")) | AT20: =B20&" - "&E20 -> - | AU20: =IFERROR(VLOOKUP(B20,adm!$C$2:$E$36,3,FALSE),"")
A21: 20 | N21: =AU21&R21&A21 -> 20 | T21: =IF(R21="","",(S21-R21)/365) | U21: =IF(R21="","",IF(T21<=0.6,"0-6 meses",IF(T21<=2,"7-23 meses",IF(T21<=5,"24-59 meses",IF(T21>5,"Mayor a 5 años"))))) | AA21: =IF(ISBLANK(Z21),"ERROR",IF(AND(Z21>=12.5,Z21<=35),"Adecuado",IF(AND(Z21<11.5,Z21>=9),"Desnutrición aguda severa",IF(AND(Z21>=11.5,Z21<12.5),"Desnutrición aguda moderada",IF(AND(Z21>=6,Z21<9),"Referencia valoración médica",IF(Z21<6,"Dato inválido",IF(Z21>35,"Dato inválido"))))))) -> ERROR | AE21: =IF(ISBLANK(AD21),"ERROR",IF(AND(AD21>3,AD21<5),"Obesidad",IF(AND(AD21>2,AD21<=3),"Sobrepeso",IF(AND(AD21<=2,AD21>=-2),"Adecuado",IF(AND(AD21>=-3,AD21<-2),"Desnutrición aguda moderada",IF(AND(AD21<-3,AD21>-5),"Desnutrición aguda severa",IF(AD21<=-5,"Dato inválido",IF(AD21>=5,"Dato inválido")))))))) -> ERROR | AR21: =IF(D21="","",TEXT(S21,"MMMM")) | AS21: =IF(F21="","",TEXT(S21,"YYYY")) | AT21: =B21&" - "&E21 -> - | AU21: =IFERROR(VLOOKUP(B21,adm!$C$2:$E$36,3,FALSE),"")
A22: 21 | N22: =AU22&R22&A22 -> 21 | T22: =IF(R22="","",(S22-R22)/365) | U22: =IF(R22="","",IF(T22<=0.6,"0-6 meses",IF(T22<=2,"7-23 meses",IF(T22<=5,"24-59 meses",IF(T22>5,"Mayor a 5 años"))))) | AA22: =IF(ISBLANK(Z22),"ERROR",IF(AND(Z22>=12.5,Z22<=35),"Adecuado",IF(AND(Z22<11.5,Z22>=9),"Desnutrición aguda severa",IF(AND(Z22>=11.5,Z22<12.5),"Desnutrición aguda moderada",IF(AND(Z22>=6,Z22<9),"Referencia valoración médica",IF(Z22<6,"Dato inválido",IF(Z22>35,"Dato inválido"))))))) -> ERROR | AE22: =IF(ISBLANK(AD22),"ERROR",IF(AND(AD22>3,AD22<5),"Obesidad",IF(AND(AD22>2,AD22<=3),"Sobrepeso",IF(AND(AD22<=2,AD22>=-2),"Adecuado",IF(AND(AD22>=-3,AD22<-2),"Desnutrición aguda moderada",IF(AND(AD22<-3,AD22>-5),"Desnutrición aguda severa",IF(AD22<=-5,"Dato inválido",IF(AD22>=5,"Dato inválido")))))))) -> ERROR | AR22: =IF(D22="","",TEXT(S22,"MMMM")) | AS22: =IF(F22="","",TEXT(S22,"YYYY")) | AT22: =B22&" - "&E22 -> - | AU22: =IFERROR(VLOOKUP(B22,adm!$C$2:$E$36,3,FALSE),"")
A23: 22 | N23: =AU23&R23&A23 -> 22 | T23: =IF(R23="","",(S23-R23)/365) | U23: =IF(R23="","",IF(T23<=0.6,"0-6 meses",IF(T23<=2,"7-23 meses",IF(T23<=5,"24-59 meses",IF(T23>5,"Mayor a 5 años"))))) | AA23: =IF(ISBLANK(Z23),"ERROR",IF(AND(Z23>=12.5,Z23<=35),"Adecuado",IF(AND(Z23<11.5,Z23>=9),"Desnutrición aguda severa",IF(AND(Z23>=11.5,Z23<12.5),"Desnutrición aguda moderada",IF(AND(Z23>=6,Z23<9),"Referencia valoración médica",IF(Z23<6,"Dato inválido",IF(Z23>35,"Dato inválido"))))))) -> ERROR | AE23: =IF(ISBLANK(AD23),"ERROR",IF(AND(AD23>3,AD23<5),"Obesidad",IF(AND(AD23>2,AD23<=3),"Sobrepeso",IF(AND(AD23<=2,AD23>=-2),"Adecuado",IF(AND(AD23>=-3,AD23<-2),"Desnutrición aguda moderada",IF(AND(AD23<-3,AD23>-5),"Desnutrición aguda severa",IF(AD23<=-5,"Dato inválido",IF(AD23>=5,"Dato inválido")))))))) -> ERROR | AR23: =IF(D23="","",TEXT(S23,"MMMM")) | AS23: =IF(F23="","",TEXT(S23,"YYYY")) | AT23: =B23&" - "&E23 -> - | AU23: =IFERROR(VLOOKUP(B23,adm!$C$2:$E$36,3,FALSE),"")
A24: 23 | N24: =AU24&R24&A24 -> 23 | T24: =IF(R24="","",(S24-R24)/365) | U24: =IF(R24="","",IF(T24<=0.6,"0-6 meses",IF(T24<=2,"7-23 meses",IF(T24<=5,"24-59 meses",IF(T24>5,"Mayor a 5 años"))))) | AA24: =IF(ISBLANK(Z24),"ERROR",IF(AND(Z24>=12.5,Z24<=35),"Adecuado",IF(AND(Z24<11.5,Z24>=9),"Desnutrición aguda severa",IF(AND(Z24>=11.5,Z24<12.5),"Desnutrición aguda moderada",IF(AND(Z24>=6,Z24<9),"Referencia valoración médica",IF(Z24<6,"Dato inválido",IF(Z24>35,"Dato inválido"))))))) -> ERROR | AE24: =IF(ISBLANK(AD24),"ERROR",IF(AND(AD24>3,AD24<5),"Obesidad",IF(AND(AD24>2,AD24<=3),"Sobrepeso",IF(AND(AD24<=2,AD24>=-2),"Adecuado",IF(AND(AD24>=-3,AD24<-2),"Desnutrición aguda moderada",IF(AND(AD24<-3,AD24>-5),"Desnutrición aguda severa",IF(AD24<=-5,"Dato inválido",IF(AD24>=5,"Dato inválido")))))))) -> ERROR | AR24: =IF(D24="","",TEXT(S24,"MMMM")) | AS24: =IF(F24="","",TEXT(S24,"YYYY")) | AT24: =B24&" - "&E24 -> - | AU24: =IFERROR(VLOOKUP(B24,adm!$C$2:$E$36,3,FALSE),"")
A25: 24 | N25: =AU25&R25&A25 -> 24 | T25: =IF(R25="","",(S25-R25)/365) | U25: =IF(R25="","",IF(T25<=0.6,"0-6 meses",IF(T25<=2,"7-23 meses",IF(T25<=5,"24-59 meses",IF(T25>5,"Mayor a 5 años"))))) | AA25: =IF(ISBLANK(Z25),"ERROR",IF(AND(Z25>=12.5,Z25<=35),"Adecuado",IF(AND(Z25<11.5,Z25>=9),"Desnutrición aguda severa",IF(AND(Z25>=11.5,Z25<12.5),"Desnutrición aguda moderada",IF(AND(Z25>=6,Z25<9),"Referencia valoración médica",IF(Z25<6,"Dato inválido",IF(Z25>35,"Dato inválido"))))))) -> ERROR | AE25: =IF(ISBLANK(AD25),"ERROR",IF(AND(AD25>3,AD25<5),"Obesidad",IF(AND(AD25>2,AD25<=3),"Sobrepeso",IF(AND(AD25<=2,AD25>=-2),"Adecuado",IF(AND(AD25>=-3,AD25<-2),"Desnutrición aguda moderada",IF(AND(AD25<-3,AD25>-5),"Desnutrición aguda severa",IF(AD25<=-5,"Dato inválido",IF(AD25>=5,"Dato inválido")))))))) -> ERROR | AR25: =IF(D25="","",TEXT(S25,"MMMM")) | AS25: =IF(F25="","",TEXT(S25,"YYYY")) | AT25: =B25&" - "&E25 -> - | AU25: =IFERROR(VLOOKUP(B25,adm!$C$2:$E$36,3,FALSE),"")
A26: 25 | N26: =AU26&R26&A26 -> 25 | T26: =IF(R26="","",(S26-R26)/365) | U26: =IF(R26="","",IF(T26<=0.6,"0-6 meses",IF(T26<=2,"7-23 meses",IF(T26<=5,"24-59 meses",IF(T26>5,"Mayor a 5 años"))))) | AA26: =IF(ISBLANK(Z26),"ERROR",IF(AND(Z26>=12.5,Z26<=35),"Adecuado",IF(AND(Z26<11.5,Z26>=9),"Desnutrición aguda severa",IF(AND(Z26>=11.5,Z26<12.5),"Desnutrición aguda moderada",IF(AND(Z26>=6,Z26<9),"Referencia valoración médica",IF(Z26<6,"Dato inválido",IF(Z26>35,"Dato inválido"))))))) -> ERROR | AE26: =IF(ISBLANK(AD26),"ERROR",IF(AND(AD26>3,AD26<5),"Obesidad",IF(AND(AD26>2,AD26<=3),"Sobrepeso",IF(AND(AD26<=2,AD26>=-2),"Adecuado",IF(AND(AD26>=-3,AD26<-2),"Desnutrición aguda moderada",IF(AND(AD26<-3,AD26>-5),"Desnutrición aguda severa",IF(AD26<=-5,"Dato inválido",IF(AD26>=5,"Dato inválido")))))))) -> ERROR | AR26: =IF(D26="","",TEXT(S26,"MMMM")) | AS26: =IF(F26="","",TEXT(S26,"YYYY")) | AT26: =B26&" - "&E26 -> - | AU26: =IFERROR(VLOOKUP(B26,adm!$C$2:$E$36,3,FALSE),"")
A27: 26 | N27: =AU27&R27&A27 -> 26 | T27: =IF(R27="","",(S27-R27)/365) | U27: =IF(R27="","",IF(T27<=0.6,"0-6 meses",IF(T27<=2,"7-23 meses",IF(T27<=5,"24-59 meses",IF(T27>5,"Mayor a 5 años"))))) | AA27: =IF(ISBLANK(Z27),"ERROR",IF(AND(Z27>=12.5,Z27<=35),"Adecuado",IF(AND(Z27<11.5,Z27>=9),"Desnutrición aguda severa",IF(AND(Z27>=11.5,Z27<12.5),"Desnutrición aguda moderada",IF(AND(Z27>=6,Z27<9),"Referencia valoración médica",IF(Z27<6,"Dato inválido",IF(Z27>35,"Dato inválido"))))))) -> ERROR | AE27: =IF(ISBLANK(AD27),"ERROR",IF(AND(AD27>3,AD27<5),"Obesidad",IF(AND(AD27>2,AD27<=3),"Sobrepeso",IF(AND(AD27<=2,AD27>=-2),"Adecuado",IF(AND(AD27>=-3,AD27<-2),"Desnutrición aguda moderada",IF(AND(AD27<-3,AD27>-5),"Desnutrición aguda severa",IF(AD27<=-5,"Dato inválido",IF(AD27>=5,"Dato inválido")))))))) -> ERROR | AR27: =IF(D27="","",TEXT(S27,"MMMM")) | AS27: =IF(F27="","",TEXT(S27,"YYYY")) | AT27: =B27&" - "&E27 -> - | AU27: =IFERROR(VLOOKUP(B27,adm!$C$2:$E$36,3,FALSE),"")
A28: 27 | N28: =AU28&R28&A28 -> 27 | T28: =IF(R28="","",(S28-R28)/365) | U28: =IF(R28="","",IF(T28<=0.6,"0-6 meses",IF(T28<=2,"7-23 meses",IF(T28<=5,"24-59 meses",IF(T28>5,"Mayor a 5 años"))))) | AA28: =IF(ISBLANK(Z28),"ERROR",IF(AND(Z28>=12.5,Z28<=35),"Adecuado",IF(AND(Z28<11.5,Z28>=9),"Desnutrición aguda severa",IF(AND(Z28>=11.5,Z28<12.5),"Desnutrición aguda moderada",IF(AND(Z28>=6,Z28<9),"Referencia valoración médica",IF(Z28<6,"Dato inválido",IF(Z28>35,"Dato inválido"))))))) -> ERROR | AE28: =IF(ISBLANK(AD28),"ERROR",IF(AND(AD28>3,AD28<5),"Obesidad",IF(AND(AD28>2,AD28<=3),"Sobrepeso",IF(AND(AD28<=2,AD28>=-2),"Adecuado",IF(AND(AD28>=-3,AD28<-2),"Desnutrición aguda moderada",IF(AND(AD28<-3,AD28>-5),"Desnutrición aguda severa",IF(AD28<=-5,"Dato inválido",IF(AD28>=5,"Dato inválido")))))))) -> ERROR | AR28: =IF(D28="","",TEXT(S28,"MMMM")) | AS28: =IF(F28="","",TEXT(S28,"YYYY")) | AT28: =B28&" - "&E28 -> - | AU28: =IFERROR(VLOOKUP(B28,adm!$C$2:$E$36,3,FALSE),"")
A29: 28 | N29: =AU29&R29&A29 -> 28 | T29: =IF(R29="","",(S29-R29)/365) | U29: =IF(R29="","",IF(T29<=0.6,"0-6 meses",IF(T29<=2,"7-23 meses",IF(T29<=5,"24-59 meses",IF(T29>5,"Mayor a 5 años"))))) | AA29: =IF(ISBLANK(Z29),"ERROR",IF(AND(Z29>=12.5,Z29<=35),"Adecuado",IF(AND(Z29<11.5,Z29>=9),"Desnutrición aguda severa",IF(AND(Z29>=11.5,Z29<12.5),"Desnutrición aguda moderada",IF(AND(Z29>=6,Z29<9),"Referencia valoración médica",IF(Z29<6,"Dato inválido",IF(Z29>35,"Dato inválido"))))))) -> ERROR | AE29: =IF(ISBLANK(AD29),"ERROR",IF(AND(AD29>3,AD29<5),"Obesidad",IF(AND(AD29>2,AD29<=3),"Sobrepeso",IF(AND(AD29<=2,AD29>=-2),"Adecuado",IF(AND(AD29>=-3,AD29<-2),"Desnutrición aguda moderada",IF(AND(AD29<-3,AD29>-5),"Desnutrición aguda severa",IF(AD29<=-5,"Dato inválido",IF(AD29>=5,"Dato inválido")))))))) -> ERROR | AR29: =IF(D29="","",TEXT(S29,"MMMM")) | AS29: =IF(F29="","",TEXT(S29,"YYYY")) | AT29: =B29&" - "&E29 -> - | AU29: =IFERROR(VLOOKUP(B29,adm!$C$2:$E$36,3,FALSE),"")
... A994: 993 | N994: =AU994&R994&A994 -> 993 | T994: =IF(R994="","",(S994-R994)/365) | U994: =IF(R994="","",IF(T994<=0.6,"0-6 meses",IF(T994<=2,"7-23 meses",IF(T994<=5,"24-59 meses",IF(T994>5,"Mayor a 5 años"))))) | AA994: =IF(ISBLANK(Z994),"ERROR",IF(AND(Z994>=12.5,Z994<=35),"Adecuado",IF(AND(Z994<11.5,Z994>=9),"Desnutrición aguda severa",IF(AND(Z994>=11.5,Z994<12.5),"Desnutrición aguda moderada",IF(AND(Z994>=6,Z994<9),"Referencia valoración médica",IF(Z994<6,"Dato inválido",IF(Z994>35,"Dato inválido"))))))) -> ERROR | AE994: =IF(ISBLANK(AD994),"ERROR",IF(AND(AD994>3,AD994<5),"Obesidad",IF(AND(AD994>2,AD994<=3),"Sobrepeso",IF(AND(AD994<=2,AD994>=-2),"Adecuado",IF(AND(AD994>=-3,AD994<-2),"Desnutrición aguda moderada",IF(AND(AD994<-3,AD994>-5),"Desnutrición aguda severa",IF(AD994<=-5,"Dato inválido",IF(AD994>=5,"Dato inválido")))))))) -> ERROR | AR994: =IF(D994="","",TEXT(S994,"MMMM")) | AS994: =IF(F994="","",TEXT(S994,"YYYY")) | AT994: =B994&" - "&E994 -> - | AU994: =IFERROR(VLOOKUP(B994,adm!$C$2:$E$36,3,FALSE),"")

Sheet 2. SAMAN EMBARAZADAS
A1: # | B1: DIOCESIS | C1: ESTADO | D1: MUNICIPIO | E1: PARROQUIA CIVIL | F1: PARROQUIA ECLESIAL / CENTRO CENTINELA | G1: SECTOR O COMUNIDAD | H1: GRUPO ETNICO | I1: Fecha de Medición dd/mm/aaaa | J1: TIPO DE INGRESO | K1: NOMBRE | L1: APELLIDO | M1: CÉDULA DE IDENTIDAD (ingrese números sin espacios) | N1: Fecha de Nacimiento dd/mm/aaaa | O1: EMBARAZADA ó LACTANTE | P1: SEMANA DE GESTACIÓN | Q1: EDAD | R1: EDEMA | S1: PESO (kg) | T1: TALLA (cm) | U1: IMC | V1: CLASIFICACIÓN NUTRICIONAL | W1: BRAZO (CM) | X1: CLASIFICACIÓN NUTRICIONAL PB | Y1: Desparasitada | Z1: Tratamiento suministrado Según Protocolo Cáritas | AA1: CANTIDAD | AB1: Situación de Salida | AC1: Observaciones | AD1: MES | AE1: AÑO | AF1: CENTRO
A2: 1 | Q2: =IF(N2="","",((YEAR(I2)-YEAR(N2))*12+MONTH(I2)-MONTH(N2))/12) | U2: =(S2/((T2/100)*(T2/100))) -> #DIV/0! | V2: =IF(U2<18.5,"Bajo Peso ",IF(AND(U2>=18.5,U2<25),"Adecuado ",IF(AND(U2>=25,U2<30),"Sobrepeso ",IF(U2>=30,"Obesidad","Obesidad")))) -> #DIV/0! | X2: =IF(ISBLANK(W2),"ERROR",IF(AND(W2>=23,W2<=50),"Peso Normal",IF(AND(W2<23,W2>=15),"Bajo peso",IF(W2<15,"Dato inválido",IF(W2>50,"Dato inválido"))))) -> ERROR | AD2: =IF(I2="","",TEXT(I2,"MMMM")) | AE2: =IF(I2="","",TEXT(I2,"YYYY")) | AF2: =Tabla3[[#This Row],[DIOCESIS]]&" "&"-"&" "&Tabla3[[#This Row],[PARROQUIA ECLESIAL / CENTRO CENTINELA]] -> -
A3: =A2+1 -> 2 | Q3: =IF(N3="","",((YEAR(I3)-YEAR(N3))*12+MONTH(I3)-MONTH(N3))/12) | U3: =(S3/((T3/100)*(T3/100))) -> #DIV/0! | V3: =IF(U3<18.5,"Bajo Peso ",IF(AND(U3>=18.5,U3<25),"Adecuado ",IF(AND(U3>=25,U3<30),"Sobrepeso ",IF(U3>=30,"Obesidad","Obesidad")))) -> #DIV/0! | X3: =IF(ISBLANK(W3),"ERROR",IF(AND(W3>=23,W3<=50),"Peso Normal",IF(AND(W3<23,W3>=15),"Bajo peso",IF(W3<15,"Dato inválido",IF(W3>50,"Dato inválido"))))) -> ERROR | AD3: =IF(I3="","",TEXT(I3,"MMMM")) | AE3: =IF(I3="","",TEXT(I3,"YYYY")) | AF3: =Tabla3[[#This Row],[DIOCESIS]]&" "&"-"&" "&Tabla3[[#This Row],[PARROQUIA ECLESIAL / CENTRO CENTINELA]] -> -
A4: =A3+1 -> 3 | Q4: =IF(N4="","",((YEAR(I4)-YEAR(N4))*12+MONTH(I4)-MONTH(N4))/12) | U4: =(S4/((T4/100)*(T4/100))) -> #DIV/0! | V4: =IF(U4<18.5,"Bajo Peso ",IF(AND(U4>=18.5,U4<25),"Adecuado ",IF(AND(U4>=25,U4<30),"Sobrepeso ",IF(U4>=30,"Obesidad","Obesidad")))) -> #DIV/0! | X4: =IF(ISBLANK(W4),"ERROR",IF(AND(W4>=23,W4<=50),"Peso Normal",IF(AND(W4<23,W4>=15),"Bajo peso",IF(W4<15,"Dato inválido",IF(W4>50,"Dato inválido"))))) -> ERROR | AD4: =IF(I4="","",TEXT(I4,"MMMM")) | AE4: =IF(I4="","",TEXT(I4,"YYYY")) | AF4: =Tabla3[[#This Row],[DIOCESIS]]&" "&"-"&" "&Tabla3[[#This Row],[PARROQUIA ECLESIAL / CENTRO CENTINELA]] -> -
A5: =A4+1 -> 4 | Q5: =IF(N5="","",((YEAR(I5)-YEAR(N5))*12+MONTH(I5)-MONTH(N5))/12) | U5: =(S5/((T5/100)*(T5/100))) -> #DIV/0! | V5: =IF(U5<18.5,"Bajo Peso ",IF(AND(U5>=18.5,U5<25),"Adecuado ",IF(AND(U5>=25,U5<30),"Sobrepeso ",IF(U5>=30,"Obesidad","Obesidad")))) -> #DIV/0! | X5: =IF(ISBLANK(W5),"ERROR",IF(AND(W5>=23,W5<=50),"Peso Normal",IF(AND(W5<23,W5>=15),"Bajo peso",IF(W5<15,"Dato inválido",IF(W5>50,"Dato inválido"))))) -> ERROR | AD5: =IF(I5="","",TEXT(I5,"MMMM")) | AE5: =IF(I5="","",TEXT(I5,"YYYY")) | AF5: =Tabla3[[#This Row],[DIOCESIS]]&" "&"-"&" "&Tabla3[[#This Row],[PARROQUIA ECLESIAL / CENTRO CENTINELA]] -> -
A6: =A5+1 -> 5 | Q6: =IF(N6="","",((YEAR(I6)-YEAR(N6))*12+MONTH(I6)-MONTH(N6))/12) | U6: =(S6/((T6/100)*(T6/100))) -> #DIV/0! | V6: =IF(U6<18.5,"Bajo Peso ",IF(AND(U6>=18.5,U6<25),"Adecuado ",IF(AND(U6>=25,U6<30),"Sobrepeso ",IF(U6>=30,"Obesidad","Obesidad")))) -> #DIV/0! | X6: =IF(ISBLANK(W6),"ERROR",IF(AND(W6>=23,W6<=50),"Peso Normal",IF(AND(W6<23,W6>=15),"Bajo peso",IF(W6<15,"Dato inválido",IF(W6>50,"Dato inválido"))))) -> ERROR | AD6: =IF(I6="","",TEXT(I6,"MMMM")) | AE6: =IF(I6="","",TEXT(I6,"YYYY")) | AF6: =Tabla3[[#This Row],[DIOCESIS]]&" "&"-"&" "&Tabla3[[#This Row],[PARROQUIA ECLESIAL / CENTRO CENTINELA]] -> -
A7: =A6+1 -> 6 | Q7: =IF(N7="","",((YEAR(I7)-YEAR(N7))*12+MONTH(I7)-MONTH(N7))/12) | U7: =(S7/((T7/100)*(T7/100))) -> #DIV/0! | V7: =IF(U7<18.5,"Bajo Peso ",IF(AND(U7>=18.5,U7<25),"Adecuado ",IF(AND(U7>=25,U7<30),"Sobrepeso ",IF(U7>=30,"Obesidad","Obesidad")))) -> #DIV/0! | X7: =IF(ISBLANK(W7),"ERROR",IF(AND(W7>=23,W7<=50),"Peso Normal",IF(AND(W7<23,W7>=15),"Bajo peso",IF(W7<15,"Dato inválido",IF(W7>50,"Dato inválido"))))) -> ERROR | AD7: =IF(I7="","",TEXT(I7,"MMMM")) | AE7: =IF(I7="","",TEXT(I7,"YYYY")) | AF7: =Tabla3[[#This Row],[DIOCESIS]]&" "&"-"&" "&Tabla3[[#This Row],[PARROQUIA ECLESIAL / CENTRO CENTINELA]] -> -
A8: =A7+1 -> 7 | Q8: =IF(N8="","",((YEAR(I8)-YEAR(N8))*12+MONTH(I8)-MONTH(N8))/12) | U8: =(S8/((T8/100)*(T8/100))) -> #DIV/0! | V8: =IF(U8<18.5,"Bajo Peso ",IF(AND(U8>=18.5,U8<25),"Adecuado ",IF(AND(U8>=25,U8<30),"Sobrepeso ",IF(U8>=30,"Obesidad","Obesidad")))) -> #DIV/0! | X8: =IF(ISBLANK(W8),"ERROR",IF(AND(W8>=23,W8<=50),"Peso Normal",IF(AND(W8<23,W8>=15),"Bajo peso",IF(W8<15,"Dato inválido",IF(W8>50,"Dato inválido"))))) -> ERROR | AD8: =IF(I8="","",TEXT(I8,"MMMM")) | AE8: =IF(I8="","",TEXT(I8,"YYYY")) | AF8: =Tabla3[[#This Row],[DIOCESIS]]&" "&"-"&" "&Tabla3[[#This Row],[PARROQUIA ECLESIAL / CENTRO CENTINELA]] -> -
A9: =A8+1 -> 8 | Q9: =IF(N9="","",((YEAR(I9)-YEAR(N9))*12+MONTH(I9)-MONTH(N9))/12) | U9: =(S9/((T9/100)*(T9/100))) -> #DIV/0! | V9: =IF(U9<18.5,"Bajo Peso ",IF(AND(U9>=18.5,U9<25),"Adecuado ",IF(AND(U9>=25,U9<30),"Sobrepeso ",IF(U9>=30,"Obesidad","Obesidad")))) -> #DIV/0! | X9: =IF(ISBLANK(W9),"ERROR",IF(AND(W9>=23,W9<=50),"Peso Normal",IF(AND(W9<23,W9>=15),"Bajo peso",IF(W9<15,"Dato inválido",IF(W9>50,"Dato inválido"))))) -> ERROR | AD9: =IF(I9="","",TEXT(I9,"MMMM")) | AE9: =IF(I9="","",TEXT(I9,"YYYY")) | AF9: =Tabla3[[#This Row],[DIOCESIS]]&" "&"-"&" "&Tabla3[[#This Row],[PARROQUIA ECLESIAL / CENTRO CENTINELA]] -> -
A10: =A9+1 -> 9 | Q10: =IF(N10="","",((YEAR(I10)-YEAR(N10))*12+MONTH(I10)-MONTH(N10))/12) | U10: =(S10/((T10/100)*(T10/100))) -> #DIV/0! | V10: =IF(U10<18.5,"Bajo Peso ",IF(AND(U10>=18.5,U10<25),"Adecuado ",IF(AND(U10>=25,U10<30),"Sobrepeso ",IF(U10>=30,"Obesidad","Obesidad")))) -> #DIV/0! | X10: =IF(ISBLANK(W10),"ERROR",IF(AND(W10>=23,W10<=50),"Peso Normal",IF(AND(W10<23,W10>=15),"Bajo peso",IF(W10<15,"Dato inválido",IF(W10>50,"Dato inválido"))))) -> ERROR | AD10: =IF(I10="","",TEXT(I10,"MMMM")) | AE10: =IF(I10="","",TEXT(I10,"YYYY")) | AF10: =Tabla3[[#This Row],[DIOCESIS]]&" "&"-"&" "&Tabla3[[#This Row],[PARROQUIA ECLESIAL / CENTRO CENTINELA]] -> -
A11: =A10+1 -> 10 | Q11: =IF(N11="","",((YEAR(I11)-YEAR(N11))*12+MONTH(I11)-MONTH(N11))/12) | U11: =(S11/((T11/100)*(T11/100))) -> #DIV/0! | V11: =IF(U11<18.5,"Bajo Peso ",IF(AND(U11>=18.5,U11<25),"Adecuado ",IF(AND(U11>=25,U11<30),"Sobrepeso ",IF(U11>=30,"Obesidad","Obesidad")))) -> #DIV/0! | X11: =IF(ISBLANK(W11),"ERROR",IF(AND(W11>=23,W11<=50),"Peso Normal",IF(AND(W11<23,W11>=15),"Bajo peso",IF(W11<15,"Dato inválido",IF(W11>50,"Dato inválido"))))) -> ERROR | AD11: =IF(I11="","",TEXT(I11,"MMMM")) | AE11: =IF(I11="","",TEXT(I11,"YYYY")) | AF11: =Tabla3[[#This Row],[DIOCESIS]]&" "&"-"&" "&Tabla3[[#This Row],[PARROQUIA ECLESIAL / CENTRO CENTINELA]] -> -
A12: =A11+1 -> 11 | Q12: =IF(N12="","",((YEAR(I12)-YEAR(N12))*12+MONTH(I12)-MONTH(N12))/12) | U12: =(S12/((T12/100)*(T12/100))) -> #DIV/0! | V12: =IF(U12<18.5,"Bajo Peso ",IF(AND(U12>=18.5,U12<25),"Adecuado ",IF(AND(U12>=25,U12<30),"Sobrepeso ",IF(U12>=30,"Obesidad","Obesidad")))) -> #DIV/0! | X12: =IF(ISBLANK(W12),"ERROR",IF(AND(W12>=23,W12<=50),"Peso Normal",IF(AND(W12<23,W12>=15),"Bajo peso",IF(W12<15,"Dato inválido",IF(W12>50,"Dato inválido"))))) -> ERROR | AD12: =IF(I12="","",TEXT(I12,"MMMM")) | AE12: =IF(I12="","",TEXT(I12,"YYYY")) | AF12: =Tabla3[[#This Row],[DIOCESIS]]&" "&"-"&" "&Tabla3[[#This Row],[PARROQUIA ECLESIAL / CENTRO CENTINELA]] -> -
A13: =A12+1 -> 12 | Q13: =IF(N13="","",((YEAR(I13)-YEAR(N13))*12+MONTH(I13)-MONTH(N13))/12) | U13: =(S13/((T13/100)*(T13/100))) -> #DIV/0! | V13: =IF(U13<18.5,"Bajo Peso ",IF(AND(U13>=18.5,U13<25),"Adecuado ",IF(AND(U13>=25,U13<30),"Sobrepeso ",IF(U13>=30,"Obesidad","Obesidad")))) -> #DIV/0! | X13: =IF(ISBLANK(W13),"ERROR",IF(AND(W13>=23,W13<=50),"Peso Normal",IF(AND(W13<23,W13>=15),"Bajo peso",IF(W13<15,"Dato inválido",IF(W13>50,"Dato inválido"))))) -> ERROR | AD13: =IF(I13="","",TEXT(I13,"MMMM")) | AE13: =IF(I13="","",TEXT(I13,"YYYY")) | AF13: =Tabla3[[#This Row],[DIOCESIS]]&" "&"-"&" "&Tabla3[[#This Row],[PARROQUIA ECLESIAL / CENTRO CENTINELA]] -> -
A14: =A13+1 -> 13 | Q14: =IF(N14="","",((YEAR(I14)-YEAR(N14))*12+MONTH(I14)-MONTH(N14))/12) | U14: =(S14/((T14/100)*(T14/100))) -> #DIV/0! | V14: =IF(U14<18.5,"Bajo Peso ",IF(AND(U14>=18.5,U14<25),"Adecuado ",IF(AND(U14>=25,U14<30),"Sobrepeso ",IF(U14>=30,"Obesidad","Obesidad")))) -> #DIV/0! | X14: =IF(ISBLANK(W14),"ERROR",IF(AND(W14>=23,W14<=50),"Peso Normal",IF(AND(W14<23,W14>=15),"Bajo peso",IF(W14<15,"Dato inválido",IF(W14>50,"Dato inválido"))))) -> ERROR | AD14: =IF(I14="","",TEXT(I14,"MMMM")) | AE14: =IF(I14="","",TEXT(I14,"YYYY")) | AF14: =Tabla3[[#This Row],[DIOCESIS]]&" "&"-"&" "&Tabla3[[#This Row],[PARROQUIA ECLESIAL / CENTRO CENTINELA]] -> -
... A100: =A99+1 -> 99 | Q100: =IF(N100="","",((YEAR(I100)-YEAR(N100))*12+MONTH(I100)-MONTH(N100))/12) | U100: =(S100/((T100/100)*(T100/100))) -> #DIV/0! | V100: =IF(U100<18.5,"Bajo Peso ",IF(AND(U100>=18.5,U100<25),"Adecuado ",IF(AND(U100>=25,U100<30),"Sobrepeso ",IF(U100>=30,"Obesidad","Obesidad")))) -> #DIV/0! | X100: =IF(ISBLANK(W100),"ERROR",IF(AND(W100>=23,W100<=50),"Peso Normal",IF(AND(W100<23,W100>=15),"Bajo peso",IF(W100<15,"Dato inválido",IF(W100>50,"Dato inválido"))))) -> ERROR | AD100: =IF(I100="","",TEXT(I100,"MMMM")) | AE100: =IF(I100="","",TEXT(I100,"YYYY")) | AF100: =Tabla3[[#This Row],[DIOCESIS]]&" "&"-"&" "&Tabla3[[#This Row],[PARROQUIA ECLESIAL / CENTRO CENTINELA]] -> -

Sheet 3. DESPARASITACIÓN
A1: N° | B1: FECHA DE ATENCIÓN dd/mm/aaaa | C1: DIOCESIS | D1: ESTADO | E1: MUNICIPIO | F1: PARROQUIA CIVIL | G1: PARROQUIA ECLESIAL/ CENTRO CENTINELA | H1: SECTOR O COMUNIDAD | I1: Total de niños desparasitados | J1: Total de niñas desparasitadas | K1: Observaciones
A2: 1
A3: 2
A4: 3
A5: 4
A6: 5
A7: 6
A8: 7
A9: 8
A10: 9
A11: 10
A12: 11
A13: 12
... A101: 100

Sheet 4. ACTIVIDADES
B1: ¿CUÁNDO? | C1: ¿DÓNDE? | I1: ¿QUÉ? | M1: Grupos poblacionales (de losbeneficiarios desagregados indique cuántos pertenecen a los siguientes grupos) | P1: Beneficiarios desagregados | Y1: OBSERVACIONES
A2: Nº | B2: Fecha de la actividad | C2: Diocesis | D2: Estado | E2: Municipio | F2: Parroquia Civil | G2: Parroquia Eclesial/ Centro Centinela | H2: Sector o comunidad de la actividad | I2: Actividad | J2: Detalle de la Actividad | K2: Proyecto | L2: Detalle del Beneficiario | M2: Actividad con beneficiarios recurrentes | N2: Número de Población Indígena | O2: Número de Personas con discapacidad | P2: Niñas de 0 a 5 años | Q2: Niños de 0 a 5 años | R2: Niñas de 6 a 17 años | S2: Niños de 6 a 17 años | T2: Mujeres de 18 a 64 años | U2: Hombres de 18 a 64 años | V2: Mujeres de 65 años o más | W2: Hombres de 65 años o más | X2: Total personas asistidas | Z2: Autorellenado Validacion_Estado | AA2: Autorellenado Validacion_Municipio | AB2: Autorellenado Validacion_Parroquia | AC2: ConcateEstasoMuni | AD2: PCODE1 | AE2: PCODE2 | AF2: PCODE3
A3: 1 | X3: =SUM(P3:W3) -> 0 | Z3: =IFERROR(IF(MATCH(D3,[1]!Table374[NAMEESTADO],0),"VALIDO"),"INVALIDO") -> INVALIDO | AA3: =IFERROR(IF(MATCH(CONCATENATE(D3,E3),[1]!Table486[ConcateMuni],0),"VALIDO"),"INVALIDO") -> INVALIDO | AB3: =IFERROR(IF(MATCH(CONCATENATE(D3,E3,F3),[1]!Table109[ConcateParro],0),"VALIDO"),"INVALIDO") -> INVALIDO | AC3: =CONCATENATE(D3,E3) | AD3: =IFERROR(INDEX([1]!Table374[PCODEESTADO],MATCH(D3,[1]!Table374[NAMEESTADO],0)),"") | AE3: =IFERROR(INDEX([1]!Table486[PCODEMUNI],MATCH(D3&E3,[1]!Table486[ConcateMuni],0)),"") | AF3: =IFERROR(INDEX([1]!Table109[PCODEPARROQUIA],MATCH(D3&E3&F3,[1]!Table109[ConcateParro],0)),"")
A4: 2 | X4: =SUM(P4:W4) -> 0 | Z4: =IFERROR(IF(MATCH(D4,[1]!Table374[NAMEESTADO],0),"VALIDO"),"INVALIDO") -> INVALIDO | AA4: =IFERROR(IF(MATCH(CONCATENATE(D4,E4),[1]!Table486[ConcateMuni],0),"VALIDO"),"INVALIDO") -> INVALIDO | AB4: =IFERROR(IF(MATCH(CONCATENATE(D4,E4,F4),[1]!Table109[ConcateParro],0),"VALIDO"),"INVALIDO") -> INVALIDO | AC4: =CONCATENATE(D4,E4) | AD4: =IFERROR(INDEX([1]!Table374[PCODEESTADO],MATCH(D4,[1]!Table374[NAMEESTADO],0)),"") | AE4: =IFERROR(INDEX([1]!Table486[PCODEMUNI],MATCH(D4&E4,[1]!Table486[ConcateMuni],0)),"") | AF4: =IFERROR(INDEX([1]!Table109[PCODEPARROQUIA],MATCH(D4&E4&F4,[1]!Table109[ConcateParro],0)),"")
A5: 3 | X5: =SUM(P5:W5) -> 0 | Z5: =IFERROR(IF(MATCH(D5,[1]!Table374[NAMEESTADO],0),"VALIDO"),"INVALIDO") -> INVALIDO | AA5: =IFERROR(IF(MATCH(CONCATENATE(D5,E5),[1]!Table486[ConcateMuni],0),"VALIDO"),"INVALIDO") -> INVALIDO | AB5: =IFERROR(IF(MATCH(CONCATENATE(D5,E5,F5),[1]!Table109[ConcateParro],0),"VALIDO"),"INVALIDO") -> INVALIDO | AC5: =CONCATENATE(D5,E5) | AD5: =IFERROR(INDEX([1]!Table374[PCODEESTADO],MATCH(D5,[1]!Table374[NAMEESTADO],0)),"") | AE5: =IFERROR(INDEX([1]!Table486[PCODEMUNI],MATCH(D5&E5,[1]!Table486[ConcateMuni],0)),"") | AF5: =IFERROR(INDEX([1]!Table109[PCODEPARROQUIA],MATCH(D5&E5&F5,[1]!Table109[ConcateParro],0)),"")
A6: 4 | X6: =SUM(P6:W6) -> 0 | Z6: =IFERROR(IF(MATCH(D6,[1]!Table374[NAMEESTADO],0),"VALIDO"),"INVALIDO") -> INVALIDO | AA6: =IFERROR(IF(MATCH(CONCATENATE(D6,E6),[1]!Table486[ConcateMuni],0),"VALIDO"),"INVALIDO") -> INVALIDO | AB6: =IFERROR(IF(MATCH(CONCATENATE(D6,E6,F6),[1]!Table109[ConcateParro],0),"VALIDO"),"INVALIDO") -> INVALIDO | AC6: =CONCATENATE(D6,E6) | AD6: =IFERROR(INDEX([1]!Table374[PCODEESTADO],MATCH(D6,[1]!Table374[NAMEESTADO],0)),"") | AE6: =IFERROR(INDEX([1]!Table486[PCODEMUNI],MATCH(D6&E6,[1]!Table486[ConcateMuni],0)),"") | AF6: =IFERROR(INDEX([1]!Table109[PCODEPARROQUIA],MATCH(D6&E6&F6,[1]!Table109[ConcateParro],0)),"")
A7: 5 | X7: =SUM(P7:W7) -> 0 | Z7: =IFERROR(IF(MATCH(D7,[1]!Table374[NAMEESTADO],0),"VALIDO"),"INVALIDO") -> INVALIDO | AA7: =IFERROR(IF(MATCH(CONCATENATE(D7,E7),[1]!Table486[ConcateMuni],0),"VALIDO"),"INVALIDO") -> INVALIDO | AB7: =IFERROR(IF(MATCH(CONCATENATE(D7,E7,F7),[1]!Table109[ConcateParro],0),"VALIDO"),"INVALIDO") -> INVALIDO | AC7: =CONCATENATE(D7,E7) | AD7: =IFERROR(INDEX([1]!Table374[PCODEESTADO],MATCH(D7,[1]!Table374[NAMEESTADO],0)),"") | AE7: =IFERROR(INDEX([1]!Table486[PCODEMUNI],MATCH(D7&E7,[1]!Table486[ConcateMuni],0)),"") | AF7: =IFERROR(INDEX([1]!Table109[PCODEPARROQUIA],MATCH(D7&E7&F7,[1]!Table109[ConcateParro],0)),"")
A8: 6 | X8: =SUM(P8:W8) -> 0 | Z8: =IFERROR(IF(MATCH(D8,[1]!Table374[NAMEESTADO],0),"VALIDO"),"INVALIDO") -> INVALIDO | AA8: =IFERROR(IF(MATCH(CONCATENATE(D8,E8),[1]!Table486[ConcateMuni],0),"VALIDO"),"INVALIDO") -> INVALIDO | AB8: =IFERROR(IF(MATCH(CONCATENATE(D8,E8,F8),[1]!Table109[ConcateParro],0),"VALIDO"),"INVALIDO") -> INVALIDO | AC8: =CONCATENATE(D8,E8) | AD8: =IFERROR(INDEX([1]!Table374[PCODEESTADO],MATCH(D8,[1]!Table374[NAMEESTADO],0)),"") | AE8: =IFERROR(INDEX([1]!Table486[PCODEMUNI],MATCH(D8&E8,[1]!Table486[ConcateMuni],0)),"") | AF8: =IFERROR(INDEX([1]!Table109[PCODEPARROQUIA],MATCH(D8&E8&F8,[1]!Table109[ConcateParro],0)),"")
A9: 7 | X9: =SUM(P9:W9) -> 0 | Z9: =IFERROR(IF(MATCH(D9,[1]!Table374[NAMEESTADO],0),"VALIDO"),"INVALIDO") -> INVALIDO | AA9: =IFERROR(IF(MATCH(CONCATENATE(D9,E9),[1]!Table486[ConcateMuni],0),"VALIDO"),"INVALIDO") -> INVALIDO | AB9: =IFERROR(IF(MATCH(CONCATENATE(D9,E9,F9),[1]!Table109[ConcateParro],0),"VALIDO"),"INVALIDO") -> INVALIDO | AC9: =CONCATENATE(D9,E9) | AD9: =IFERROR(INDEX([1]!Table374[PCODEESTADO],MATCH(D9,[1]!Table374[NAMEESTADO],0)),"") | AE9: =IFERROR(INDEX([1]!Table486[PCODEMUNI],MATCH(D9&E9,[1]!Table486[ConcateMuni],0)),"") | AF9: =IFERROR(INDEX([1]!Table109[PCODEPARROQUIA],MATCH(D9&E9&F9,[1]!Table109[ConcateParro],0)),"")
A10: 8 | X10: =SUM(P10:W10) -> 0 | Z10: =IFERROR(IF(MATCH(D10,[1]!Table374[NAMEESTADO],0),"VALIDO"),"INVALIDO") -> INVALIDO | AA10: =IFERROR(IF(MATCH(CONCATENATE(D10,E10),[1]!Table486[ConcateMuni],0),"VALIDO"),"INVALIDO") -> INVALIDO | AB10: =IFERROR(IF(MATCH(CONCATENATE(D10,E10,F10),[1]!Table109[ConcateParro],0),"VALIDO"),"INVALIDO") -> INVALIDO | AC10: =CONCATENATE(D10,E10) | AD10: =IFERROR(INDEX([1]!Table374[PCODEESTADO],MATCH(D10,[1]!Table374[NAMEESTADO],0)),"") | AE10: =IFERROR(INDEX([1]!Table486[PCODEMUNI],MATCH(D10&E10,[1]!Table486[ConcateMuni],0)),"") | AF10: =IFERROR(INDEX([1]!Table109[PCODEPARROQUIA],MATCH(D10&E10&F10,[1]!Table109[ConcateParro],0)),"")
A11: 9 | X11: =SUM(P11:W11) -> 0 | Z11: =IFERROR(IF(MATCH(D11,[1]!Table374[NAMEESTADO],0),"VALIDO"),"INVALIDO") -> INVALIDO | AA11: =IFERROR(IF(MATCH(CONCATENATE(D11,E11),[1]!Table486[ConcateMuni],0),"VALIDO"),"INVALIDO") -> INVALIDO | AB11: =IFERROR(IF(MATCH(CONCATENATE(D11,E11,F11),[1]!Table109[ConcateParro],0),"VALIDO"),"INVALIDO") -> INVALIDO | AC11: =CONCATENATE(D11,E11) | AD11: =IFERROR(INDEX([1]!Table374[PCODEESTADO],MATCH(D11,[1]!Table374[NAMEESTADO],0)),"") | AE11: =IFERROR(INDEX([1]!Table486[PCODEMUNI],MATCH(D11&E11,[1]!Table486[ConcateMuni],0)),"") | AF11: =IFERROR(INDEX([1]!Table109[PCODEPARROQUIA],MATCH(D11&E11&F11,[1]!Table109[ConcateParro],0)),"")
A12: 10 | X12: =SUM(P12:W12) -> 0 | Z12: =IFERROR(IF(MATCH(D12,[1]!Table374[NAMEESTADO],0),"VALIDO"),"INVALIDO") -> INVALIDO | AA12: =IFERROR(IF(MATCH(CONCATENATE(D12,E12),[1]!Table486[ConcateMuni],0),"VALIDO"),"INVALIDO") -> INVALIDO | AB12: =IFERROR(IF(MATCH(CONCATENATE(D12,E12,F12),[1]!Table109[ConcateParro],0),"VALIDO"),"INVALIDO") -> INVALIDO | AC12: =CONCATENATE(D12,E12) | AD12: =IFERROR(INDEX([1]!Table374[PCODEESTADO],MATCH(D12,[1]!Table374[NAMEESTADO],0)),"") | AE12: =IFERROR(INDEX([1]!Table486[PCODEMUNI],MATCH(D12&E12,[1]!Table486[ConcateMuni],0)),"") | AF12: =IFERROR(INDEX([1]!Table109[PCODEPARROQUIA],MATCH(D12&E12&F12,[1]!Table109[ConcateParro],0)),"")
A13: 11 | X13: =SUM(P13:W13) -> 0 | Z13: =IFERROR(IF(MATCH(D13,[1]!Table374[NAMEESTADO],0),"VALIDO"),"INVALIDO") -> INVALIDO | AA13: =IFERROR(IF(MATCH(CONCATENATE(D13,E13),[1]!Table486[ConcateMuni],0),"VALIDO"),"INVALIDO") -> INVALIDO | AB13: =IFERROR(IF(MATCH(CONCATENATE(D13,E13,F13),[1]!Table109[ConcateParro],0),"VALIDO"),"INVALIDO") -> INVALIDO | AC13: =CONCATENATE(D13,E13) | AD13: =IFERROR(INDEX([1]!Table374[PCODEESTADO],MATCH(D13,[1]!Table374[NAMEESTADO],0)),"") | AE13: =IFERROR(INDEX([1]!Table486[PCODEMUNI],MATCH(D13&E13,[1]!Table486[ConcateMuni],0)),"") | AF13: =IFERROR(INDEX([1]!Table109[PCODEPARROQUIA],MATCH(D13&E13&F13,[1]!Table109[ConcateParro],0)),"")
A14: 12 | X14: =SUM(P14:W14) -> 0 | Z14: =IFERROR(IF(MATCH(D14,[1]!Table374[NAMEESTADO],0),"VALIDO"),"INVALIDO") -> INVALIDO | AA14: =IFERROR(IF(MATCH(CONCATENATE(D14,E14),[1]!Table486[ConcateMuni],0),"VALIDO"),"INVALIDO") -> INVALIDO | AB14: =IFERROR(IF(MATCH(CONCATENATE(D14,E14,F14),[1]!Table109[ConcateParro],0),"VALIDO"),"INVALIDO") -> INVALIDO | AC14: =CONCATENATE(D14,E14) | AD14: =IFERROR(INDEX([1]!Table374[PCODEESTADO],MATCH(D14,[1]!Table374[NAMEESTADO],0)),"") | AE14: =IFERROR(INDEX([1]!Table486[PCODEMUNI],MATCH(D14&E14,[1]!Table486[ConcateMuni],0)),"") | AF14: =IFERROR(INDEX([1]!Table109[PCODEPARROQUIA],MATCH(D14&E14&F14,[1]!Table109[ConcateParro],0)),"")
... A150: 148 | X150: =SUM(P150:W150) -> 0 | Z150: =IFERROR(IF(MATCH(D150,[1]!Table374[NAMEESTADO],0),"VALIDO"),"INVALIDO") -> INVALIDO | AA150: =IFERROR(IF(MATCH(CONCATENATE(D150,E150),[1]!Table486[ConcateMuni],0),"VALIDO"),"INVALIDO") -> INVALIDO | AB150: =IFERROR(IF(MATCH(CONCATENATE(D150,E150,F150),[1]!Table109[ConcateParro],0),"VALIDO"),"INVALIDO") -> INVALIDO | AC150: =CONCATENATE(D150,E150) | AD150: =IFERROR(INDEX([1]!Table374[PCODEESTADO],MATCH(D150,[1]!Table374[NAMEESTADO],0)),"") | AE150: =IFERROR(INDEX([1]!Table486[PCODEMUNI],MATCH(D150&E150,[1]!Table486[ConcateMuni],0)),"") | AF150: =IFERROR(INDEX([1]!Table109[PCODEPARROQUIA],MATCH(D150&E150&F150,[1]!Table109[ConcateParro],0)),"")
A151: 149 | Z151: =IFERROR(IF(MATCH(D151,[1]!Table374[NAMEESTADO],0),"VALIDO"),"INVALIDO") -> INVALIDO | AA151: =IFERROR(IF(MATCH(CONCATENATE(D151,E151),[1]!Table486[ConcateMuni],0),"VALIDO"),"INVALIDO") -> INVALIDO | AB151: =IFERROR(IF(MATCH(CONCATENATE(D151,E151,F151),[1]!Table109[ConcateParro],0),"VALIDO"),"INVALIDO") -> INVALIDO | AC151: =CONCATENATE(D151,E151) | AD151: =IFERROR(INDEX([1]!Table374[PCODEESTADO],MATCH(D151,[1]!Table374[NAMEESTADO],0)),"") | AE151: =IFERROR(INDEX([1]!Table486[PCODEMUNI],MATCH(D151&E151,[1]!Table486[ConcateMuni],0)),"") | AF151: =IFERROR(INDEX([1]!Table109[PCODEPARROQUIA],MATCH(D151&E151&F151,[1]!Table109[ConcateParro],0)),"")
A152: 150 | Z152: =IFERROR(IF(MATCH(D152,[1]!Table374[NAMEESTADO],0),"VALIDO"),"INVALIDO") -> INVALIDO | AA152: =IFERROR(IF(MATCH(CONCATENATE(D152,E152),[1]!Table486[ConcateMuni],0),"VALIDO"),"INVALIDO") -> INVALIDO | AB152: =IFERROR(IF(MATCH(CONCATENATE(D152,E152,F152),[1]!Table109[ConcateParro],0),"VALIDO"),"INVALIDO") -> INVALIDO | AC152: =CONCATENATE(D152,E152) | AD152: =IFERROR(INDEX([1]!Table374[PCODEESTADO],MATCH(D152,[1]!Table374[NAMEESTADO],0)),"") | AE152: =IFERROR(INDEX([1]!Table486[PCODEMUNI],MATCH(D152&E152,[1]!Table486[ConcateMuni],0)),"") | AF152: =IFERROR(INDEX([1]!Table109[PCODEPARROQUIA],MATCH(D152&E152&F152,[1]!Table109[ConcateParro],0)),"")
A153: 151 | Z153: =IFERROR(IF(MATCH(D153,[1]!Table374[NAMEESTADO],0),"VALIDO"),"INVALIDO") -> INVALIDO | AA153: =IFERROR(IF(MATCH(CONCATENATE(D153,E153),[1]!Table486[ConcateMuni],0),"VALIDO"),"INVALIDO") -> INVALIDO | AB153: =IFERROR(IF(MATCH(CONCATENATE(D153,E153,F153),[1]!Table109[ConcateParro],0),"VALIDO"),"INVALIDO") -> INVALIDO | AC153: =CONCATENATE(D153,E153) | AD153: =IFERROR(INDEX([1]!Table374[PCODEESTADO],MATCH(D153,[1]!Table374[NAMEESTADO],0)),"") | AE153: =IFERROR(INDEX([1]!Table486[PCODEMUNI],MATCH(D153&E153,[1]!Table486[ConcateMuni],0)),"") | AF153: =IFERROR(INDEX([1]!Table109[PCODEPARROQUIA],MATCH(D153&E153&F153,[1]!Table109[ConcateParro],0)),"")
A154: 152 | Z154: =IFERROR(IF(MATCH(D154,[1]!Table374[NAMEESTADO],0),"VALIDO"),"INVALIDO") -> INVALIDO | AA154: =IFERROR(IF(MATCH(CONCATENATE(D154,E154),[1]!Table486[ConcateMuni],0),"VALIDO"),"INVALIDO") -> INVALIDO | AB154: =IFERROR(IF(MATCH(CONCATENATE(D154,E154,F154),[1]!Table109[ConcateParro],0),"VALIDO"),"INVALIDO") -> INVALIDO | AC154: =CONCATENATE(D154,E154) | AD154: =IFERROR(INDEX([1]!Table374[PCODEESTADO],MATCH(D154,[1]!Table374[NAMEESTADO],0)),"") | AE154: =IFERROR(INDEX([1]!Table486[PCODEMUNI],MATCH(D154&E154,[1]!Table486[ConcateMuni],0)),"") | AF154: =IFERROR(INDEX([1]!Table109[PCODEPARROQUIA],MATCH(D154&E154&F154,[1]!Table109[ConcateParro],0)),"")
A155: 153 | Z155: =IFERROR(IF(MATCH(D155,[1]!Table374[NAMEESTADO],0),"VALIDO"),"INVALIDO") -> INVALIDO | AA155: =IFERROR(IF(MATCH(CONCATENATE(D155,E155),[1]!Table486[ConcateMuni],0),"VALIDO"),"INVALIDO") -> INVALIDO | AB155: =IFERROR(IF(MATCH(CONCATENATE(D155,E155,F155),[1]!Table109[ConcateParro],0),"VALIDO"),"INVALIDO") -> INVALIDO | AC155: =CONCATENATE(D155,E155) | AD155: =IFERROR(INDEX([1]!Table374[PCODEESTADO],MATCH(D155,[1]!Table374[NAMEESTADO],0)),"") | AE155: =IFERROR(INDEX([1]!Table486[PCODEMUNI],MATCH(D155&E155,[1]!Table486[ConcateMuni],0)),"") | AF155: =IFERROR(INDEX([1]!Table109[PCODEPARROQUIA],MATCH(D155&E155&F155,[1]!Table109[ConcateParro],0)),"")
A156: 154 | Z156: =IFERROR(IF(MATCH(D156,[1]!Table374[NAMEESTADO],0),"VALIDO"),"INVALIDO") -> INVALIDO | AA156: =IFERROR(IF(MATCH(CONCATENATE(D156,E156),[1]!Table486[ConcateMuni],0),"VALIDO"),"INVALIDO") -> INVALIDO | AB156: =IFERROR(IF(MATCH(CONCATENATE(D156,E156,F156),[1]!Table109[ConcateParro],0),"VALIDO"),"INVALIDO") -> INVALIDO | AC156: =CONCATENATE(D156,E156) | AD156: =IFERROR(INDEX([1]!Table374[PCODEESTADO],MATCH(D156,[1]!Table374[NAMEESTADO],0)),"") | AE156: =IFERROR(INDEX([1]!Table486[PCODEMUNI],MATCH(D156&E156,[1]!Table486[ConcateMuni],0)),"") | AF156: =IFERROR(INDEX([1]!Table109[PCODEPARROQUIA],MATCH(D156&E156&F156,[1]!Table109[ConcateParro],0)),"")
A157: 155 | Z157: =IFERROR(IF(MATCH(D157,[1]!Table374[NAMEESTADO],0),"VALIDO"),"INVALIDO") -> INVALIDO | AA157: =IFERROR(IF(MATCH(CONCATENATE(D157,E157),[1]!Table486[ConcateMuni],0),"VALIDO"),"INVALIDO") -> INVALIDO | AB157: =IFERROR(IF(MATCH(CONCATENATE(D157,E157,F157),[1]!Table109[ConcateParro],0),"VALIDO"),"INVALIDO") -> INVALIDO | AC157: =CONCATENATE(D157,E157) | AD157: =IFERROR(INDEX([1]!Table374[PCODEESTADO],MATCH(D157,[1]!Table374[NAMEESTADO],0)),"") | AE157: =IFERROR(INDEX([1]!Table486[PCODEMUNI],MATCH(D157&E157,[1]!Table486[ConcateMuni],0)),"") | AF157: =IFERROR(INDEX([1]!Table109[PCODEPARROQUIA],MATCH(D157&E157&F157,[1]!Table109[ConcateParro],0)),"")
A158: 156 | Z158: =IFERROR(IF(MATCH(D158,[1]!Table374[NAMEESTADO],0),"VALIDO"),"INVALIDO") -> INVALIDO | AA158: =IFERROR(IF(MATCH(CONCATENATE(D158,E158),[1]!Table486[ConcateMuni],0),"VALIDO"),"INVALIDO") -> INVALIDO | AB158: =IFERROR(IF(MATCH(CONCATENATE(D158,E158,F158),[1]!Table109[ConcateParro],0),"VALIDO"),"INVALIDO") -> INVALIDO | AC158: =CONCATENATE(D158,E158) | AD158: =IFERROR(INDEX([1]!Table374[PCODEESTADO],MATCH(D158,[1]!Table374[NAMEESTADO],0)),"") | AE158: =IFERROR(INDEX([1]!Table486[PCODEMUNI],MATCH(D158&E158,[1]!Table486[ConcateMuni],0)),"") | AF158: =IFERROR(INDEX([1]!Table109[PCODEPARROQUIA],MATCH(D158&E158&F158,[1]!Table109[ConcateParro],0)),"")
A159: 157 | Z159: =IFERROR(IF(MATCH(D159,[1]!Table374[NAMEESTADO],0),"VALIDO"),"INVALIDO") -> INVALIDO | AA159: =IFERROR(IF(MATCH(CONCATENATE(D159,E159),[1]!Table486[ConcateMuni],0),"VALIDO"),"INVALIDO") -> INVALIDO | AB159: =IFERROR(IF(MATCH(CONCATENATE(D159,E159,F159),[1]!Table109[ConcateParro],0),"VALIDO"),"INVALIDO") -> INVALIDO | AC159: =CONCATENATE(D159,E159) | AD159: =IFERROR(INDEX([1]!Table374[PCODEESTADO],MATCH(D159,[1]!Table374[NAMEESTADO],0)),"") | AE159: =IFERROR(INDEX([1]!Table486[PCODEMUNI],MATCH(D159&E159,[1]!Table486[ConcateMuni],0)),"") | AF159: =IFERROR(INDEX([1]!Table109[PCODEPARROQUIA],MATCH(D159&E159&F159,[1]!Table109[ConcateParro],0)),"")
A160: 158 | Z160: =IFERROR(IF(MATCH(D160,[1]!Table374[NAMEESTADO],0),"VALIDO"),"INVALIDO") -> INVALIDO | AA160: =IFERROR(IF(MATCH(CONCATENATE(D160,E160),[1]!Table486[ConcateMuni],0),"VALIDO"),"INVALIDO") -> INVALIDO | AB160: =IFERROR(IF(MATCH(CONCATENATE(D160,E160,F160),[1]!Table109[ConcateParro],0),"VALIDO"),"INVALIDO") -> INVALIDO | AC160: =CONCATENATE(D160,E160) | AD160: =IFERROR(INDEX([1]!Table374[PCODEESTADO],MATCH(D160,[1]!Table374[NAMEESTADO],0)),"") | AE160: =IFERROR(INDEX([1]!Table486[PCODEMUNI],MATCH(D160&E160,[1]!Table486[ConcateMuni],0)),"") | AF160: =IFERROR(INDEX([1]!Table109[PCODEPARROQUIA],MATCH(D160&E160&F160,[1]!Table109[ConcateParro],0)),"")
A161: 159 | Z161: =IFERROR(IF(MATCH(D161,[1]!Table374[NAMEESTADO],0),"VALIDO"),"INVALIDO") -> INVALIDO | AA161: =IFERROR(IF(MATCH(CONCATENATE(D161,E161),[1]!Table486[ConcateMuni],0),"VALIDO"),"INVALIDO") -> INVALIDO | AB161: =IFERROR(IF(MATCH(CONCATENATE(D161,E161,F161),[1]!Table109[ConcateParro],0),"VALIDO"),"INVALIDO") -> INVALIDO | AC161: =CONCATENATE(D161,E161) | AD161: =IFERROR(INDEX([1]!Table374[PCODEESTADO],MATCH(D161,[1]!Table374[NAMEESTADO],0)),"") | AE161: =IFERROR(INDEX([1]!Table486[PCODEMUNI],MATCH(D161&E161,[1]!Table486[ConcateMuni],0)),"") | AF161: =IFERROR(INDEX([1]!Table109[PCODEPARROQUIA],MATCH(D161&E161&F161,[1]!Table109[ConcateParro],0)),"")
A162: 160 | Z162: =IFERROR(IF(MATCH(D162,[1]!Table374[NAMEESTADO],0),"VALIDO"),"INVALIDO") -> INVALIDO | AA162: =IFERROR(IF(MATCH(CONCATENATE(D162,E162),[1]!Table486[ConcateMuni],0),"VALIDO"),"INVALIDO") -> INVALIDO | AB162: =IFERROR(IF(MATCH(CONCATENATE(D162,E162,F162),[1]!Table109[ConcateParro],0),"VALIDO"),"INVALIDO") -> INVALIDO | AC162: =CONCATENATE(D162,E162) | AD162: =IFERROR(INDEX([1]!Table374[PCODEESTADO],MATCH(D162,[1]!Table374[NAMEESTADO],0)),"") | AE162: =IFERROR(INDEX([1]!Table486[PCODEMUNI],MATCH(D162&E162,[1]!Table486[ConcateMuni],0)),"") | AF162: =IFERROR(INDEX([1]!Table109[PCODEPARROQUIA],MATCH(D162&E162&F162,[1]!Table109[ConcateParro],0)),"")
... A1001: 999 | Z1001: =IFERROR(IF(MATCH(D1001,[1]!Table374[NAMEESTADO],0),"VALIDO"),"INVALIDO") -> INVALIDO | AA1001: =IFERROR(IF(MATCH(CONCATENATE(D1001,E1001),[1]!Table486[ConcateMuni],0),"VALIDO"),"INVALIDO") -> INVALIDO | AB1001: =IFERROR(IF(MATCH(CONCATENATE(D1001,E1001,F1001),[1]!Table109[ConcateParro],0),"VALIDO"),"INVALIDO") -> INVALIDO | AC1001: =CONCATENATE(D1001,E1001) | AD1001: =IFERROR(INDEX([1]!Table374[PCODEESTADO],MATCH(D1001,[1]!Table374[NAMEESTADO],0)),"") | AE1001: =IFERROR(INDEX([1]!Table486[PCODEMUNI],MATCH(D1001&E1001,[1]!Table486[ConcateMuni],0)),"") | AF1001: =IFERROR(INDEX([1]!Table109[PCODEPARROQUIA],MATCH(D1001&E1001&F1001,[1]!Table109[ConcateParro],0)),"")

Sheet Validación Actividades
A1: Actividad | B1: Detalle del Beneficiario | C1: Agua_Higiene_Saneamiento_WASH | D1: Cambio_Comportamiento_Bienestar_Social_CCBS | E1: Rendicion_De_Cuentas_AAP | F1: Prevencion_Explotación_Abuso_Sexual_PEAS | G1: Transferencias directas (CASH) | H1: Racion de comida (Plato servido) | I1: Examenes de laboratorio | J1: Capacitacion en Salud | K1: Kit de Higiene Individual | L1: Filtro artesanal | M1: Bolsas ecologicas con Logo Caritas | N1: Kit de alimentos (Bolsas complentarias) | O1: Kit de Bioseguridad | P1: Kit obstétrico | Q1: Kit Medicina vivero | R1: Indicar en Observaciones | S1: Movilidad | T1: Alianzas | U1: Sala_Situacional | V1: Gestión_y_Reduccción_de_Riegos_de_Desastres | W1: Medios_de_Vida | X1: DIOCESIS
A2: Agua_Higiene_Saneamiento_WASH | B2: Voluntarios/Promotores de Cáritas | C2: Capacitaciones_talleres_sensibilizaciones | D2: Entrega de Guía de 12 pasos | E2: Asambleas para la toma de desiciones | F2: Entrega de flyer o volantes | G2: Entrega de Tarjeta TENGO | H2: Otro… Indicar en Observaciones | I2: RX | J2: Capacitacion en Nutrición (Lactancia materna, alimentación de niños, preparación de alimentos, etc) | K2: Kit de Higiene Familiar | L2: Pastillas purificadoras | M2: Franelas Caritas | N2: Super Alimento | O2: Tapaboca Niños | P2: Kit de embarazada | Q2: Kit de Lamparatomia | S2: Casas de paso | T2: Describir en observaciones caraterísticas de la alianza | U2: Describir en observaciones resultados de la sala situacional | V2: Capacitaciones | W2: Capacitaciones | X2: ACARIGUA
A3: Cambio_Comportamiento_Bienestar_Social_CCBS | B3: Beneficiarios de las comunidades | C3: Jabones | D3: Disfución o sensibilización en mensajes claves (presencial) | E3: Socialización del proyecto | F3: Entrega de Afiches | G3: Otro… Indicar en Observaciones | I3: Medicamento | J3: Capacitacion en Contexto Covid-19 | K3: Kit de Higiene Femenino | L3: Kit de Hidratacion | M3: Gorras con Logo Caritas | N3: Otro… Indicar en Observaciones | O3: Tapaboca de Tela (Caritas) | P3: Kit de Toallas sanitarias | Q3: Insumos Quirurgico | S3: Otro… Indicar en Observaciones | V3: Elaboración de Planes Comunitarios | W3: Entrega de Capital e insumos | X3: ARAURE
A4: Rendicion_De_Cuentas_AAP | B4: Personas con criterio de vulnerabilidad alta | C4: Pastillas potabilizadoras | D4: Disfución ONLINE de mensajes Claves | E4: Opiniones, reclamos, sugerencias y quejas recibidas (buzones) | F4: Entrega de calcomanías | I4: Otro… Indicar en Observaciones | J4: Capacitacion en Atención Psicosocial | K4: Kit de Higiene Recien Nacido | L4: Botellón de agua / dispensador | M4: Chalecos con Logo Caritas | O4: Gel Antibacterial | P4: Otro… Indicar en Observaciones | Q4: Kit Covid-19 Medicinas | V4: Formación de | W4: Desarrollo de proyectos productivos | X4: BARCELONA
A5: Prevencion_Explotación_Abuso_Sexual_PEAS | B5: Personas dejadas atrás (Motivo Migración) | C5: Filtro artesanal | D5: "Grupo de Apoyo de Madres" | E5: Otro… Indicar en Observaciones | F5: Otro canal de disfución…indicar en observaciones | J5: Capacitacion en Caritas Parroquial | K5: Kit de Higiene Migrante | L5: Jabones | M5: Chalecos con Logo Caritas (Voluntarios) | O5: Alcohol | Q5: Otro… Indicar en Observaciones | V5: Otro… Indicar en Observaciones | W5: Otro… Indicar en Observaciones | X5: BARINAS
A6: Transferencias_Monetarias | B6: Migrantes | C6: Kit de Hidratacion | D6: Otro… Indicar en Observaciones | J6: Capacitacion en Protocolos SAMAN | K6: Kit de Higiene Centro De Alojamiento | L6: Otro… Indicar en Observaciones | O6: Dispensador | X6: BARQUISIMETO
A7: Ollas_Comunitarias | B7: Beneficiarios 3era edad | C7: Botellón de agua / dispensador | J7: Capacitacion en Movilidad Humana | K7: Kit de Higiene Hábitat | O7: Otro… Indicar en Observaciones | X7: CABIMAS
A8: Otras_Capacitaciones_Talleres_Sensibilizaciones | B8: Beneficiarios con discapacidad | C8: Kits de Higiene familiar (GAM) | J8: Capacitacion en Valores | K8: Kit domestico (Cepillo/tobo) | X8: CALABOZO
A9: Entrega_Material_Informativo_Formativo | B9: Beneficiarios de comedores | C9: Otro… Indicar en Observaciones | J9: Capacitacion en Temas claves | K9: Kit de hogar en emergencia (Sabana/Colchoneta) | X9: CARACAS
A10: Fondo_Solidario | B10: Madres de Niños SAMAN | J10: Capacitacion en Salvaguardia | K10: Otro… Indicar en Observaciones | X10: CARONI
A11: Gestión_y_Reduccción_de_Riegos_de_Desastres | B11: Familias de los Niños en Vivero | J11: Capacitacion en Violencia basada en genero | X11: CARORA
A12: Kit_e_insumos_Higiene | B12: Niños en Vivero | J12: Capacitacion en Derechos Humanos | X12: CARUPANO
A13: Kit_e_Insumos_Visibilidad_Caritas | B13: Embarazadas en Vivero | J13: Capacitacion en Trata de personas | X13: CIUDAD BOLIVAR
A14: Kit_e_Insumos_Alimentos | B14: Escolares | J14: Capacitación en Presupuesto Familiar y Mercados Inteligentes | X14: CIUDAD GUAYANA
A15: Kit_e_Insumos_Bioseguridad | B15: Otro… Indicar en Observaciones | J15: Capacitación en Prevención del Embarazo en Adolescentes | X15: CORO
A16: Kit_e_Insumos_Mujeres | J16: Capacitación en Gestión de la Información (Monitoreo y Seguimiento) | X16: CUMANA
A17: Kit_e_Insumos_Salud | J17: Capacitación en Gestión de Riesgo de Desastres | X17: EL TIGRE
A18: Medios_de_Vida | J18: Capacitación en Servicios de alimentacion (Comedores) | X18: EL VIGIA
A19: Movilidad | J19: Otro… Indicar en Observaciones | X19: GUANARE
A20: Alianzas | X20: GUARENAS
A21: Sala_Situacional | X21: GUASDUALITO
A22: Otro…Indicar_en_Observaciones | X22: LA GUAIRA
X23: LOS TEQUES
X24: MACHIQUES
X25: MARACAIBO II
X26: MARACAIBO I
X27: MARACAY
X28: MARGARITA
X29: MATURIN
X30: MERIDA
X31: PETARE
X32: PUERTO AYACUCHO
X33: PUERTO CABELLO
X34: PUNTO FIJO
... X42: VALLE DE LA PASCUA

Sheet LISTAS DE VALIDACION
A1: N° | B1: DIOCESIS | C1: ESTADO | D1: MUNICIPIO | E1: PARROQUIA CIVIL / COMUNIDAD | F1: PARROQUIA ECLESIAL | G1: MES | H1: AÑO | I1: CENTRO | J1: GRUPO ETNICO | K1: EDAD (del acompañante del niño para ese dia de la atención) | L1: PARENTEZCO CON EL NIÑO O NIÑA | M1: TIPO DE INGRESO | N1: N° Control | O1: N° de Historia o Código del niño | P1: Nombres del niño o niña | Q1: Apellidos del niño o niña | R1: Sexo | S1: Fecha de Nacimiento dd/mm/aaaa | T1: Fecha de valoración dd/mm/aaaa | V1: Edad (Años y Meses) | W1: Rango de Edad | X1: ¿Consume Leche materna? | Y1: Indique el numero de veces que consumio el dia de ayer | Z1: Usa TETERO | AA1: Otros alimentos sólidos | AB1: El Agua para consumo: ¿es hervida? | AC1: El Agua para consumo: Filtrada o Clorada | AD1: ¿Purifican el agua para el comsumo? | AE1: Enferm. última sem: ¿Gripe o Tos? | AF1: Enferm. última sem: ¿Fiebre? | AG1: Enferm. última sem: ¿Diarrea? | AH1: Enferm. última sem: ¿Vómito? | AI1: Enferm. última sem: ¿Deshidratado? | AJ1: Enferm. última sem: ¿Paludismo? | AK1: ¿Tiene condición de discapacidad? | AL1: En caso afirmativo indique: ¿Cúal? | AM1: Edema Si, No | AN1: Hemoglobina (g/dL) | AO1: TALLA (cm) | AP1: PESO (kg) | AQ1: C. BRAZO (cm) | AR1: Z-Score (ZPT) | AS1: Estado Nutricional | AT1: Desparasitación | AU1: Tratamiento suministrado Según Protocolo Cáritas | AV1: Cantidad Suministrada | AW1: FECHA INICIO DE VIVERO | AX1: FECHA SALIDA DE VIVERO | AY1: Z-Score (ZPT) ENTRADA | AZ1: Z-Score (ZPT) SALIDA | BA1: SAMANAS DE DURACION EN VIVERO (1,2,3,4,5,6,7,8) | BB1: SITUACÍON A LA SALIDA | BC1: REFERIDO S/N | BD1: Observaciones | BE1: CODIDO DE DIOCESIS | BG1: Indicar si el niño es Beneficiario de otro Proyecto TENGO
D2: SELECCIONAR | E2: SELECCIONAR | F2: SELECCIONAR | G2: ENERO | H2: 2019 | I2: Formula | J2: INDÍGENA | K2: Menos de 17 años | L2: MADRE | M2: DIAGNOSTICO INICIAL | N2: 0 | O2: DIOCESIS+N°+FECHA DE NACIMIENTO | R2: FEMENINO | S2: DD/MM/AAAA | T2: DD/MM/AAAA | V2: Formula | W2: 0 - 6 meses | X2: SI | Y2: 0 | Z2: SI | AA2: SI | AB2: SI | AC2: SI | AD2: SI | AE2: SI | AF2: SI | AG2: SI | AH2: SI | AI2: SI | AJ2: SI | AK2: SI | AL2: FISICA | AM2: SI | AO2: Numero ( 0 / 130) | AP2: Numero ( 0 / 50) | AQ2: Numero ( 0 / 30) | AR2: 3 | AS2: Normal | AT2: SI | AU2: Suplementación con micronutrientes (Vitaminas) | AV2: DD/MM/AAAA | AW2: DD/MM/AAAA | AX2: 0 | AY2: 1 | AZ2: 1 | BA2: RECUPERADO | BB2: SI | BD2: Formula | BG2: SI
G3: FEBRERO | H3: 2020 | J3: AFRODESCENDIENTE | K3: Entre 18 - 49 años | L3: PADRE | M3: MONITOREO | N3: 1 | R3: MASCULINO | W3: 7 - 23 meses | X3: NO | Y3: 1 | Z3: NO | AA3: NO | AB3: NO | AC3: NO | AD3: NO | AE3: NO | AF3: NO | AG3: NO | AH3: NO | AI3: NO | AJ3: NO | AK3: NO | AL3: SENSORIAL | AM3: NO | AR3: 2 | AS3: Alerta | AT3: NO | AU3: Plumply DOZ- sobre Amarillo (6 a 23 meses) | AX3: -1 | AY3: 0 | AZ3: 2 | BA3: NO RECUPERADO | BB3: NO | BG3: NO
G4: MARZO | H4: 2021 | J4: MESTIZO | K4: Entre 50 - 65 años | L4: ABUELA | M4: SALIDA DE VIVERO | N4: 2 | W4: 24- 59 meses | X4: SD | Y4: 2 | Z4: SD | AA4: SD | AB4: SD | AC4: SD | AD4: SD | AE4: SD | AF4: SD | AG4: SD | AH4: SD | AI4: SD | AJ4: SD | AK4: SD | AL4: INTELECTUAL | AM4: SD | AR4: 1 | AS4: Riesgo | AT4: SD | AU4: Plumply NUT- sobre Rojo (DAM-Moderada) | AX4: -2 | AY4: -1 | AZ4: 3 | BA4: ABANDONO PROGRAMA | BB4: SD | BG4: NS/NR
G5: ABRIL | H5: 2022 | J5: SD | K5: Mas de 65 años | L5: ABUELO | M5: REINGRESO | N5: 3 | W5: 4 | Y5: 3 | AL5: PSÍQUICA | AR5: 0 | AS5: Moderado | AU5: Plumply NUT- sobre Rojo (DAS- Severa) | AX5: -3 | AY5: -2 | AZ5: 4 | BA5: FALLECIDO
G6: MAYO | L6: HERMANA | N6: 4 | W6: 5 | Y6: 4 | AL6: MULTIPLE | AR6: -1 | AS6: Severo | AU6: Sin Tratamiento | AY6: -3 | AZ6: 5
G7: JUNIO | L7: HERMANO | N7: 5 | W7: 6 | Y7: 5 | AL7: OTROS | AR7: -2 | AZ7: 6
G8: JULIO | L8: TIA | N8: 6 | Y8: 6 | AL8: SD | AR8: -3 | AZ8: 7
G9: AGOSTO | L9: TIO | N9: 7 | Y9: 7 | AZ9: 8
G10: SEPTIEMBRE | L10: OTRO | N10: 8 | Y10: 8 | AZ10: 9
G11: OCTUBRE | N11: 9 | Y11: 9 | AZ11: 10
G12: NOVIEMBRE | N12: 10 | AZ12: 11
G13: DICIEMBRE | N13: 11 | AZ13: 12
N14: 12
A16: # | B16: FECHA DE MEDICIÓN | C16: TIPO DE INGRESO | D16: NOMBRE | E16: APELLIDO | F16: FECHA NACIMIENTO | G16: EMBARAZADA ó LACTANTE | H16: SEMANA DE GESTACIÓN | I16: EDAD | J16: EDEMA | K16: BRAZO (CM) | L16: PESO | M16: TALLA | N16: CLASIFICACIÓN NUTRICIONAL | O16: CRITERIO DE EMBARAZADA VULNERABLE | P16: DIOCESIS | Q16: ESTADO | R16: MUNICIPIO | S16: PARROQUIA CIVIL / COMUNIDAD | T16: PARROQUIA ECLESIAL | V16: MES | W16: AÑO | X16: CENTRO | Y16: TRATAMIENTO | Z16: CANTIDAD | AA16: DESPARASITADA | AB16: Situación a la Salida
B17: DD/MM/AAAA | C17: DIAGNOSTICO INICIAL | F17: DD/MM/AAAA | G17: EMBARAZADA | I17: FORMULA | J17: SI | K17: Numero ( 0 / 100) | L17: Numero ( 0 / 150) | M17: Numero ( 0 / 200) | N17: BAJO PESO | O17: MUJER AL FRENTE | P17: SELECCIONAR | Q17: SELECCIONAR | R17: SELECCIONAR | V17: LISTA DE VALIDACION | W17: LISTA DE VALIDACION | X17: FORMULA | Y17: PLUMPY MOM | AA17: SI | AB17: Recuperada
C18: MONITOREO | G18: LACTANTE | J18: NO | N18: PESO NORMAL | O18: MUJER VIUDA | Y18: TABLETAS PRENATALES | AA18: NO | AB18: Superó el Tiempo de Vivero
C19: SALIDA DE VIVERO | J19: SD | O19: AREA EN SITUACIÓN DE RIESGO DESVENTAJOSA | Y19: OTROS | AA19: NO SABE | AB19: Otro
C20: REINGRESO | O20: CON INGRESO MUY BAJO SIN ACCESO ADECUADO DE ALIMENTO | AA20: NO RESPONDE
O21: SIN RECIBIR CLAP, NI OTRA FUENTE DE INGRESO
A24: Nro | B24: FECHA DE ATENCIÓN dd/mm/aaaa | C24: ESTADO | D24: MUNICIPIO | E24: PARROQUIA | F24: COMUNIDAD | G24: NOMBRE | H24: APELLIDO | I24: FECHA DE NACIMIENTO dd/mm/aaaa | J24: RANGO DE EDAD | K24: SEXO | L24: Tipo de Desparasitante
B25: DD/MM/AAAA | J25: 2 a 5 años | K25: FEMENINO | L25: Albendazol
J26: 5 a 14 años | K26: MASCULINO | L26: Mebendazol
L27: Otro…Antihelmínticos_Antiparasitarios
A31: # | B31: FECHA | C31: TEMA DE LA CAPACITACIÓN | D31: TIPO DE PARTICIPANTE | E31: TOTAL PARTICIPANTES CAPACITADOS | F31: TOTAL FEMENINO | G31: 0-4,9 Años | H31: 5 - 17 Años | I31: 18 - 49 Años | J31: > 49 Años | K31: TOTAL MASCULINO | L31: 0-4,9 Años | M31: 5 - 17 Años | N31: 18 - 49 Años | O31: > 49 Años | P31: DIOCESIS | Q31: ESTADO | R31: MUNICIPIO | S31: PARROQUIA CIVIL / COMUNIDAD | T31: PARROQUIA ECLESIAL | V31: MES | W31: AÑO | X31: CENTRO | Y31: Observaciones
A32: 1 | C32: Salud | D32: Voluntarios/Promotores de Cáritas | E32: se auto-llena | F32: se auto-llena | K32: se auto-llena | X32: =P32&" - "&T32 -> - | Y32: =Q32&" - "&U32 -> -
A33: 2 | C33: Nutrición | D33: Beneficiarios de las Comunidades | E33: se auto-llena | F33: se auto-llena | K33: se auto-llena | X33: =T33&" - "&P33 -> - | Y33: =U33&" - "&Q33 -> -
C34: Agua segura - WASH | D34: Madres de Niños SAMAN
C35: Contexto Covid-19 | D35: Otros
C36: Valores
C37: Caritas Parroquial
C38: Protocolos SAMAN
C39: Movilidad Humana
C40: Atención Psicosocial
C41: Derechos Humanos
C42: Temas claves
C43: Otro… Indicar en Observaciones el tema
A44: # | B44: FECHA | C44: INSUMO ENTREGADO A BENEFICIADOS | D44: Tipo de Beneficiario | E44: NOMBRE Y APELLIDO Beneficiario que recibe | F44: Sexo | G44: EDAD | H44: Nº Personas en la familia | I44: PARROQUIA ECLESIAL CENTINELA | J44: DIOCESIS | K44: ESTADO | L44: MUNICIPIO | M44: MES | N44: AÑO | O44: CENTRO
A45: 1 | C45: KIT DE HIGIENE | D45: Niños en Vivero | F45: FEMENINO | O45: =I45&" - "&J45 -> -
A46: =A45+1 -> 2 | C46: FILTRO ARTESANAL | D46: Embarazadas en Vivero | F46: MASCULINO | O46: =I46&" - "&J46 -> -
A47: =A46+1 -> 3 | C47: PASTILLAS PURIFICADORAS | D47: Personas con criterio de vulnerabilidad | O47: =I47&" - "&J47 -> -
A48: =A47+1 -> 4 | C48: KIT DE ALIMENTOS (SAMAN) | D48: Voluntarios/Promotores de Cáritas | O48: =I48&" - "&J48 -> -
A49: =A48+1 -> 5 | C49: KIT DE ALIMENTOS (GESTO SOLIDARIO) | D49: Dejados atras | O49: =I49&" - "&J49 -> -
C50: KIT OBSTETRICO | D50: Migrantes
C51: KIT DE EMBARAZADA
C52: KIT MEDICINA VIVERO
C53: FONDO SOLIDARIO
C54: KIT COVID-19 proteccion al Personal
C55: KIT COVID-19 proteccion a Comunidades
C56: KIT COVID-19 Higiene domestico (cloro, desifectante)
C57: KIT COVID-19 Medicinas
C58: KIT COCINA
C59: KIT FAMILIAR (COLCHONETA)
C60: BOTELLON / DISPENSADOR
C61: SABANAS
C62: COLCHONETAS
C63: KIT DOMESTICO ((CEPILLO/TOBO)
A66: AÑO | B66: MES | C66: DIOCESIS | D66: 1-a | E66: 1-b | F66: 1-c | G66: 1-d | H66: 1-e | I66: 1-f | J66: 1-g | K66: 1-h | L66: 1-i | M66: 1-j | N66: 1-k | O66: 2-a Menores de 12 años | P66: 3-a ¿Cuántos NIÑOS? | Q66: ENFERMEDAD | R66: 2-b ADULTOS | S66: 3-b ¿Cuántos ADULTOS? | T66: ENFERMEDAD | U66: 5. ¿Frecuencia? | V66: 18- A | W66: 18- B | X66: 18- C | Y66: 18- D | Z66: 18- E | AA66: 18- F | AB66: 18- G | AC66: 18- H | AD66: 18- I | AE66: 18- J | AF66: 18- K | AG66: 18- L | AH66: 19 | AI66: 20 | AJ66: 21 | AK66: ¿Cuál? | AL66: 22 | AM66: ¿Cuál? | AN66: 23 | AO66: 24 | AP66: ¿Cuál es el motivo? | AQ66: 25 | AR66: ¿Qué Nacionalidad? | AS66: 26 | AT66: ¿Cual? | AU66: 27 | AV66: ¿Cuál es el motivo? | AW66: Especifuque | AX66: 28 | AY66: ¿Cuánto? | AZ66: ¿Cuál metodo? | BA66: sirve para
A67: 2022 | B67: ENERO | C67: BARCELONA | D67: NO | E67: NO | F67: NO | G67: NO | H67: NO | I67: NO | J67: NO | K67: NO | L67: NO | M67: NO | N67: NO | O67: SI | R67: SI | U67: 1. Nunca | V67: SI | W67: SI | X67: SI | Y67: SI | Z67: SI | AA67: SI | AB67: SI | AC67: SI | AD67: SI | AE67: SI | AF67: SI | AG67: SI | AH67: 1. Toma en casa | AI67: 1. Continua, Todos los dias | AJ67: 1. Botellon | AL67: 1. Sanitario Conectado a una red municipal | AN67: 1. Jabon y champú personal | AO67: SI | AP67: 1. En busqueda de mejoras economicas | AQ67: SI | AS67: SI | AT67: 1. Han tramitado su Proceso de Regularización | AU67: SI | AV67: 1. Buscando mejorar las condiciones de vida | AX67: SI | BA67: a. Comprar alimentos del mes
A68: 2023 | B68: FEBRERO | C68: BARINAS | D68: A VECES | E68: A VECES | F68: A VECES | G68: A VECES | H68: A VECES | I68: A VECES | J68: A VECES | K68: A VECES | L68: A VECES | M68: A VECES | N68: A VECES | O68: NO | R68: NO | U68: 2. Casi nunca | V68: NO | W68: NO | X68: NO | Y68: NO | Z68: NO | AA68: NO | AB68: NO | AC68: NO | AD68: NO | AE68: NO | AF68: NO | AG68: NO | AH68: 2. Toma de agua en otro lugar | AI68: 2. Todos los dias, pocas horas | AJ68: 2. Filtrada | AL68: 2. Letrina con pozo séptico | AN68: 2. Jabon de ropa | AO68: NO | AP68: 2. Protegerse de la violencia y alta delincuencia | AQ68: NO | AS68: NO | AT68: 2. Han solicitado refugio | AU68: NO | AV68: 2. Consiguió trabajo en esa ciudad. | AX68: NO | BA68: b. Comprar algunos alimentos
A69: 2022 | B69: MARZO | C69: BARQUISIMETO | D69: MUCHO | E69: MUCHO | F69: MUCHO | G69: MUCHO | H69: MUCHO | I69: MUCHO | J69: MUCHO | K69: MUCHO | L69: MUCHO | M69: MUCHO | N69: MUCHO | O69: NS/NR | R69: NS/NR | U69: 3. Con Frecuencia | V69: NS/NR | W69: NS/NR | X69: NS/NR | Y69: NS/NR | Z69: NS/NR | AA69: NS/NR | AB69: NS/NR | AC69: NS/NR | AD69: NS/NR | AE69: NS/NR | AF69: NS/NR | AG69: NS/NR | AH69: 3. Otro | AI69: 3. No tuvimos agua | AJ69: 3. Clorada | AL69: 3. Letrina directa a tierra o quebrada | AN69: 3. Cloro | AO69: NS/NR | AP69: 3. las dos anteriores | AQ69: NS/NR | AT69: 3. Ninguna de las anteriores | AU69: NS/NR | AV69: 3. Atender mejor u problema de salud | AX69: NS/NR | BA69: c. Comprar las medicinas
B70: ABRIL | C70: CABIMAS | D70: SIEMPRE | E70: SIEMPRE | F70: SIEMPRE | G70: SIEMPRE | H70: SIEMPRE | I70: SIEMPRE | J70: SIEMPRE | K70: SIEMPRE | L70: SIEMPRE | M70: SIEMPRE | N70: SIEMPRE | U70: 4. Casi siempre | AI70: 4. Tuvimos agua menos de 3 dias | AJ70: 4. Filtrada y Clorada | AL70: 4. No tenemos sanitario | AN70: 4. Pasta dental | AP70: 4. Motivos personales no identificadas | AT70: 4. No responde | AV70: 4. Para protegerse de la violencia o la delincuencia | BA70: d. Comprar algunas medicinas
B71: MAYO | C71: CALABOZO | U71: 5. Siempre | AJ71: 5. La tomamos directa del tubo sin tratar | AL71: 5. Otro | AN71: 5. Definfectante para la casa | AV71: 5. Otra | BA71: e. Comprar los alimentos y medicinas
B72: JUNIO | C72: CARACAS | AJ72: 6. Otro | BA72: f. Ayudar con los estudios a los niños, niñas y adolescentes
B73: JULIO | C73: CARONI | BA73: g. Mejorar la calidad de vida
B74: AGOSTO | C74: CARUPANO
B75: SEPTIEMBRE | C75: CIUDAD GUAYANA
B76: OCTUBRE | C76: CIUDAD BOLIVAR
B77: NOVIEMBRE | C77: CORO
B78: DICIEMBRE | C78: CUMANA
C79: EL TIGRE
C80: EL VIGIA
C81: GUANARE
C82: GUARENAS
C83: GUASDUALITO
C84: LA GUAIRA
C85: LOS TEQUES
C86: MACHIQUES
C87: MARACAIBO
C88: MARACAY
C89: MARGARITA
C90: MATURIN
... C101: VALLE DE LA PASCUA
A102: FECHA DE ENTREGA dd/mm/aaaa | B102: SEXO del paciente | D102: RANGO DE EDAD del paciente | E102: PARENTEZCO Con el paciente principal | F102: CATEGORIA de la medicina entregada | G102: DETALLE de la medicina entregada | H102: CANTIDAD ENTREGA DOSIFICADA | I102: DIOCESIS | J102: ESTADO | K102: MUNICIPIO | L102: PARROQUIA CIVIL / COMUNIDAD | M102: PARROQUIA ECLESIAL | N102: MES | O102: AÑO
A103: DD/MM/AAAA | B103: FEMENINO | C103: EDAD del paciente | D103: Entre 00 - 12 años | E103: Ella/El mismo | I103: MADRE | K103: SELECCIONAR | L103: SELECCIONAR | M103: SELECCIONAR | N103: ENERO | O103: 2019
B104: MASCULINO | D104: Entre 13 - 17 años | E104: Madre | I104: PADRE | N104: FEBRERO | O104: 2020
D105: Entre 18 - 49 años | E105: Padre | I105: ABUELA | N105: MARZO
D106: Mas de 50 años | E106: Abuela | I106: ABUELO | N106: ABRIL
E107: Abuelo | I107: HERMANA | N107: MAYO
E108: Hijo | I108: HERMANO | N108: JUNIO
E109: Hija | I109: TIA | N109: JULIO
E110: Otro | I110: TIO | N110: AGOSTO
I111: OTRO | N111: SEPTIEMBRE
N112: OCTUBRE
N113: NOVIEMBRE
N114: DICIEMBRE
A115: # | B115: TIPO DE CONSULTA | D115: NOMBRE | E115: APELLIDO | F115: SEXO | G115: EDAD | H115: EDAD | I115: CODIGO | J115: MOTIVO #1 DIAGNOSTICO DE LA CONSULTA | K115: CATEGORIA | L115: Observacion/ Detalles de la consulta #1 | M115: CODIGO | N115: MOTIVO #2 DIAGNOSTICO DE LA CONSULTA | O115: CATEGORIA | P115: Observacion/ Detalles de la consulta #2 | Q115: TRATAMIENTO INDICADO / REFERENCIA MEDICA | R115: Nº DE MEDICINAS ENTREGADAS POR CARITAS | S115: DIOCESIS | T115: ESTADO | V115: MUNICIPIO | W115: PARROQUIA ECLESIAL | X115: PARROQUIA CIVIL / COMUNIDAD | Y115: MES | Z115: AÑO | AA115: CENTRO | AB115: Proyecto
B116: MEDICA EN CONSULTORIO | C116: FECHA DE LA JORNADA | F116: FEMENINO | H116: Entre 0 - 1 Años
B117: MEDICA EN JORNADA ABIERTA | F117: MASCULINO | H117: Entre 2 - 4 Años
B118: PSICOLOGICA | H118: Entre 5- 11 Años
...

Sheet 5. SALUD
A1: # | B1: DIOCESIS | C1: MODALIDAD DE CONSULTA | D1: TIPO DE CONSULTA | E1: FECHA DE CONSULTA dd/mm/aaaa | F1: Sexo | G1: Edad | H1: Rango de Edad | I1: Discapacidad | J1: CODIGO | K1: MOTIVO #1 Diagnostico de la consulta | L1: CATEGORIA | M1: Observacion/ Detalles de la consulta #1 | N1: CODIGO | O1: MOTIVO #2 Diagnostico de la consulta | P1: CATEGORIA | Q1: Observacion/ Detalles de la consulta #2 | R1: ESTADO | S1: MUNICIPIO | T1: PARROQUIA CIVIL | U1: SECTOR O COMUNIDAD | V1: PROYECTO | W1: MES | X1: AÑO | Y1: CENTRO
A2: 1 | H2: =IF(G2="","",IF(G2<=1,"Entre 0-1 años",IF(G2<=4,"Entre 2-4",IF(G2<=11,"Entre 5-11",IF(G2<=19,"Entre 12-19",IF(G2<=25,"Entre 20-25",IF(G2<=59,"Entre 26-59",IF(G2<=79,"Entre 60-79","Mayor de 80")))))))) | K2: =IFERROR(VLOOKUP(J2,[5]Instrucciones!$DD$2:$DE$116,2,FALSE),"") | O2: =IFERROR(VLOOKUP(N2,[5]Instrucciones!$DD$2:$DE$116,2,FALSE),"") | P2: =IFERROR(VLOOKUP(O2,[5]Instrucciones!$DE$2:$DF$116,2,FALSE),"") | R2: =IFERROR(VLOOKUP(#REF!,adm!$C$2:$D$36,2,FALSE),"") | W2: =IF(E2="","",TEXT(E2,"MMMM")) | X2: =IF(E2="","",TEXT(E2,"YYYY")) | Y2: =B2&" - "&#REF! -> #REF!
A3: 2 | H3: =IF(G3="","",IF(G3<=1,"Entre 0-1 años",IF(G3<=4,"Entre 2-4",IF(G3<=11,"Entre 5-11",IF(G3<=19,"Entre 12-19",IF(G3<=25,"Entre 20-25",IF(G3<=59,"Entre 26-59",IF(G3<=79,"Entre 60-79","Mayor de 80")))))))) | K3: =IFERROR(VLOOKUP(J3,[5]Instrucciones!$DD$2:$DE$116,2,FALSE),"") | O3: =IFERROR(VLOOKUP(N3,[5]Instrucciones!$DD$2:$DE$116,2,FALSE),"") | P3: =IFERROR(VLOOKUP(O3,[5]Instrucciones!$DE$2:$DF$116,2,FALSE),"") | R3: =IFERROR(VLOOKUP(#REF!,adm!$C$2:$D$36,2,FALSE),"") | W3: =IF(E3="","",TEXT(E3,"MMMM")) | X3: =IF(E3="","",TEXT(E3,"YYYY")) | Y3: =B3&" - "&#REF! -> #REF!
A4: 3 | H4: =IF(G4="","",IF(G4<=1,"Entre 0-1 años",IF(G4<=4,"Entre 2-4",IF(G4<=11,"Entre 5-11",IF(G4<=19,"Entre 12-19",IF(G4<=25,"Entre 20-25",IF(G4<=59,"Entre 26-59",IF(G4<=79,"Entre 60-79","Mayor de 80")))))))) | K4: =IFERROR(VLOOKUP(J4,[5]Instrucciones!$DD$2:$DE$116,2,FALSE),"") | O4: =IFERROR(VLOOKUP(N4,[5]Instrucciones!$DD$2:$DE$116,2,FALSE),"") | P4: =IFERROR(VLOOKUP(O4,[5]Instrucciones!$DE$2:$DF$116,2,FALSE),"") | R4: =IFERROR(VLOOKUP(#REF!,adm!$C$2:$D$36,2,FALSE),"") | W4: =IF(E4="","",TEXT(E4,"MMMM")) | X4: =IF(E4="","",TEXT(E4,"YYYY")) | Y4: =B4&" - "&#REF! -> #REF!
A5: 4 | H5: =IF(G5="","",IF(G5<=1,"Entre 0-1 años",IF(G5<=4,"Entre 2-4",IF(G5<=11,"Entre 5-11",IF(G5<=19,"Entre 12-19",IF(G5<=25,"Entre 20-25",IF(G5<=59,"Entre 26-59",IF(G5<=79,"Entre 60-79","Mayor de 80")))))))) | K5: =IFERROR(VLOOKUP(J5,[5]Instrucciones!$DD$2:$DE$116,2,FALSE),"") | O5: =IFERROR(VLOOKUP(N5,[5]Instrucciones!$DD$2:$DE$116,2,FALSE),"") | P5: =IFERROR(VLOOKUP(O5,[5]Instrucciones!$DE$2:$DF$116,2,FALSE),"") | R5: =IFERROR(VLOOKUP(#REF!,adm!$C$2:$D$36,2,FALSE),"") | W5: =IF(E5="","",TEXT(E5,"MMMM")) | X5: =IF(E5="","",TEXT(E5,"YYYY")) | Y5: =B5&" - "&#REF! -> #REF!
A6: 5 | H6: =IF(G6="","",IF(G6<=1,"Entre 0-1 años",IF(G6<=4,"Entre 2-4",IF(G6<=11,"Entre 5-11",IF(G6<=19,"Entre 12-19",IF(G6<=25,"Entre 20-25",IF(G6<=59,"Entre 26-59",IF(G6<=79,"Entre 60-79","Mayor de 80")))))))) | K6: =IFERROR(VLOOKUP(J6,[5]Instrucciones!$DD$2:$DE$116,2,FALSE),"") | O6: =IFERROR(VLOOKUP(N6,[5]Instrucciones!$DD$2:$DE$116,2,FALSE),"") | P6: =IFERROR(VLOOKUP(O6,[5]Instrucciones!$DE$2:$DF$116,2,FALSE),"") | R6: =IFERROR(VLOOKUP(#REF!,adm!$C$2:$D$36,2,FALSE),"") | W6: =IF(E6="","",TEXT(E6,"MMMM")) | X6: =IF(E6="","",TEXT(E6,"YYYY")) | Y6: =B6&" - "&#REF! -> #REF!
A7: 6 | H7: =IF(G7="","",IF(G7<=1,"Entre 0-1 años",IF(G7<=4,"Entre 2-4",IF(G7<=11,"Entre 5-11",IF(G7<=19,"Entre 12-19",IF(G7<=25,"Entre 20-25",IF(G7<=59,"Entre 26-59",IF(G7<=79,"Entre 60-79","Mayor de 80")))))))) | K7: =IFERROR(VLOOKUP(J7,[5]Instrucciones!$DD$2:$DE$116,2,FALSE),"") | L7: =IFERROR(VLOOKUP(K7,[5]Instrucciones!$DE$2:$DF$116,2,FALSE),"") | O7: =IFERROR(VLOOKUP(N7,[5]Instrucciones!$DD$2:$DE$116,2,FALSE),"") | P7: =IFERROR(VLOOKUP(O7,[5]Instrucciones!$DE$2:$DF$116,2,FALSE),"") | R7: =IFERROR(VLOOKUP(#REF!,adm!$C$2:$D$36,2,FALSE),"") | W7: =IF(E7="","",TEXT(E7,"MMMM")) | X7: =IF(E7="","",TEXT(E7,"YYYY")) | Y7: =B7&" - "&#REF! -> #REF!
A8: 7 | H8: =IF(G8="","",IF(G8<=1,"Entre 0-1 años",IF(G8<=4,"Entre 2-4",IF(G8<=11,"Entre 5-11",IF(G8<=19,"Entre 12-19",IF(G8<=25,"Entre 20-25",IF(G8<=59,"Entre 26-59",IF(G8<=79,"Entre 60-79","Mayor de 80")))))))) | K8: =IFERROR(VLOOKUP(J8,[5]Instrucciones!$DD$2:$DE$116,2,FALSE),"") | L8: =IFERROR(VLOOKUP(K8,[5]Instrucciones!$DE$2:$DF$116,2,FALSE),"") | O8: =IFERROR(VLOOKUP(N8,[5]Instrucciones!$DD$2:$DE$116,2,FALSE),"") | P8: =IFERROR(VLOOKUP(O8,[5]Instrucciones!$DE$2:$DF$116,2,FALSE),"") | R8: =IFERROR(VLOOKUP(#REF!,adm!$C$2:$D$36,2,FALSE),"") | W8: =IF(E8="","",TEXT(E8,"MMMM")) | X8: =IF(E8="","",TEXT(E8,"YYYY")) | Y8: =B8&" - "&#REF! -> #REF!
A9: 8 | H9: =IF(G9="","",IF(G9<=1,"Entre 0-1 años",IF(G9<=4,"Entre 2-4",IF(G9<=11,"Entre 5-11",IF(G9<=19,"Entre 12-19",IF(G9<=25,"Entre 20-25",IF(G9<=59,"Entre 26-59",IF(G9<=79,"Entre 60-79","Mayor de 80")))))))) | K9: =IFERROR(VLOOKUP(J9,[5]Instrucciones!$DD$2:$DE$116,2,FALSE),"") | L9: =IFERROR(VLOOKUP(K9,[5]Instrucciones!$DE$2:$DF$116,2,FALSE),"") | O9: =IFERROR(VLOOKUP(N9,[5]Instrucciones!$DD$2:$DE$116,2,FALSE),"") | P9: =IFERROR(VLOOKUP(O9,[5]Instrucciones!$DE$2:$DF$116,2,FALSE),"") | R9: =IFERROR(VLOOKUP(#REF!,adm!$C$2:$D$36,2,FALSE),"") | W9: =IF(E9="","",TEXT(E9,"MMMM")) | X9: =IF(E9="","",TEXT(E9,"YYYY")) | Y9: =B9&" - "&#REF! -> #REF!
A10: 9 | H10: =IF(G10="","",IF(G10<=1,"Entre 0-1 años",IF(G10<=4,"Entre 2-4",IF(G10<=11,"Entre 5-11",IF(G10<=19,"Entre 12-19",IF(G10<=25,"Entre 20-25",IF(G10<=59,"Entre 26-59",IF(G10<=79,"Entre 60-79","Mayor de 80")))))))) | K10: =IFERROR(VLOOKUP(J10,[5]Instrucciones!$DD$2:$DE$116,2,FALSE),"") | L10: =IFERROR(VLOOKUP(K10,[5]Instrucciones!$DE$2:$DF$116,2,FALSE),"") | O10: =IFERROR(VLOOKUP(N10,[5]Instrucciones!$DD$2:$DE$116,2,FALSE),"") | P10: =IFERROR(VLOOKUP(O10,[5]Instrucciones!$DE$2:$DF$116,2,FALSE),"") | R10: =IFERROR(VLOOKUP(#REF!,adm!$C$2:$D$36,2,FALSE),"") | W10: =IF(E10="","",TEXT(E10,"MMMM")) | X10: =IF(E10="","",TEXT(E10,"YYYY")) | Y10: =B10&" - "&#REF! -> #REF!
A11: 10 | H11: =IF(G11="","",IF(G11<=1,"Entre 0-1 años",IF(G11<=4,"Entre 2-4",IF(G11<=11,"Entre 5-11",IF(G11<=19,"Entre 12-19",IF(G11<=25,"Entre 20-25",IF(G11<=59,"Entre 26-59",IF(G11<=79,"Entre 60-79","Mayor de 80")))))))) | K11: =IFERROR(VLOOKUP(J11,[5]Instrucciones!$DD$2:$DE$116,2,FALSE),"") | L11: =IFERROR(VLOOKUP(K11,[5]Instrucciones!$DE$2:$DF$116,2,FALSE),"") | O11: =IFERROR(VLOOKUP(N11,[5]Instrucciones!$DD$2:$DE$116,2,FALSE),"") | P11: =IFERROR(VLOOKUP(O11,[5]Instrucciones!$DE$2:$DF$116,2,FALSE),"") | R11: =IFERROR(VLOOKUP(#REF!,adm!$C$2:$D$36,2,FALSE),"") | W11: =IF(E11="","",TEXT(E11,"MMMM")) | X11: =IF(E11="","",TEXT(E11,"YYYY")) | Y11: =B11&" - "&#REF! -> #REF!
A12: 11 | H12: =IF(G12="","",IF(G12<=1,"Entre 0-1 años",IF(G12<=4,"Entre 2-4",IF(G12<=11,"Entre 5-11",IF(G12<=19,"Entre 12-19",IF(G12<=25,"Entre 20-25",IF(G12<=59,"Entre 26-59",IF(G12<=79,"Entre 60-79","Mayor de 80")))))))) | K12: =IFERROR(VLOOKUP(J12,[5]Instrucciones!$DD$2:$DE$116,2,FALSE),"") | L12: =IFERROR(VLOOKUP(K12,[5]Instrucciones!$DE$2:$DF$116,2,FALSE),"") | O12: =IFERROR(VLOOKUP(N12,[5]Instrucciones!$DD$2:$DE$116,2,FALSE),"") | P12: =IFERROR(VLOOKUP(O12,[5]Instrucciones!$DE$2:$DF$116,2,FALSE),"") | R12: =IFERROR(VLOOKUP(#REF!,adm!$C$2:$D$36,2,FALSE),"") | W12: =IF(E12="","",TEXT(E12,"MMMM")) | X12: =IF(E12="","",TEXT(E12,"YYYY")) | Y12: =B12&" - "&#REF! -> #REF!
A13: 12 | H13: =IF(G13="","",IF(G13<=1,"Entre 0-1 años",IF(G13<=4,"Entre 2-4",IF(G13<=11,"Entre 5-11",IF(G13<=19,"Entre 12-19",IF(G13<=25,"Entre 20-25",IF(G13<=59,"Entre 26-59",IF(G13<=79,"Entre 60-79","Mayor de 80")))))))) | K13: =IFERROR(VLOOKUP(J13,[5]Instrucciones!$DD$2:$DE$116,2,FALSE),"") | L13: =IFERROR(VLOOKUP(K13,[5]Instrucciones!$DE$2:$DF$116,2,FALSE),"") | O13: =IFERROR(VLOOKUP(N13,[5]Instrucciones!$DD$2:$DE$116,2,FALSE),"") | P13: =IFERROR(VLOOKUP(O13,[5]Instrucciones!$DE$2:$DF$116,2,FALSE),"") | R13: =IFERROR(VLOOKUP(#REF!,adm!$C$2:$D$36,2,FALSE),"") | W13: =IF(E13="","",TEXT(E13,"MMMM")) | X13: =IF(E13="","",TEXT(E13,"YYYY")) | Y13: =B13&" - "&#REF! -> #REF!
A14: 13 | H14: =IF(G14="","",IF(G14<=1,"Entre 0-1 años",IF(G14<=4,"Entre 2-4",IF(G14<=11,"Entre 5-11",IF(G14<=19,"Entre 12-19",IF(G14<=25,"Entre 20-25",IF(G14<=59,"Entre 26-59",IF(G14<=79,"Entre 60-79","Mayor de 80")))))))) | K14: =IFERROR(VLOOKUP(J14,[5]Instrucciones!$DD$2:$DE$116,2,FALSE),"") | L14: =IFERROR(VLOOKUP(K14,[5]Instrucciones!$DE$2:$DF$116,2,FALSE),"") | O14: =IFERROR(VLOOKUP(N14,[5]Instrucciones!$DD$2:$DE$116,2,FALSE),"") | P14: =IFERROR(VLOOKUP(O14,[5]Instrucciones!$DE$2:$DF$116,2,FALSE),"") | R14: =IFERROR(VLOOKUP(#REF!,adm!$C$2:$D$36,2,FALSE),"") | W14: =IF(E14="","",TEXT(E14,"MMMM")) | X14: =IF(E14="","",TEXT(E14,"YYYY")) | Y14: =B14&" - "&#REF! -> #REF!
A15: 14 | H15: =IF(G15="","",IF(G15<=1,"Entre 0-1 años",IF(G15<=4,"Entre 2-4",IF(G15<=11,"Entre 5-11",IF(G15<=19,"Entre 12-19",IF(G15<=25,"Entre 20-25",IF(G15<=59,"Entre 26-59",IF(G15<=79,"Entre 60-79","Mayor de 80")))))))) | K15: =IFERROR(VLOOKUP(J15,[5]Instrucciones!$DD$2:$DE$116,2,FALSE),"") | L15: =IFERROR(VLOOKUP(K15,[5]Instrucciones!$DE$2:$DF$116,2,FALSE),"") | O15: =IFERROR(VLOOKUP(N15,[5]Instrucciones!$DD$2:$DE$116,2,FALSE),"") | P15: =IFERROR(VLOOKUP(O15,[5]Instrucciones!$DE$2:$DF$116,2,FALSE),"") | R15: =IFERROR(VLOOKUP(#REF!,adm!$C$2:$D$36,2,FALSE),"") | W15: =IF(E15="","",TEXT(E15,"MMMM")) | X15: =IF(E15="","",TEXT(E15,"YYYY")) | Y15: =B15&" - "&#REF! -> #REF!
A16: 15 | H16: =IF(G16="","",IF(G16<=1,"Entre 0-1 años",IF(G16<=4,"Entre 2-4",IF(G16<=11,"Entre 5-11",IF(G16<=19,"Entre 12-19",IF(G16<=25,"Entre 20-25",IF(G16<=59,"Entre 26-59",IF(G16<=79,"Entre 60-79","Mayor de 80")))))))) | K16: =IFERROR(VLOOKUP(J16,[5]Instrucciones!$DD$2:$DE$116,2,FALSE),"") | L16: =IFERROR(VLOOKUP(K16,[5]Instrucciones!$DE$2:$DF$116,2,FALSE),"") | O16: =IFERROR(VLOOKUP(N16,[5]Instrucciones!$DD$2:$DE$116,2,FALSE),"") | P16: =IFERROR(VLOOKUP(O16,[5]Instrucciones!$DE$2:$DF$116,2,FALSE),"") | R16: =IFERROR(VLOOKUP(#REF!,adm!$C$2:$D$36,2,FALSE),"") | W16: =IF(E16="","",TEXT(E16,"MMMM")) | X16: =IF(E16="","",TEXT(E16,"YYYY")) | Y16: =B16&" - "&#REF! -> #REF!
A17: 16 | H17: =IF(G17="","",IF(G17<=1,"Entre 0-1 años",IF(G17<=4,"Entre 2-4",IF(G17<=11,"Entre 5-11",IF(G17<=19,"Entre 12-19",IF(G17<=25,"Entre 20-25",IF(G17<=59,"Entre 26-59",IF(G17<=79,"Entre 60-79","Mayor de 80")))))))) | K17: =IFERROR(VLOOKUP(J17,[5]Instrucciones!$DD$2:$DE$116,2,FALSE),"") | L17: =IFERROR(VLOOKUP(K17,[5]Instrucciones!$DE$2:$DF$116,2,FALSE),"") | O17: =IFERROR(VLOOKUP(N17,[5]Instrucciones!$DD$2:$DE$116,2,FALSE),"") | P17: =IFERROR(VLOOKUP(O17,[5]Instrucciones!$DE$2:$DF$116,2,FALSE),"") | R17: =IFERROR(VLOOKUP(#REF!,adm!$C$2:$D$36,2,FALSE),"") | W17: =IF(E17="","",TEXT(E17,"MMMM")) | X17: =IF(E17="","",TEXT(E17,"YYYY")) | Y17: =B17&" - "&#REF! -> #REF!
A18: 17 | H18: =IF(G18="","",IF(G18<=1,"Entre 0-1 años",IF(G18<=4,"Entre 2-4",IF(G18<=11,"Entre 5-11",IF(G18<=19,"Entre 12-19",IF(G18<=25,"Entre 20-25",IF(G18<=59,"Entre 26-59",IF(G18<=79,"Entre 60-79","Mayor de 80")))))))) | K18: =IFERROR(VLOOKUP(J18,[5]Instrucciones!$DD$2:$DE$116,2,FALSE),"") | L18: =IFERROR(VLOOKUP(K18,[5]Instrucciones!$DE$2:$DF$116,2,FALSE),"") | O18: =IFERROR(VLOOKUP(N18,[5]Instrucciones!$DD$2:$DE$116,2,FALSE),"") | P18: =IFERROR(VLOOKUP(O18,[5]Instrucciones!$DE$2:$DF$116,2,FALSE),"") | R18: =IFERROR(VLOOKUP(#REF!,adm!$C$2:$D$36,2,FALSE),"") | W18: =IF(E18="","",TEXT(E18,"MMMM")) | X18: =IF(E18="","",TEXT(E18,"YYYY")) | Y18: =B18&" - "&#REF! -> #REF!
... A820: 819 | H820: =IF(G820="","",IF(G820<=1,"Entre 0-1 años",IF(G820<=4,"Entre 2-4",IF(G820<=11,"Entre 5-11",IF(G820<=19,"Entre 12-19",IF(G820<=25,"Entre 20-25",IF(G820<=59,"Entre 26-59",IF(G820<=79,"Entre 60-79","Mayor de 80")))))))) | K820: =IFERROR(VLOOKUP(J820,[5]Instrucciones!$DD$2:$DE$116,2,FALSE),"") | L820: =IFERROR(VLOOKUP(K820,[5]Instrucciones!$DE$2:$DF$116,2,FALSE),"") | O820: =IFERROR(VLOOKUP(N820,[5]Instrucciones!$DD$2:$DE$116,2,FALSE),"") | P820: =IFERROR(VLOOKUP(O820,[5]Instrucciones!$DE$2:$DF$116,2,FALSE),"") | R820: =IFERROR(VLOOKUP(#REF!,adm!$C$2:$D$36,2,FALSE),"") | W820: =IF(E820="","",TEXT(E820,"MMMM")) | X820: =IF(E820="","",TEXT(E820,"YYYY")) | Y820: =B820&" - "&#REF! -> #REF!

Sheet 5.1 MEDICINAS
A1: DIÓCESIS | B1: FECHA DE ENTREGA dd/mm/aaaa | C1: CÉDULA de quien retira la medicina | D1: PARENTESCO con el Beneficiario final | E1: BENEFICIARIO RECURRENTE | F1: SEXO del Beneficiario final | G1: EDAD del Beneficiario final | H1: Rango de Edad | I1: Nombre y presentación de la medicina entregada | J1: CANTIDAD de unidosis | K1: CATEGORIA de la medicina entregada | L1: ESTADO | M1: MUNICIPIO | N1: PARROQUIA CIVIL | O1: COMUNIDAD O SECTOR | P1: Observaciones | Q1: MES | R1: AÑO | S1: PROYECTO
H2: =IF(G2="","",IF(G2<=1,"Entre 0-1 años",IF(G2<=4,"Entre 2-4",IF(G2<=11,"Entre 5-11",IF(G2<=19,"Entre 12-19",IF(G2<=25,"Entre 20-25",IF(G2<=59,"Entre 26-59",IF(G2<=79,"Entre 60-79","Mayor de 80")))))))) | K2: =IFERROR(VLOOKUP(I2,'CATEGORIAS MEDICINAS'!$H$1:$I$183,2,FALSE),"")
H3: =IF(G3="","",IF(G3<=1,"Entre 0-1 años",IF(G3<=4,"Entre 2-4",IF(G3<=11,"Entre 5-11",IF(G3<=19,"Entre 12-19",IF(G3<=25,"Entre 20-25",IF(G3<=59,"Entre 26-59",IF(G3<=79,"Entre 60-79","Mayor de 80")))))))) | K3: =IFERROR(VLOOKUP(I3,'CATEGORIAS MEDICINAS'!$H$1:$I$183,2,FALSE),"") | Q3: =IF(B3="","",TEXT(B3,"MMMM")) | R3: =IF(B3="","",TEXT(B3,"YYYY"))
H4: =IF(G4="","",IF(G4<=1,"Entre 0-1 años",IF(G4<=4,"Entre 2-4",IF(G4<=11,"Entre 5-11",IF(G4<=19,"Entre 12-19",IF(G4<=25,"Entre 20-25",IF(G4<=59,"Entre 26-59",IF(G4<=79,"Entre 60-79","Mayor de 80")))))))) | K4: =IFERROR(VLOOKUP(I4,'CATEGORIAS MEDICINAS'!$H$1:$I$183,2,FALSE),"") | Q4: =IF(B4="","",TEXT(B4,"MMMM")) | R4: =IF(B4="","",TEXT(B4,"YYYY"))
H5: =IF(G5="","",IF(G5<=1,"Entre 0-1 años",IF(G5<=4,"Entre 2-4",IF(G5<=11,"Entre 5-11",IF(G5<=19,"Entre 12-19",IF(G5<=25,"Entre 20-25",IF(G5<=59,"Entre 26-59",IF(G5<=79,"Entre 60-79","Mayor de 80")))))))) | K5: =IFERROR(VLOOKUP(I5,'CATEGORIAS MEDICINAS'!$H$1:$I$183,2,FALSE),"") | Q5: =IF(B5="","",TEXT(B5,"MMMM")) | R5: =IF(B5="","",TEXT(B5,"YYYY"))
H6: =IF(G6="","",IF(G6<=1,"Entre 0-1 años",IF(G6<=4,"Entre 2-4",IF(G6<=11,"Entre 5-11",IF(G6<=19,"Entre 12-19",IF(G6<=25,"Entre 20-25",IF(G6<=59,"Entre 26-59",IF(G6<=79,"Entre 60-79","Mayor de 80")))))))) | K6: =IFERROR(VLOOKUP(I6,'CATEGORIAS MEDICINAS'!$H$1:$I$183,2,FALSE),"") | Q6: =IF(B6="","",TEXT(B6,"MMMM")) | R6: =IF(B6="","",TEXT(B6,"YYYY"))
H7: =IF(G7="","",IF(G7<=1,"Entre 0-1 años",IF(G7<=4,"Entre 2-4",IF(G7<=11,"Entre 5-11",IF(G7<=19,"Entre 12-19",IF(G7<=25,"Entre 20-25",IF(G7<=59,"Entre 26-59",IF(G7<=79,"Entre 60-79","Mayor de 80")))))))) | K7: =IFERROR(VLOOKUP(I7,'CATEGORIAS MEDICINAS'!$H$1:$I$183,2,FALSE),"") | Q7: =IF(B7="","",TEXT(B7,"MMMM")) | R7: =IF(B7="","",TEXT(B7,"YYYY"))
H8: =IF(G8="","",IF(G8<=1,"Entre 0-1 años",IF(G8<=4,"Entre 2-4",IF(G8<=11,"Entre 5-11",IF(G8<=19,"Entre 12-19",IF(G8<=25,"Entre 20-25",IF(G8<=59,"Entre 26-59",IF(G8<=79,"Entre 60-79","Mayor de 80")))))))) | K8: =IFERROR(VLOOKUP(I8,'CATEGORIAS MEDICINAS'!$H$1:$I$183,2,FALSE),"") | Q8: =IF(B8="","",TEXT(B8,"MMMM")) | R8: =IF(B8="","",TEXT(B8,"YYYY"))
H9: =IF(G9="","",IF(G9<=1,"Entre 0-1 años",IF(G9<=4,"Entre 2-4",IF(G9<=11,"Entre 5-11",IF(G9<=19,"Entre 12-19",IF(G9<=25,"Entre 20-25",IF(G9<=59,"Entre 26-59",IF(G9<=79,"Entre 60-79","Mayor de 80")))))))) | K9: =IFERROR(VLOOKUP(I9,'CATEGORIAS MEDICINAS'!$H$1:$I$183,2,FALSE),"") | Q9: =IF(B9="","",TEXT(B9,"MMMM")) | R9: =IF(B9="","",TEXT(B9,"YYYY"))
H10: =IF(G10="","",IF(G10<=1,"Entre 0-1 años",IF(G10<=4,"Entre 2-4",IF(G10<=11,"Entre 5-11",IF(G10<=19,"Entre 12-19",IF(G10<=25,"Entre 20-25",IF(G10<=59,"Entre 26-59",IF(G10<=79,"Entre 60-79","Mayor de 80")))))))) | K10: =IFERROR(VLOOKUP(I10,'CATEGORIAS MEDICINAS'!$H$1:$I$183,2,FALSE),"") | Q10: =IF(B10="","",TEXT(B10,"MMMM")) | R10: =IF(B10="","",TEXT(B10,"YYYY"))
H11: =IF(G11="","",IF(G11<=1,"Entre 0-1 años",IF(G11<=4,"Entre 2-4",IF(G11<=11,"Entre 5-11",IF(G11<=19,"Entre 12-19",IF(G11<=25,"Entre 20-25",IF(G11<=59,"Entre 26-59",IF(G11<=79,"Entre 60-79","Mayor de 80")))))))) | K11: =IFERROR(VLOOKUP(I11,'CATEGORIAS MEDICINAS'!$H$1:$I$183,2,FALSE),"") | Q11: =IF(B11="","",TEXT(B11,"MMMM")) | R11: =IF(B11="","",TEXT(B11,"YYYY"))
H12: =IF(G12="","",IF(G12<=1,"Entre 0-1 años",IF(G12<=4,"Entre 2-4",IF(G12<=11,"Entre 5-11",IF(G12<=19,"Entre 12-19",IF(G12<=25,"Entre 20-25",IF(G12<=59,"Entre 26-59",IF(G12<=79,"Entre 60-79","Mayor de 80")))))))) | K12: =IFERROR(VLOOKUP(I12,'CATEGORIAS MEDICINAS'!$H$1:$I$183,2,FALSE),"") | Q12: =IF(B12="","",TEXT(B12,"MMMM")) | R12: =IF(B12="","",TEXT(B12,"YYYY"))
H13: =IF(G13="","",IF(G13<=1,"Entre 0-1 años",IF(G13<=4,"Entre 2-4",IF(G13<=11,"Entre 5-11",IF(G13<=19,"Entre 12-19",IF(G13<=25,"Entre 20-25",IF(G13<=59,"Entre 26-59",IF(G13<=79,"Entre 60-79","Mayor de 80")))))))) | K13: =IFERROR(VLOOKUP(I13,'CATEGORIAS MEDICINAS'!$H$1:$I$183,2,FALSE),"") | Q13: =IF(B13="","",TEXT(B13,"MMMM")) | R13: =IF(B13="","",TEXT(B13,"YYYY"))
H14: =IF(G14="","",IF(G14<=1,"Entre 0-1 años",IF(G14<=4,"Entre 2-4",IF(G14<=11,"Entre 5-11",IF(G14<=19,"Entre 12-19",IF(G14<=25,"Entre 20-25",IF(G14<=59,"Entre 26-59",IF(G14<=79,"Entre 60-79","Mayor de 80")))))))) | K14: =IFERROR(VLOOKUP(I14,'CATEGORIAS MEDICINAS'!$H$1:$I$183,2,FALSE),"") | Q14: =IF(B14="","",TEXT(B14,"MMMM")) | R14: =IF(B14="","",TEXT(B14,"YYYY"))
... H2565: =IF(G2565="","",IF(G2565<=1,"Entre 0-1 años",IF(G2565<=4,"Entre 2-4",IF(G2565<=11,"Entre 5-11",IF(G2565<=19,"Entre 12-19",IF(G2565<=25,"Entre 20-25",IF(G2565<=59,"Entre 26-59",IF(G2565<=79,"Entre 60-79","Mayor de 80")))))))) | K2565: =IFERROR(VLOOKUP(I2565,'CATEGORIAS MEDICINAS'!$H$1:$I$183,2,FALSE),"") | Q2565: =IF(B2565="","",TEXT(B2565,"MMMM")) | R2565: =IF(B2565="","",TEXT(B2565,"YYYY"))

Sheet 5.2 PRUEBAS O TEST
A1: N° | B1: Mes de reporte | C1: DIOCESIS | D1: ESTADO | E1: MUNICIPIO | F1: PARROQUIA CIVIL | G1: PARROQUIA ECLESIAL/ CENTRO CENTINELA | H1: SECTOR O COMUNIDAD | I1: Pruebas de VIH aplicadas | L1: Pruebas de VIH - Resultados | N1: Pruebas de Orina aplicadas | Q1: Observaciones o comentarios
B2: Mes de reporte | C2: DIOCESIS | D2: ESTADO | E2: MUNICIPIO | F2: PARROQUIA CIVIL | G2: PARROQUIA ECLESIAL/ CENTRO CENTINELA | H2: SECTOR O COMUNIDAD | I2: Niñas de 6 a 19 años | J2: Mujeres de 20 a 64 años | K2: TOTAL | L2: Positivas | M2: Negativas | N2: Niñas de 6 a 19 años | O2: Mujeres de 20 a 64 años | P2: TOTAL
A3: 1 | B3: julio | C3: CARACAS | D3: Distrito Capital | E3: Libertador | F3: Antimano | G3: San José Obrero | H3: Las Palmitas | I3: 1 | J3: 4 | K3: =SUM(I3:J3) -> 5 | L3: 1 | M3: 4 | N3: 2 | O3: 2 | P3: =SUM(N3:O3) -> 4
A4: 2 | K4: =SUM(I4:J4) -> 0 | P4: =SUM(N4:O4) -> 0
A5: 3 | K5: =SUM(I5:J5) -> 0 | P5: =SUM(N5:O5) -> 0
A6: 4 | K6: =SUM(I6:J6) -> 0 | P6: =SUM(N6:O6) -> 0
A7: 5 | K7: =SUM(I7:J7) -> 0 | P7: =SUM(N7:O7) -> 0
A8: 6 | K8: =SUM(I8:J8) -> 0 | P8: =SUM(N8:O8) -> 0
A9: 7 | K9: =SUM(I9:J9) -> 0 | P9: =SUM(N9:O9) -> 0
A10: 8 | K10: =SUM(I10:J10) -> 0 | P10: =SUM(N10:O10) -> 0
A11: 9 | K11: =SUM(I11:J11) -> 0 | P11: =SUM(N11:O11) -> 0
A12: 10 | K12: =SUM(I12:J12) -> 0 | P12: =SUM(N12:O12) -> 0
A13: 11 | K13: =SUM(I13:J13) -> 0 | P13: =SUM(N13:O13) -> 0
A14: 12 | K14: =SUM(I14:J14) -> 0 | P14: =SUM(N14:O14) -> 0
A15: 13 | K15: =SUM(I15:J15) -> 0 | P15: =SUM(N15:O15) -> 0
... A102: 100 | K102: =SUM(I102:J102) -> 0 | P102: =SUM(N102:O102) -> 0

Sheet CÓD. 4 - 4.1
A2: CÓDIGOS PARA EL LLENADO DE LA BASE DE DATOS DE SALUD Y MEDICINAS - CARITAS VENEZUELA - 2020
A4: CATEGORÍA | B4: Código | C4: Motivo de Consulta | D4: Código de la Categoria | F4: CODIGO | G4: CATEGORÍA | H4: MEDICAMENTO
A5: 0. TIPO DE CONSULTA | B5: 01 | C5: CONSULTA: ATENCIÓN DE MADRE LACTANTE / POSTNATAL (Z39: Z391) | D5: 0 | F5: 1 | G5: Anestésicos | H5: 1. Ketamina Ampollas
B6: 02 | C6: CONSULTA: CONTROL PRENATAL (Z32.- -- Z35.-) | D6: 0 | H6: 1. Lidocaína Ampollas
B7: 03 | C7: CONSULTA: TAMIZAJE Y PESQUISA ANTROPOMÉTRICA NUTRICIONAL - SAMÁN PRIMERA (Z13.2; Z13.4) | D7: 0 | H7: 1. Naloxona Ampollas
B8: 04 | C8: CONSULTA: CONTROL VIVERO SAMÁN SEGUIMIENTO (Z76.0, Z76.1, Z76.2) | D8: 0 | H8: 1. Otro…Anestésicos
B9: 05 | C9: CONSULTA: SEGUIMIENTO DE TRATAMIENTO Y/O CONVALESCENCIA TODAS LAS EDADES (Z09.-, Z54) | D9: 0
B10: 06 | C10: CONSULTAS PARA PROCEDIMIENTOS: CITOLOGÍA, EXODONCIA, VACUNACIÓN, CURA, ETC (Z40.--Z53) | D10: 0
B11: 07 | C11: SOLICITUD DE AYUDAS POR RIESGOS POTENCIALES PARA LA SALUD SOCIOECONÓMICOS Y PSICOSOCIALES: MIGRACIÓN FAMILIAR; VIOLENCIAS; INDIGENCIA (Z55–Z65; Z70.-- Z76.8) | D11: 0
B12: 08 | C12: CONSULTAS DE CONTROL DE SALUD GENERAL: NIÑOS Y ADULTOS SANOS (Z00 - Z01.-) | D12: 0 | F12: 2 | G12: Analgésicos_Antipiréticos_AINES | H12: 2. Ácido acetilsalicílico
B13: 09 | C13: CONSULTAS PARA DESPISTAJES Y EXÁMENES ESPECIALES: CA DE MAMAS, HTA, VISIÓN, DENTAL, CARDIOVASCULAR | D13: 0 | H13: 2. Diclofenac Gel
A14: I. ENFERMEDADES INFECCIOSAS Y PARASITARIAS | B14: IA1 | C14: DIARREA TODAS LAS EDADES (A08; A09) | D14: IA | H14: 2. Diclofenac Potasico
B15: IA2 | C15: AMIBIASIS, GIARDIASIS Y OTRAS PARASITOSIS POR PROTOZOARIOS (A06.- A07.1) | D15: IA | H15: 2. Diclofenac Sódico
B16: IA3 | C16: PARASITISMO INTESTINAL: HELMINTIASIS Y PLATELMINTOS (B82) | D16: IA | H16: 2. Diclofenac Sódico Ampollas
B17: IB1 | C17: TUBERCULOSIS (A15-A19) | D17: IB | H17: 2. Ibuprofeno 400 mg
B18: IC1 | C18: GONORREA, SÍFILIS, TRICOMONIASIS, VPH Y OTRAS ITS (A51-A53; A54; B20-B24, Z21) | D18: IC | H18: 2. Ibuprofeno tabs
B19: IC2 | C19: VIH (B20.---B24.-) | D19: IC | H19: 2. Ibuprofeno, Suspensión oral
B20: ID1 | C20: DIFTERIA (A36.-) | D20: ID | H20: 2. Paracetamol 100mg
B21: ID2 | C21: PAROTIDITIS INFECCIOSA (B26) | D21: ID | H21: 2. Paracetamol 500mg
B22: ID3 | C22: RUBEOLA (B06.-) | D22: ID | H22: 2. Paracetamol Ampollas
B23: ID4 | C23: SARAMPION (B05.-) | D23: ID | H23: 2. Paracetamol supositorios
B24: ID5 | C24: TOSFERINA Y SINDROME COQUELUCHOIDE (TOS CONVULSA) (A37.9.-) | D24: ID | H24: 2. Paracetamol, Suspensión oral
B25: IE1 | C25: DENGUE, CHIKUNGUNYA, ZIKA Y OTRAS TRANSMITIDAS POR VECTORES (A90; A92,0; U06) | D25: IE | H25: 2. Tramadol tabs./caps
B26: IE2 | C26: PALUDISMO (B54) | D26: IE | H26: 2. Otro… Analgésicos_Antipiréticos_AINES
B27: IG1 | C27: ESCABIOSIS (B86) | D27: IG
B28: IG2 | C28: HEPATITIS (B19.-) | D28: IG
B29: IG3 | C29: CANDIDIASIS, TIÑAS Y OTRAS MICOSIS SUPERFICIALES (B35.-,B36.-, B37.- ) | D29: IG
B30: IG4 | C30: HERPES Y OTRAS ENFERMEDADES VIRALES NO CODIFICADAS EN OTRA PARTE (B00.9; B97) | D30: IG | F30: 3 | G30: Antialérgicos | H30: 3. Prometazina
B31: IG5 | C31: PEDICULOSIS, MIASIS Y OTRAS ACARIASIS (B85–B89) | D31: IG | H31: 3. Prometazina Ampollas
B32: IG6 | C32: SINDROME VIRAL (B34.-) | D32: IG | H32: 3. Otro... Antialérgicos
B33: IG7 | C33: VARICELA Y HERPES ZÒSTER (B01.-; B02.1) | D33: IG
A34: II. ENFERMEDADES TUMORALES | B34: II | C34: NEOPLASIAS (C00-D48) | D34: II
A35: III. ENFERMEDADES DE LA SANGRE Y ORG. HEMATOPOYÉTICOS | B35: III | C35: ANEMIAS (D50.- D64: D64.9) | D35: III
A36: IV. ENFERMEDADES NUTRICIONALES, ENDOCRINAS Y METABÓLICAS | B36: IV1 | C36: DESNUTRICIÓN (E44.1; E46; Z59.4 O T73.0; E.45): TALLA BAJA, BAJO PESO, DESNUTRICIÓN LEVE Y MODERADA Y OTROS | D36: IV | F36: 4 | G36: Antiepilécticos | H36: 4. Carbamazepina
B37: IV2 | C37: DESNUTRICIÓN SEVERA EN ADULTOS (E43) | D37: IV | H37: 4. Fenitoína Sódica
B38: IV3 | C38: DIABETES MELLITUS TODAS LAS EDADES (E1. A E14.-) | D38: IV | H38: 4. Levodopa + Carbidopa
B39: IV4 | C39: HIPERCALCIURIA Y OTROS TRASTORNOS METABÓLICOS (E83.5; E88) | D39: IV | H39: 4. Otro…Antiepilécticos
B40: IV5 | C40: HIPERGLICEMIA, DISLIPIDEMIA (R73.-, E78.-) | D40: IV
B41: IV6 | C41: OBESIDAD (E66.-) | D41: IV
B42: IV7 | C42: TRASTORNOS DE LA TIROIDES Y OTRAS GLÁNDULAS ENDOCRINAS (E00-E07; E20–E35) | D42: IV
A43: V. ENFERMEDAES MENTALES | B43: V1 | C43: AUTISMO /ESPECTRO AUTISTA (F84.0) | D43: V | F43: 5 | G43: Antihelmínticos_Antiparasitarios | H43: 5. Albendazol tabs. 400 mg
B44: V2 | C44: NEUROSIS, PSICOSIS Y OTROS TRAST.MENTALES Y DEL COMPORT. (F00-F99) | D44: V | H44: 5. Albendazol tabs. masticables 200 mg
B45: V3 | C45: RETARDO DEL DESARROLLO (R62.-) | D45: V | H45: 5. Mebendazol 500 mg
B46: V4 | C46: RETRASO MENTAL (F70–F79) | D46: V | H46: 5. Mebendazol tabs. 100 mg
A47: VI. ENFERMEDADES CEREBRALES Y OTRAS NEUROLÓGICAS | B47: VI1 | C47: EPILEPSIA (G40) | D47: VI | H47: 5. Otro…Antihelmínticos_Antiparasitarios
B48: VI2 | C48: PARÁLISIS, PARKINSON Y OTROS TRASTORNOS NEUROLÓGICOS (G20.- G22.-; G80-G83; G51.0) | D48: VI
A49: VII. ENFEMEDADES DEL OJO Y SUS ANEXOS | B49: VII1 | C49: CONJUNTIVITIS (H10.-) | D49: VII
B50: VII2 | C50: DEFICIENCIA VISUAL (H54.-) | D50: VII
B51: VII3 | C51: DOLOR OCULAR, GLAUCOMA Y OTRAS ENF. DEL OJO (H00-H09,H11-H59; H57.1;) | D51: VII | F51: 6 | G51: Antibióticos_Antifúngicos_Antivirales | H51: 6. Amoxicilina 250 mg + Ácido Clavulánico 62,5 mg/5 ml para suspensión oral
A52: VIII. ENFERMEDADES DEL OÍDO Y MASTOIDES | B52: VIII1 | C52: VÉRTIGO Y OTRAS ENFERMEDADES DEL OÍDO Y MASTOIDES (H81; H92.0; H61; H68.--H95.-) | D52: VIII | H52: 6. Amoxicilina 875 mg+ acido clavulanico
B53: VIII2 | C53: OTITIS AGUDA TODAS LAS EDADES (H60.-, H62.- H65.---H68) | D53: VIII | H53: 6. Amoxicilina dispersable 10x10 250mg
A54: IX. ENFERMEDADES DEL SISTEMA CIRCULATORIO | B54: IX1 | C54: ACV Y OTRAS ENF. CEREBROVASCULARES (I60-I69) | D54: IX | H54: 6. Amoxicilina para Suspensión oral 125 mg/5 ml
B55: IX2 | C55: HIPERTENSION ARTERIAL TODAS LAS EDADES (I10, I16.-) | D55: IX | H55: 6. Amoxicilina tabs./caps. 250 mg
B56: IX3 | C56: INSUF. CARDÍACA, OTRAS ENFERMEDADES DEL CORAZÓN Y DEL SISTEMA CIRCULATORIO (I95.- I99) | D56: IX | H56: 6. Amoxicilina tabs./caps. 500 mg
B57: IX4 | C57: VARICES: HEMORROIDES, VARICOCELE, INSUF VENOSA Y OTRAS (I83.-, I85.-, I86.1, I89.-) | D57: IX | H57: 6. Ampicilina Sódica para inyectar 1g
A58: X. ENFERMEDADES DEL SISTEMA RESPIRATORIO | B58: X1 | C58: AMIGDALITIS, FARINGITIS TODAS LAS EDADES (J02; J03.-) | D58: X | H58: 6. Cefalexina caps. 250 mg
B59: X2 | C59: ASMA TODAS LAS EDADES (J45) | D59: X | H59: 6. Cefixima tabs. 200 mg
B60: X3 | C60: ASMA EN CRISIS (J45) | D60: X | H60: 6. Ceftriaxona para inyectar 1.000 mg (Substancia seca)
B61: X4 | C61: BRONQUIOLITIS AGUDA <2años(J21.-) | D61: X | H61: 6. Ceftriaxona Sódica para inyectar 1g
B62: X5 | C62: BRONQUITIS AGUDA (J20.-) | D62: X | H62: 6. Ceftriaxona Sódica para inyectar 250 mg
B63: X6 | C63: ENFISEMA, BRONQUITIS CRÓNICA Y OTRAS EBPOC (J43.-, J44.-) | D63: X | H63: 6. Ciprofloxacina tabs. 250 mg
B64: X7 | C64: SINUSITIS, ADENOIDITIS, LARINGITIS Y OTRAS ENFERMEDADES RESPIRATORIAS (J01; J32; J35.2; J05; R06.8) | D64: X | H64: 6. Ciprofloxacina tabs. 500 mg
B65: X8 | C65: NEUMONÍAS Y OTRAS IRA BAJA NOEM TODAS LAS EDADES (J12-J18; J22) | D65: X | H65: 6. Cloxacilina caps 500 mg
B66: X9 | C66: OTROS BRONCOESPASMOS (J98.01) | D66: X | H66: 6. Cloxacilina Sódica para inyección 500 mg (sustancia seca)
B67: X10 | C67: RINITIS ALERGICA (J30.1-J30.4) | D67: X | H67: 6. Cotrimoxazol en polvo para suspensión oral. 240 mg/5 ml Sulfametoxazol 200 mg, Trimetropima 40 mg/5 ml
B68: X11 | C68: RINOFARINGITIS AGUDA TODAS LAS EDADES (J00) | D68: X | H68: 6. Cotrimoxazol tabs. 480 mg
A69: XI. ENFERMEDADES DEL ESTÓMAGO, INTESTINO Y OTRAS DEL SISTEMA DIGESTIVO | B69: XI1 | C69: CONSTIPACIÓN (K59.0) | D69: XI | H69: 6. Doxicilina tabs. 100 mg
B70: XI2 | C70: DOLOR: CÓLICO HEPÁTICO Y COLELITIASIS (K80.-, K80.5) | D70: XI | H70: 6. Eritromicina etilsuccinato para suspensión oral 125 mg/5 ml
B71: XI3 | C71: GASTRITIS, ÚLCERA PÉPTICA, REFLUJO GASTROESOFÁGICO Y ACIDEZ (K27; K29.-; K21; R12) | D71: XI | H71: 6. Eritromicina tabs. 250 mg
B72: XI4 | C72: HERNIAS CAVIDAD ABDOMINAL (K40….K46.-) | D72: XI | H72: 6. Fluconazol caps. 50 mg
B73: XI5 | C73: APENDICITIS, DIVERTICULITIS, PANCREATITIS, HÍGADO GRASO Y OTRAS ENF. ESOF.,ESTOMAGO E INTESTINO (K35; K37.-; K70-K77; K85; K92) | D73: XI | H73: 6. Gentamicina 80 mg, ampollas
A74: XIA. ENFERMEDADES BUCO-DENTALES | B74: XIA1 | C74: DOLOR: DENTAL Y CARIES (K08.8; K02.-) | D74: XIA | H74: 6. Ketoconazol tabs. 200 mg
B75: XIA2 | C75: ESTOMATITIS, GINGIVITIS Y PERIODONTITIS CON O SIN ABSCESO (K12.0, K12.1; K05.0, KO5.1, K05.2) | D75: XIA | H75: 6. Miconazol 20 mg/g
B76: XIA3 | C76: MALPOSICIÓN DENTARIA, ERUPCIÓN DENTAL Y OTROS TRASTORNOS BUCODENTALES (K00–K14; K00.7; K07.3) | D76: XIA | H76: 6. Nistatina Suspensión oral 100.000 IU/ml
A77: XII. ENFERMEDADES DE LA PIEL Y TEJIDO SUBCUTÁNEO | B77: XII1 | C77: ABSCESO (L02.9) | D77: XII | H77: 6. Nistatina vaginal tabs. 100.000 IU
B78: XII2 | C78: CELULITIS Y PIODERMITIS (IMPÉTIGO) (L03; L08.0) | D78: XII | H78: 6. Nistatina vaginal tabs. 100.000 IU con aplicador
B79: XII3 | C79: DERMATITIS Y ECZEMA (L20.—L30.-) | D79: XII | H79: 6. Penicilina Benzatícina en polvo para inyección 2,4 Millones. IU (sustancia seca)
B80: XII4 | C80: URTICARIA, TRASTORNOS DE PELOS, UÑAS Y OTRAS ENFERMEDADES DE PIEL Y TEJIDO SUBCUTÀNEO(L50.-; L.00, L60.--L65.9-L75.- L80-L99): ALOPECIA, PRÚRIGO, MOLUSCO CONTAGIOSO, VITILIGO | D80: XII | H80: 6. Penicilina benzatínica Sódica 5 mega unidades (Substancia seca)
A81: XIII. ENFERMEDADES DE ARTICULACIONES, MÚSCULOS, HUESOS Y NERVIOS (SISTEMA OSTEOMUSCULAR Y TEJIDO CONJUNTIVO) | B81: XIII1 | C81: DOLOR: ARTICULAR, ARTRITIS Y ARTROSIS (M00-M14; M15.-M19.-; M25.5) | D81: XIII | H81: 6. Penicilina procaínica 3 mega unidades + Penicilina benzatínica 1 mega unidad inyección (Substancia seca)
B82: XIII2 | C82: DOLOR DE ESPALDA: LUMBALGIA, CERVICALGIA Y OTRAS DORSALGIAS POR CIÁTICA, TRASTORNOS DISCOS INTERVERTEBRALES Y OTRAS DORSOPATÌAS (M54.5; M54.10; M54.9;M51: M51.1; M54.3; M54.4; G57.0) | D82: XIII | H82: 6. Penicilina V tabs. 400.000 IU (250 mg)
B83: XIII3 | C83: DOLOR: NEURITIS / NEURALGIA (M79.2) | D83: XIII | H83: 6. Penicilina-G-Sódica para inyectar 1 mega unidad (Substancia seca)
B84: XIII4 | C84: DOLOR MUSCULAR: TORTICOLIS, OTRAS CONTRACTURAS MUSCULARES Y MIALGIAS (M62.4; M79.1) | D84: XIII | H84: 6. Trimetropin/sulfametotoxazol botellax 100 ml/suspension oral 200mg+ 40mg/5ml
B85: XIII5 | C85: OTRAS ENF. MUSCULOESQUELÈTICAS ESPECÍFICAS: BURSITIS, TENDINITIS, TÚNEL CARPIANO, OSTEOCONDRITIS, OSTEOPOROSIS (M70.-,M71.-,M75.-M77.-; M76; M81.8, M81.9; K58; M93.9) | D85: XIII | H85: 6. Otro… Antibióticos_Antifúngicos_Antivirales
A86: XIVA. ENFERMEDADES DEL RIÑÓN Y SISTEMA URINARIO | B86: XIVA1 | C86: DOLOR: CÓLICO NEFRÍTICO (N23) | D86: XIVA
B87: XIVA2 | C87: INFECCION URINARIA Y CISTITIS (N39.0; N30) | D87: XIVA
B88: XIVA3 | C88: OTRAS ENFERM. DE RIÑÓN ( NEFRO Y UROPATÍAS) (N00–N99): | D88: XIVA
A89: XIVB. ENFEMEDADES GINECOLÓGICAS | B89: XIVB1 | C89: DOLOR: DISMENORREA (N94.6) | D89: XIVB | F89: 7 | G89: Antiamebianos_Antileishmaniasis | H89: 7. Metronidazol inyección 500 mg/100 ml
B90: XIVB2 | C90: LEUCORREA NO ESPECIFICADA, ENFERMEDAD INFLAMATORIA PÉLVICA Y VAGINITIS (N70.--N74.-; N76.0; N76.1; N89.8) | D90: XIVB | H90: 7. Metronidazol tabs. 250 mg
B91: XIVB3 | C91: MENOPAUSIA (Z78.0—N95.-) | D91: XIVB | H91: 7. Metronidazol vaginal tabs. 500 mg
B92: XIVB4 | C92: MENSTRUACIÓN IRREGULAR Y HEMORR. GENITAL NO ESPEC. (N92.-; N93.9) | D92: XIVB | H92: 7. Otro… Antiamebianos_Antileishmaniasis
A93: XIVC. ENFERMEDADES DEL SISTEMA REPRODUCTOR MASCULINO | B93: XIVC | C93: HIPERPLASIA PROSTÀTICA, FIMOSIS Y OTRAS ENF. GENITALES MASCULINAS (N40—N51.-) | D93: XIVC
A94: XV. ENFERMEDADES ASOCIADAS CON EL EMBARAZO, PARTO Y PUERPERIO | B94: XV1 | C94: ECLAMPSIA, PRE-ECLAMPSIA Y OTRAS COMPLICACIONES DEL EMBARAZO (O13,O14.-,O15.-; O20.--O48.-)) | D94: XV
B95: XV2 | C95: MASTITIS Y OTROS TRAST. MAMARIOS DEL PUERPERIO (O91.-O92.-) | D95: XV
B96: XV3 | C96: OTRAS COMPLICAC. DEL EMBARAZO, PARTO Y PUERPERIO (O00–O99) (H35.-) | D96: XV | F96: 8 | G96: Antimaláricos | H96: 8. Arteméter 180 mg + Lumefantrina 1080 mg suspensión
A97: XVIII. SÍNTOMAS, SIGNOS Y HALLAZGOS ANORMALES INESPECÍFICOS | B97: XVIII1 | C97: ADENOMEGALIA, ADENITIS (R59.9, SAI) | D97: XVIII | H97: 8. Arteméter 20 mg + Lumefantrina 120 mg tabs. (Coartem ®)
B98: XVIII2 | C98: ALERGIAS / "INTOXICACIONES" (T78.4, SAI) | D98: XVIII | H98: 8. Arteméter 20 mg + Lumefantrina 120 mg tabs. dispersables (Coartem ®)
B99: XVIII3 | C99: ASTENIA (R53) | D99: XVIII | H99: 8. Arteméter inyección 80 mg/ml
B100: XVIII4 | C100: CONVULSIONES TODAS LAS EDADES (R56.-) | D100: XVIII | H100: 8. Artesiunato para inyección 60 mg/ml (con solvente)
B101: XVIII5 | C101: DESVANECIMIENTO, LIPOTIMIA, MAREO POR DESHIDRATACIÓN, HIPLOGLICEMIA U OTRAS CAUSAS (R42) | D101: XVIII | H101: 8. Artesunato 50 mg + Amodiaquina 153 mg base tabs.
B102: XVIII6 | C102: DOLOR NO ESPECIFICADO (R52.-) | D102: XVIII | H102: 8. Cloroquina 150 mg
...
